Workbook

Sheet Budget Figures
C3: FORECAST MONTHLY CASHFLOW: | U3: Goods & Sales Tax % | V3: 0.15
D6: 44287 | E6: 44317 | F6: 44348 | G6: 44378 | H6: 44409 | I6: 44440 | J6: 44470 | K6: 44501 | L6: 44531 | M6: 44562 | N6: 44593 | O6: 44621 | Q6: Year to Date
C7: DEPOSITS
C9: Sales | D9: 25000 | E9: 35000 | F9: 45000 | G9: 15000 | H9: 25000 | I9: 30000 | J9: 12500 | K9: 25000 | L9: 35000 | M9: 40000 | N9: 25000 | O9: 35800 | Q9: =SUM(D9:O9) -> 348300
C10: Tax Rebates | Q10: =SUM(D10:O10) -> 0
C11: Interest Received | Q11: =SUM(D11:O11) -> 0
C12: Capital Introduced | Q12: =SUM(D12:O12) -> 0
C13: Other | Q13: =SUM(D13:O13) -> 0
C14: Non GST Related Sales | D14: 250 | E14: 250 | F14: 250 | G14: 250 | H14: 250 | I14: 250 | J14: 250 | K14: 250 | L14: 250 | M14: 250 | N14: 250 | O14: 250 | Q14: =SUM(D14:O14) -> 3000
C16: SUBTOTAL DEPOSITS: | D16: =SUM(D9:D14) -> 25250 | E16: =SUM(E9:E14) -> 35250 | F16: =SUM(F9:F14) -> 45250 | G16: =SUM(G9:G14) -> 15250 | H16: =SUM(H9:H14) -> 25250 | I16: =SUM(I9:I14) -> 30250 | J16: =SUM(J9:J14) -> 12750 | K16: =SUM(K9:K14) -> 25250 | ... O16: =SUM(O9:O14) -> 36050 | Q16: =SUM(D16:O16) -> 351300
C18: WITHDRAWALS (Expenses)
C20: Car | D20: 500 | E20: 500 | F20: 500 | G20: 500 | H20: 500 | I20: 500 | J20: 500 | K20: 500 | L20: 500 | M20: 500 | N20: 500 | O20: 500 | Q20: =SUM(D20:O20) -> 6000
C21: Bank Fees | Q21: =SUM(D21:O21) -> 0
C22: Credit Card Charges | Q22: =SUM(D22:O22) -> 0
C23: Computer ( Hardware & Software) | Q23: =SUM(D23:O23) -> 0
C24: Entertainment | D24: 150 | E24: 150 | F24: 150 | G24: 150 | H24: 150 | I24: 150 | J24: 150 | K24: 150 | L24: 150 | M24: 150 | N24: 150 | O24: 150 | Q24: =SUM(D24:O24) -> 1800
C25: General Expenses | Q25: =SUM(D25:O25) -> 0
C26: Printing | Q26: =SUM(D26:O26) -> 0
C27: Stationary & Supplies | Q27: =SUM(D27:O27) -> 0
C28: Vehicle Leases | D28: 1000 | E28: 1000 | F28: 1000 | G28: 1000 | H28: 1000 | I28: 1000 | J28: 1000 | K28: 1000 | L28: 1000 | M28: 1000 | N28: 1000 | O28: 1000 | Q28: =SUM(D28:O28) -> 12000
C29: Telephone, Tolls & E-Mail | Q29: =SUM(D29:O29) -> 0
C30: Cell Phone | Q30: =SUM(D30:O30) -> 0
C31: Travelling & Accomodation | Q31: =SUM(D31:O31) -> 0
C32: Insurance | Q32: =SUM(D32:O32) -> 0
C33: Accounting | D33: 600 | E33: 600 | F33: 600 | G33: 600 | H33: 600 | I33: 600 | J33: 600 | K33: 600 | L33: 600 | M33: 600 | N33: 600 | O33: 600 | Q33: =SUM(D33:O33) -> 7200
C34: Provision for Taxation | Q34: =SUM(D34:O34) -> 0
C35: Fringe Benefit Tax | Q35: =SUM(D35:O35) -> 0
C36: Legal | Q36: =SUM(D36:O36) -> 0
C37: Low Cost Assets | Q37: =SUM(D37:O37) -> 0
C38: Plant & Equipment | Q38: =SUM(D38:O38) -> 0
C39: Drawings | Q39: =SUM(D39:O39) -> 0
C40: Principle Loan Repayments | D40: 500 | E40: 500 | F40: 500 | G40: 500 | H40: 500 | I40: 500 | J40: 500 | K40: 500 | L40: 500 | M40: 500 | N40: 500 | O40: 500 | Q40: =SUM(D40:O40) -> 6000
C41: Other 1 | Q41: =SUM(D41:O41) -> 0
C42: Other 2 | Q42: =SUM(D42:O42) -> 0
C43: Other 3 | Q43: =SUM(D43:O43) -> 0
C44: Other 4 | Q44: =SUM(D44:O44) -> 0
C45: Other 5 | Q45: =SUM(D45:O45) -> 0
C46: Other 6 | Q46: =SUM(D46:O46) -> 0
C48: NON GST RELATED WITHDRAWALS
C50: Wages | D50: 14000 | E50: 14000 | F50: 14000 | G50: 14000 | H50: 14000 | I50: 14000 | J50: 14000 | K50: 14000 | L50: 14000 | M50: 14000 | N50: 14000 | O50: 14000 | Q50: =SUM(D50:O50) -> 168000
C51: Interest Only Loan Payments | D51: 750 | E51: 750 | F51: 750 | G51: 750 | H51: 750 | I51: 750 | J51: 750 | K51: 750 | L51: 750 | M51: 750 | N51: 750 | O51: 750 | Q51: =SUM(D51:O51) -> 9000
C52: Other 1 | Q52: =SUM(D52:O52) -> 0
C53: Other 2 | Q53: =SUM(D53:O53) -> 0
C54: Other 3 | Q54: =SUM(D54:O54) -> 0
C56: SUBTOTAL WITHDRAWALS: | D56: =SUM(D20:D54) -> 17500 | E56: =SUM(E20:E54) -> 17500 | F56: =SUM(F20:F54) -> 17500 | G56: =SUM(G20:G54) -> 17500 | H56: =SUM(H20:H54) -> 17500 | I56: =SUM(I20:I54) -> 17500 | J56: =SUM(J20:J54) -> 17500 | K56: =SUM(K20:K54) -> 17500 | ... O56: =SUM(O20:O54) -> 17500 | Q56: =SUM(D56:O56) -> 210000
C58: GST Related Deposits | D58: =D9+D11+D13 -> 25000 | E58: =E9+E11+E13 -> 35000 | F58: =F9+F11+F13 -> 45000 | G58: =G9+G11+G13 -> 15000 | H58: =H9+H11+H13 -> 25000 | I58: =I9+I11+I13 -> 30000 | J58: =J9+J11+J13 -> 12500 | K58: =K9+K11+K13 -> 25000 | ... O58: =O9+O11+O13 -> 35800
C59: GST Related Withdrawals | D59: =sum(D20:D46) -> 2750 | E59: =sum(E20:E46) -> 2750 | F59: =sum(F20:F46) -> 2750 | G59: =sum(G20:G46) -> 2750 | H59: =sum(H20:H46) -> 2750 | I59: =sum(I20:I46) -> 2750 | J59: =sum(J20:J46) -> 2750 | K59: =sum(K20:K46) -> 2750 | ... O59: =sum(O20:O46) -> 2750
C61: GST MOVEMENTS
C62: Input (Expense Related) | D62: =D59-(D59/(1+$V$3)) -> 358.69565 | E62: =E59-(E59/(1+$V$3)) -> 358.69565 | F62: =F59-(F59/(1+$V$3)) -> 358.69565 | G62: =G59-(G59/(1+$V$3)) -> 358.69565 | H62: =H59-(H59/(1+$V$3)) -> 358.69565 | I62: =I59-(I59/(1+$V$3)) -> 358.69565 | J62: =J59-(J59/(1+$V$3)) -> 358.69565 | K62: =K59-(K59/(1+$V$3)) -> 358.69565 | ... O62: =O59-(O59/(1+$V$3)) -> 358.69565 | Q62: =SUM(D62:O62) -> 4304.3478
C63: Output (Income Related) | D63: =D58-(D58/(1+$V$3)) -> 3260.8696 | E63: =E58-(E58/(1+$V$3)) -> 4565.2174 | F63: =F58-(F58/(1+$V$3)) -> 5869.5652 | G63: =G58-(G58/(1+$V$3)) -> 1956.5217 | H63: =H58-(H58/(1+$V$3)) -> 3260.8696 | I63: =I58-(I58/(1+$V$3)) -> 3913.0435 | J63: =J58-(J58/(1+$V$3)) -> 1630.4348 | K63: =K58-(K58/(1+$V$3)) -> 3260.8696 | ... O63: =O58-(O58/(1+$V$3)) -> 4669.5652 | Q63: =SUM(D63:O63) -> 45430.435
C64: NET CASH RELATED TO GST | D64: =D62-D63 -> -2902.1739 | E64: =E62-E63 -> -4206.5217 | F64: =F62-F63 -> -5510.8696 | G64: =G62-G63 -> -1597.8261 | H64: =H62-H63 -> -2902.1739 | I64: =I62-I63 -> -3554.3478 | J64: =J62-J63 -> -1271.7391 | K64: =K62-K63 -> -2902.1739 | ... O64: =O62-O63 -> -4310.8696 | Q64: =SUM(D64:O64) -> -41126.087
C66: NET CHANGE IN BANK BALANCE | D66: =D16-(D56+D64) -> 10652.174 | E66: =E16-(E56+E64) -> 21956.522 | F66: =F16-(F56+F64) -> 33260.87 | G66: =G16-(G56+G64) -> -652.17391 | H66: =H16-(H56+H64) -> 10652.174 | I66: =I16-(I56+I64) -> 16304.348 | J66: =J16-(J56+J64) -> -3478.2609 | K66: =K16-(K56+K64) -> 10652.174 | ... O66: =O16-(O56+O64) -> 22860.87 | Q66: =SUM(D66:O66) -> 182426.09
C68: Opening Bank Balance: | D68: 10000 | E68: =D72 -> 20652.174 | F68: =E72 -> 42608.696 | G68: =F72 -> 75869.565 | H68: =G72 -> 75217.391 | I68: =H72 -> 85869.565 | J68: =I72 -> 102173.91 | K68: =J72 -> 98695.652 | L68: =K72 -> 109347.83 | ... O68: =N72 -> 169565.22
C69: Add Total (Net) Deposits | D69: =D16+D63 -> 28510.87 | E69: =E16+E63 -> 39815.217 | F69: =F16+F63 -> 51119.565 | G69: =G16+G63 -> 17206.522 | H69: =H16+H63 -> 28510.87 | I69: =I16+I63 -> 34163.043 | J69: =J16+J63 -> 14380.435 | K69: =K16+K63 -> 28510.87 | ... O69: =O16+O63 -> 40719.565
D70: =SUM(D68:D69) -> 38510.87 | E70: =SUM(E68:E69) -> 60467.391 | F70: =SUM(F68:F69) -> 93728.261 | G70: =SUM(G68:G69) -> 93076.087 | H70: =SUM(H68:H69) -> 103728.26 | I70: =SUM(I68:I69) -> 120032.61 | J70: =SUM(J68:J69) -> 116554.35 | K70: =SUM(K68:K69) -> 127206.52 | ... O70: =SUM(O68:O69) -> 210284.78
C71: Less Total (Net) Withdrawals | D71: =D56+D62 -> 17858.696 | E71: =E56+E62 -> 17858.696 | F71: =F56+F62 -> 17858.696 | G71: =G56+G62 -> 17858.696 | H71: =H56+H62 -> 17858.696 | I71: =I56+I62 -> 17858.696 | J71: =J56+J62 -> 17858.696 | K71: =K56+K62 -> 17858.696 | ... O71: =O56+O62 -> 17858.696
C72: Closing Bank Balance | D72: =D70-D71 -> 20652.174 | E72: =E70-E71 -> 42608.696 | F72: =F70-F71 -> 75869.565 | G72: =G70-G71 -> 75217.391 | H72: =H70-H71 -> 85869.565 | I72: =I70-I71 -> 102173.91 | J72: =J70-J71 -> 98695.652 | K72: =K70-K71 -> 109347.83 | ... O72: =O70-O71 -> 192426.09

Sheet Actual Figures
C3: ACTUAL MONTHLY CASHFLOW: | U3: ='Budget Figures'!U3 -> Goods & Sales Tax % | V3: ='Budget Figures'!V3 -> 0.15
D6: ='Budget Figures'!D6 -> 44287 | E6: ='Budget Figures'!E6 -> 44317 | F6: ='Budget Figures'!F6 -> 44348 | G6: ='Budget Figures'!G6 -> 44378 | H6: ='Budget Figures'!H6 -> 44409 | I6: ='Budget Figures'!I6 -> 44440 | J6: ='Budget Figures'!J6 -> 44470 | K6: ='Budget Figures'!K6 -> 44501 | ... O6: ='Budget Figures'!O6 -> 44621 | Q6: Year to Date
C7: DEPOSITS
C9: ='Budget Figures'!C9 -> Sales | D9: 15000 | E9: 18000 | F9: 20000 | G9: 14000 | H9: 25000 | I9: 26000 | J9: 27000 | K9: 28000 | L9: 30000 | M9: 31000 | N9: 32000 | O9: 33000 | Q9: =SUM(D9:O9) -> 299000
C10: ='Budget Figures'!C10 -> Tax Rebates | Q10: =SUM(D10:O10) -> 0
C11: ='Budget Figures'!C11 -> Interest Received | Q11: =SUM(D11:O11) -> 0
C12: ='Budget Figures'!C12 -> Capital Introduced | Q12: =SUM(D12:O12) -> 0
C13: ='Budget Figures'!C13 -> Other | Q13: =SUM(D13:O13) -> 0
C14: ='Budget Figures'!C14 -> Non GST Related Sales
C15: ='Budget Figures'!C15
C16: ='Budget Figures'!C16 -> SUBTOTAL DEPOSITS: | D16: =SUM(D9:D13) -> 15000 | E16: =SUM(E9:E13) -> 18000 | F16: =SUM(F9:F13) -> 20000 | G16: =SUM(G9:G13) -> 14000 | H16: =SUM(H9:H13) -> 25000 | I16: =SUM(I9:I13) -> 26000 | J16: =SUM(J9:J13) -> 27000 | K16: =SUM(K9:K13) -> 28000 | ... O16: =SUM(O9:O13) -> 33000 | Q16: =SUM(D16:O16) -> 299000
C17: ='Budget Figures'!C17
C18: ='Budget Figures'!C18 -> WITHDRAWALS (Expenses)
C19: ='Budget Figures'!C19
C20: ='Budget Figures'!C20 -> Car | D20: 450 | E20: 450 | F20: 450 | G20: 450 | H20: 450 | I20: 450 | J20: 450 | K20: 450 | L20: 450 | M20: 450 | N20: 450 | O20: 450 | Q20: =SUM(D20:O20) -> 5400
C21: ='Budget Figures'!C21 -> Bank Fees | Q21: =SUM(D21:O21) -> 0
C22: ='Budget Figures'!C22 -> Credit Card Charges | Q22: =SUM(D22:O22) -> 0
C23: ='Budget Figures'!C23 -> Computer ( Hardware & Software) | Q23: =SUM(D23:O23) -> 0
C24: ='Budget Figures'!C24 -> Entertainment | D24: 250 | E24: 250 | F24: 250 | G24: 250 | H24: 250 | I24: 250 | J24: 250 | K24: 250 | L24: 250 | M24: 250 | N24: 250 | O24: 250 | Q24: =SUM(D24:O24) -> 3000
C25: ='Budget Figures'!C25 -> General Expenses | Q25: =SUM(D25:O25) -> 0
C26: ='Budget Figures'!C26 -> Printing | D26: 175 | E26: 175 | F26: 175 | G26: 175 | H26: 175 | I26: 175 | J26: 175 | K26: 175 | L26: 175 | M26: 175 | N26: 175 | O26: 175 | Q26: =SUM(D26:O26) -> 2100
C27: ='Budget Figures'!C27 -> Stationary & Supplies | Q27: =SUM(D27:O27) -> 0
C28: ='Budget Figures'!C28 -> Vehicle Leases | D28: 1050 | E28: 1050 | F28: 1050 | G28: 1050 | H28: 1050 | I28: 1050 | J28: 1050 | K28: 1050 | L28: 1050 | M28: 1050 | N28: 1050 | O28: 1050 | Q28: =SUM(D28:O28) -> 12600
C29: ='Budget Figures'!C29 -> Telephone, Tolls & E-Mail | Q29: =SUM(D29:O29) -> 0
C30: ='Budget Figures'!C30 -> Cell Phone | Q30: =SUM(D30:O30) -> 0
C31: ='Budget Figures'!C31 -> Travelling & Accomodation | Q31: =SUM(D31:O31) -> 0
C32: ='Budget Figures'!C32 -> Insurance | Q32: =SUM(D32:O32) -> 0
C33: ='Budget Figures'!C33 -> Accounting | D33: 600 | E33: 600 | F33: 600 | G33: 600 | H33: 600 | I33: 600 | J33: 600 | K33: 600 | L33: 600 | M33: 600 | N33: 600 | O33: 600 | Q33: =SUM(D33:O33) -> 7200
C34: ='Budget Figures'!C34 -> Provision for Taxation | Q34: =SUM(D34:O34) -> 0
C35: ='Budget Figures'!C35 -> Fringe Benefit Tax | Q35: =SUM(D35:O35) -> 0
C36: ='Budget Figures'!C36 -> Legal | Q36: =SUM(D36:O36) -> 0
C37: ='Budget Figures'!C37 -> Low Cost Assets | Q37: =SUM(D37:O37) -> 0
C38: ='Budget Figures'!C38 -> Plant & Equipment | Q38: =SUM(D38:O38) -> 0
C39: ='Budget Figures'!C39 -> Drawings | Q39: =SUM(D39:O39) -> 0
C40: ='Budget Figures'!C40 -> Principle Loan Repayments | D40: 500 | E40: 500 | F40: 500 | G40: 500 | H40: 500 | I40: 500 | J40: 500 | K40: 500 | L40: 500 | M40: 500 | N40: 500 | O40: 500 | Q40: =SUM(D40:O40) -> 6000
C41: ='Budget Figures'!C41 -> Other 1 | Q41: =SUM(D41:O41) -> 0
C42: ='Budget Figures'!C42 -> Other 2 | Q42: =SUM(D42:O42) -> 0
C43: ='Budget Figures'!C43 -> Other 3 | Q43: =SUM(D43:O43) -> 0
C44: ='Budget Figures'!C44 -> Other 4 | Q44: =SUM(D44:O44) -> 0
C45: ='Budget Figures'!C45 -> Other 5 | Q45: =SUM(D45:O45) -> 0
C46: ='Budget Figures'!C46 -> Other 6 | Q46: =SUM(D46:O46) -> 0
C47: ='Budget Figures'!C47
C48: ='Budget Figures'!C48 -> NON GST RELATED WITHDRAWALS
C49: ='Budget Figures'!C49
C50: ='Budget Figures'!C50 -> Wages | D50: 12500 | E50: 12500 | F50: 12500 | G50: 12500 | H50: 12500 | I50: 12500 | J50: 12500 | K50: 12500 | L50: 12500 | M50: 12500 | N50: 12500 | O50: 12500 | Q50: =SUM(D50:O50) -> 150000
C51: ='Budget Figures'!C51 -> Interest Only Loan Payments | D51: 825 | E51: 825 | F51: 825 | G51: 825 | H51: 825 | I51: 825 | J51: 825 | K51: 825 | L51: 825 | M51: 825 | N51: 825 | O51: 825 | Q51: =SUM(D51:O51) -> 9900
C52: ='Budget Figures'!C52 -> Other 1 | Q52: =SUM(D52:O52) -> 0
C53: ='Budget Figures'!C53 -> Other 2 | Q53: =SUM(D53:O53) -> 0
C54: ='Budget Figures'!C54 -> Other 3 | Q54: =SUM(D54:O54) -> 0
C55: ='Budget Figures'!C55
C56: ='Budget Figures'!C56 -> SUBTOTAL WITHDRAWALS: | D56: =SUM(D20:D46) -> 3025 | E56: =SUM(E20:E46) -> 3025 | F56: =SUM(F20:F46) -> 3025 | G56: =SUM(G20:G46) -> 3025 | H56: =SUM(H20:H46) -> 3025 | I56: =SUM(I20:I46) -> 3025 | J56: =SUM(J20:J46) -> 3025 | K56: =SUM(K20:K46) -> 3025 | ... O56: =SUM(O20:O46) -> 3025 | Q56: =SUM(D56:O56) -> 36300
C57: ='Budget Figures'!C57
C58: ='Budget Figures'!C58 -> GST Related Deposits | D58: =D9+D11+D13 -> 15000 | E58: =E9+E11+E13 -> 18000 | F58: =F9+F11+F13 -> 20000 | G58: =G9+G11+G13 -> 14000 | H58: =H9+H11+H13 -> 25000 | I58: =I9+I11+I13 -> 26000 | J58: =J9+J11+J13 -> 27000 | K58: =K9+K11+K13 -> 28000 | ... O58: =O9+O11+O13 -> 33000
C59: ='Budget Figures'!C59 -> GST Related Withdrawals | D59: =sum(D20:D46) -> 3025 | E59: =sum(E20:E46) -> 3025 | F59: =sum(F20:F46) -> 3025 | G59: =sum(G20:G46) -> 3025 | H59: =sum(H20:H46) -> 3025 | I59: =sum(I20:I46) -> 3025 | J59: =sum(J20:J46) -> 3025 | K59: =sum(K20:K46) -> 3025 | ... O59: =sum(O20:O46) -> 3025
C61: GST MOVEMENTS
C62: Input (Expense Related) | D62: =D59-(D59/(1+$V$3)) -> 394.56522 | E62: =E59-(E59/(1+$V$3)) -> 394.56522 | F62: =F59-(F59/(1+$V$3)) -> 394.56522 | G62: =G59-(G59/(1+$V$3)) -> 394.56522 | H62: =H59-(H59/(1+$V$3)) -> 394.56522 | I62: =I59-(I59/(1+$V$3)) -> 394.56522 | J62: =J59-(J59/(1+$V$3)) -> 394.56522 | K62: =K59-(K59/(1+$V$3)) -> 394.56522 | ... O62: =O59-(O59/(1+$V$3)) -> 394.56522 | Q62: =SUM(D62:O62) -> 4734.7826
C63: Output (Income Related) | D63: =D58-(D58/(1+$V$3)) -> 1956.5217 | E63: =E58-(E58/(1+$V$3)) -> 2347.8261 | F63: =F58-(F58/(1+$V$3)) -> 2608.6957 | G63: =G58-(G58/(1+$V$3)) -> 1826.087 | H63: =H58-(H58/(1+$V$3)) -> 3260.8696 | I63: =I58-(I58/(1+$V$3)) -> 3391.3043 | J63: =J58-(J58/(1+$V$3)) -> 3521.7391 | K63: =K58-(K58/(1+$V$3)) -> 3652.1739 | ... O63: =O58-(O58/(1+$V$3)) -> 4304.3478 | Q63: =SUM(D63:O63) -> 39000
C64: NET CASH RELATED TO GST | D64: =D62-D63 -> -1561.9565 | E64: =E62-E63 -> -1953.2609 | F64: =F62-F63 -> -2214.1304 | G64: =G62-G63 -> -1431.5217 | H64: =H62-H63 -> -2866.3043 | I64: =I62-I63 -> -2996.7391 | J64: =J62-J63 -> -3127.1739 | K64: =K62-K63 -> -3257.6087 | ... O64: =O62-O63 -> -3909.7826 | Q64: =SUM(D64:O64) -> -34265.217
C66: NET CHANGE IN BANK BALANCE | D66: =D16-(D56+D64) -> 13536.957 | E66: =E16-(E56+E64) -> 16928.261 | F66: =F16-(F56+F64) -> 19189.13 | G66: =G16-(G56+G64) -> 12406.522 | H66: =H16-(H56+H64) -> 24841.304 | I66: =I16-(I56+I64) -> 25971.739 | J66: =J16-(J56+J64) -> 27102.174 | K66: =K16-(K56+K64) -> 28232.609 | ... O66: =O16-(O56+O64) -> 33884.783 | Q66: =SUM(D66:O66) -> 296965.22
C68: Opening Bank Balance: | D68: 6500 | E68: =D72 -> 20036.957 | F68: =E72 -> 36965.217 | G68: =F72 -> 56154.348 | H68: =G72 -> 68560.87 | I68: =H72 -> 93402.174 | J68: =I72 -> 119373.91 | K68: =J72 -> 146476.09 | L68: =K72 -> 174708.7 | ... O68: =N72 -> 269580.43
C69: Add Total Deposits | D69: =D16+D63 -> 16956.522 | E69: =E16+E63 -> 20347.826 | F69: =F16+F63 -> 22608.696 | G69: =G16+G63 -> 15826.087 | H69: =H16+H63 -> 28260.87 | I69: =I16+I63 -> 29391.304 | J69: =J16+J63 -> 30521.739 | K69: =K16+K63 -> 31652.174 | ... O69: =O16+O63 -> 37304.348
D70: =SUM(D68:D69) -> 23456.522 | E70: =SUM(E68:E69) -> 40384.783 | F70: =SUM(F68:F69) -> 59573.913 | G70: =SUM(G68:G69) -> 71980.435 | H70: =SUM(H68:H69) -> 96821.739 | I70: =SUM(I68:I69) -> 122793.48 | J70: =SUM(J68:J69) -> 149895.65 | K70: =SUM(K68:K69) -> 178128.26 | ... O70: =SUM(O68:O69) -> 306884.78
C71: Less Total Withdrawals | D71: =D56+D62 -> 3419.5652 | E71: =E56+E62 -> 3419.5652 | F71: =F56+F62 -> 3419.5652 | G71: =G56+G62 -> 3419.5652 | H71: =H56+H62 -> 3419.5652 | I71: =I56+I62 -> 3419.5652 | J71: =J56+J62 -> 3419.5652 | K71: =K56+K62 -> 3419.5652 | ... O71: =O56+O62 -> 3419.5652
C72: Closing Bank Balance | D72: =D70-D71 -> 20036.957 | E72: =E70-E71 -> 36965.217 | F72: =F70-F71 -> 56154.348 | G72: =G70-G71 -> 68560.87 | H72: =H70-H71 -> 93402.174 | I72: =I70-I71 -> 119373.91 | J72: =J70-J71 -> 146476.09 | K72: =K70-K71 -> 174708.7 | ... O72: =O70-O71 -> 303465.22

Sheet Cashflow Variances
C3: VARIANCES TO FORECASTED CASHFLOW:
D6: ='Budget Figures'!D6 -> 44287 | E6: ='Budget Figures'!E6 -> 44317 | F6: ='Budget Figures'!F6 -> 44348 | G6: ='Budget Figures'!G6 -> 44378 | H6: ='Budget Figures'!H6 -> 44409 | I6: ='Budget Figures'!I6 -> 44440 | J6: ='Budget Figures'!J6 -> 44470 | K6: ='Budget Figures'!K6 -> 44501 | ... O6: ='Budget Figures'!O6 -> 44621 | Q6: Year to Date
C7: DEPOSITS
C9: ='Budget Figures'!C9 -> Sales | D9: =IF('Actual Figures'!D9<>"",'Actual Figures'!D9-'Budget Figures'!D9,"") -> -10000 | E9: =IF('Actual Figures'!E9<>"",'Actual Figures'!E9-'Budget Figures'!E9,"") -> -17000 | F9: =IF('Actual Figures'!F9<>"",'Actual Figures'!F9-'Budget Figures'!F9,"") -> -25000 | G9: =IF('Actual Figures'!G9<>"",'Actual Figures'!G9-'Budget Figures'!G9,"") -> -1000 | H9: =IF('Actual Figures'!H9<>"",'Actual Figures'!H9-'Budget Figures'!H9,"") -> 0 | I9: =IF('Actual Figures'!I9<>"",'Actual Figures'!I9-'Budget Figures'!I9,"") -> -4000 | J9: =IF('Actual Figures'!J9<>"",'Actual Figures'!J9-'Budget Figures'!J9,"") -> 14500 | K9: =IF('Actual Figures'!K9<>"",'Actual Figures'!K9-'Budget Figures'!K9,"") -> 3000 | ... O9: =IF('Actual Figures'!O9<>"",'Actual Figures'!O9-'Budget Figures'!O9,"") -> -2800 | Q9: =SUM(D9:O9) -> -49300
C10: ='Budget Figures'!C10 -> Tax Rebates | D10: =IF('Actual Figures'!D10<>"",'Actual Figures'!D10-'Budget Figures'!D10,"") | E10: =IF('Actual Figures'!E10<>"",'Actual Figures'!E10-'Budget Figures'!E10,"") | F10: =IF('Actual Figures'!F10<>"",'Actual Figures'!F10-'Budget Figures'!F10,"") | G10: =IF('Actual Figures'!G10<>"",'Actual Figures'!G10-'Budget Figures'!G10,"") | H10: =IF('Actual Figures'!H10<>"",'Actual Figures'!H10-'Budget Figures'!H10,"") | I10: =IF('Actual Figures'!I10<>"",'Actual Figures'!I10-'Budget Figures'!I10,"") | J10: =IF('Actual Figures'!J10<>"",'Actual Figures'!J10-'Budget Figures'!J10,"") | K10: =IF('Actual Figures'!K10<>"",'Actual Figures'!K10-'Budget Figures'!K10,"") | ... O10: =IF('Actual Figures'!O10<>"",'Actual Figures'!O10-'Budget Figures'!O10,"") | Q10: =SUM(D10:O10) -> 0
C11: ='Budget Figures'!C11 -> Interest Received | D11: =IF('Actual Figures'!D11<>"",'Actual Figures'!D11-'Budget Figures'!D11,"") | E11: =IF('Actual Figures'!E11<>"",'Actual Figures'!E11-'Budget Figures'!E11,"") | F11: =IF('Actual Figures'!F11<>"",'Actual Figures'!F11-'Budget Figures'!F11,"") | G11: =IF('Actual Figures'!G11<>"",'Actual Figures'!G11-'Budget Figures'!G11,"") | H11: =IF('Actual Figures'!H11<>"",'Actual Figures'!H11-'Budget Figures'!H11,"") | I11: =IF('Actual Figures'!I11<>"",'Actual Figures'!I11-'Budget Figures'!I11,"") | J11: =IF('Actual Figures'!J11<>"",'Actual Figures'!J11-'Budget Figures'!J11,"") | K11: =IF('Actual Figures'!K11<>"",'Actual Figures'!K11-'Budget Figures'!K11,"") | ... O11: =IF('Actual Figures'!O11<>"",'Actual Figures'!O11-'Budget Figures'!O11,"") | Q11: =SUM(D11:O11) -> 0
C12: ='Budget Figures'!C12 -> Capital Introduced | D12: =IF('Actual Figures'!D12<>"",'Actual Figures'!D12-'Budget Figures'!D12,"") | E12: =IF('Actual Figures'!E12<>"",'Actual Figures'!E12-'Budget Figures'!E12,"") | F12: =IF('Actual Figures'!F12<>"",'Actual Figures'!F12-'Budget Figures'!F12,"") | G12: =IF('Actual Figures'!G12<>"",'Actual Figures'!G12-'Budget Figures'!G12,"") | H12: =IF('Actual Figures'!H12<>"",'Actual Figures'!H12-'Budget Figures'!H12,"") | I12: =IF('Actual Figures'!I12<>"",'Actual Figures'!I12-'Budget Figures'!I12,"") | J12: =IF('Actual Figures'!J12<>"",'Actual Figures'!J12-'Budget Figures'!J12,"") | K12: =IF('Actual Figures'!K12<>"",'Actual Figures'!K12-'Budget Figures'!K12,"") | ... O12: =IF('Actual Figures'!O12<>"",'Actual Figures'!O12-'Budget Figures'!O12,"") | Q12: =SUM(D12:O12) -> 0
C13: ='Budget Figures'!C13 -> Other | D13: =IF('Actual Figures'!D13<>"",'Actual Figures'!D13-'Budget Figures'!D13,"") | E13: =IF('Actual Figures'!E13<>"",'Actual Figures'!E13-'Budget Figures'!E13,"") | F13: =IF('Actual Figures'!F13<>"",'Actual Figures'!F13-'Budget Figures'!F13,"") | G13: =IF('Actual Figures'!G13<>"",'Actual Figures'!G13-'Budget Figures'!G13,"") | H13: =IF('Actual Figures'!H13<>"",'Actual Figures'!H13-'Budget Figures'!H13,"") | I13: =IF('Actual Figures'!I13<>"",'Actual Figures'!I13-'Budget Figures'!I13,"") | J13: =IF('Actual Figures'!J13<>"",'Actual Figures'!J13-'Budget Figures'!J13,"") | K13: =IF('Actual Figures'!K13<>"",'Actual Figures'!K13-'Budget Figures'!K13,"") | ... O13: =IF('Actual Figures'!O13<>"",'Actual Figures'!O13-'Budget Figures'!O13,"") | Q13: =SUM(D13:O13) -> 0
C14: ='Budget Figures'!C14 -> Non GST Related Sales | D14: =IF('Actual Figures'!D14<>"",'Actual Figures'!D14-'Budget Figures'!D14,"") | E14: =IF('Actual Figures'!E14<>"",'Actual Figures'!E14-'Budget Figures'!E14,"") | F14: =IF('Actual Figures'!F14<>"",'Actual Figures'!F14-'Budget Figures'!F14,"") | G14: =IF('Actual Figures'!G14<>"",'Actual Figures'!G14-'Budget Figures'!G14,"") | H14: =IF('Actual Figures'!H14<>"",'Actual Figures'!H14-'Budget Figures'!H14,"") | I14: =IF('Actual Figures'!I14<>"",'Actual Figures'!I14-'Budget Figures'!I14,"") | J14: =IF('Actual Figures'!J14<>"",'Actual Figures'!J14-'Budget Figures'!J14,"") | K14: =IF('Actual Figures'!K14<>"",'Actual Figures'!K14-'Budget Figures'!K14,"") | ... O14: =IF('Actual Figures'!O14<>"",'Actual Figures'!O14-'Budget Figures'!O14,"") | Q14: =SUM(D14:O14) -> 0
C15: ='Budget Figures'!C15
C16: ='Budget Figures'!C16 -> SUBTOTAL DEPOSITS: | D16: =SUM(D9:D13) -> -10000 | E16: =SUM(E9:E13) -> -17000 | F16: =SUM(F9:F13) -> -25000 | G16: =SUM(G9:G13) -> -1000 | H16: =SUM(H9:H13) -> 0 | I16: =SUM(I9:I13) -> -4000 | J16: =SUM(J9:J13) -> 14500 | K16: =SUM(K9:K13) -> 3000 | ... O16: =SUM(O9:O13) -> -2800 | Q16: =SUM(D16:O16) -> -49300
C17: ='Budget Figures'!C17
C18: ='Budget Figures'!C18 -> WITHDRAWALS (Expenses)
C19: ='Budget Figures'!C19
C20: ='Budget Figures'!C20 -> Car | D20: =IF('Actual Figures'!D20<>"",'Actual Figures'!D20-'Budget Figures'!D20,"") -> -50 | E20: =IF('Actual Figures'!E20<>"",'Actual Figures'!E20-'Budget Figures'!E20,"") -> -50 | F20: =IF('Actual Figures'!F20<>"",'Actual Figures'!F20-'Budget Figures'!F20,"") -> -50 | G20: =IF('Actual Figures'!G20<>"",'Actual Figures'!G20-'Budget Figures'!G20,"") -> -50 | H20: =IF('Actual Figures'!H20<>"",'Actual Figures'!H20-'Budget Figures'!H20,"") -> -50 | I20: =IF('Actual Figures'!I20<>"",'Actual Figures'!I20-'Budget Figures'!I20,"") -> -50 | J20: =IF('Actual Figures'!J20<>"",'Actual Figures'!J20-'Budget Figures'!J20,"") -> -50 | K20: =IF('Actual Figures'!K20<>"",'Actual Figures'!K20-'Budget Figures'!K20,"") -> -50 | ... O20: =IF('Actual Figures'!O20<>"",'Actual Figures'!O20-'Budget Figures'!O20,"") -> -50 | Q20: =SUM(D20:O20) -> -600
C21: ='Budget Figures'!C21 -> Bank Fees | D21: =IF('Actual Figures'!D21<>"",'Actual Figures'!D21-'Budget Figures'!D21,"") | E21: =IF('Actual Figures'!E21<>"",'Actual Figures'!E21-'Budget Figures'!E21,"") | F21: =IF('Actual Figures'!F21<>"",'Actual Figures'!F21-'Budget Figures'!F21,"") | G21: =IF('Actual Figures'!G21<>"",'Actual Figures'!G21-'Budget Figures'!G21,"") | H21: =IF('Actual Figures'!H21<>"",'Actual Figures'!H21-'Budget Figures'!H21,"") | I21: =IF('Actual Figures'!I21<>"",'Actual Figures'!I21-'Budget Figures'!I21,"") | J21: =IF('Actual Figures'!J21<>"",'Actual Figures'!J21-'Budget Figures'!J21,"") | K21: =IF('Actual Figures'!K21<>"",'Actual Figures'!K21-'Budget Figures'!K21,"") | ... O21: =IF('Actual Figures'!O21<>"",'Actual Figures'!O21-'Budget Figures'!O21,"") | Q21: =SUM(D21:O21) -> 0
C22: ='Budget Figures'!C22 -> Credit Card Charges | D22: =IF('Actual Figures'!D22<>"",'Actual Figures'!D22-'Budget Figures'!D22,"") | E22: =IF('Actual Figures'!E22<>"",'Actual Figures'!E22-'Budget Figures'!E22,"") | F22: =IF('Actual Figures'!F22<>"",'Actual Figures'!F22-'Budget Figures'!F22,"") | G22: =IF('Actual Figures'!G22<>"",'Actual Figures'!G22-'Budget Figures'!G22,"") | H22: =IF('Actual Figures'!H22<>"",'Actual Figures'!H22-'Budget Figures'!H22,"") | I22: =IF('Actual Figures'!I22<>"",'Actual Figures'!I22-'Budget Figures'!I22,"") | J22: =IF('Actual Figures'!J22<>"",'Actual Figures'!J22-'Budget Figures'!J22,"") | K22: =IF('Actual Figures'!K22<>"",'Actual Figures'!K22-'Budget Figures'!K22,"") | ... O22: =IF('Actual Figures'!O22<>"",'Actual Figures'!O22-'Budget Figures'!O22,"") | Q22: =SUM(D22:O22) -> 0
C23: ='Budget Figures'!C23 -> Computer ( Hardware & Software) | D23: =IF('Actual Figures'!D23<>"",'Actual Figures'!D23-'Budget Figures'!D23,"") | E23: =IF('Actual Figures'!E23<>"",'Actual Figures'!E23-'Budget Figures'!E23,"") | F23: =IF('Actual Figures'!F23<>"",'Actual Figures'!F23-'Budget Figures'!F23,"") | G23: =IF('Actual Figures'!G23<>"",'Actual Figures'!G23-'Budget Figures'!G23,"") | H23: =IF('Actual Figures'!H23<>"",'Actual Figures'!H23-'Budget Figures'!H23,"") | I23: =IF('Actual Figures'!I23<>"",'Actual Figures'!I23-'Budget Figures'!I23,"") | J23: =IF('Actual Figures'!J23<>"",'Actual Figures'!J23-'Budget Figures'!J23,"") | K23: =IF('Actual Figures'!K23<>"",'Actual Figures'!K23-'Budget Figures'!K23,"") | ... O23: =IF('Actual Figures'!O23<>"",'Actual Figures'!O23-'Budget Figures'!O23,"") | Q23: =SUM(D23:O23) -> 0
C24: ='Budget Figures'!C24 -> Entertainment | D24: =IF('Actual Figures'!D24<>"",'Actual Figures'!D24-'Budget Figures'!D24,"") -> 100 | E24: =IF('Actual Figures'!E24<>"",'Actual Figures'!E24-'Budget Figures'!E24,"") -> 100 | F24: =IF('Actual Figures'!F24<>"",'Actual Figures'!F24-'Budget Figures'!F24,"") -> 100 | G24: =IF('Actual Figures'!G24<>"",'Actual Figures'!G24-'Budget Figures'!G24,"") -> 100 | H24: =IF('Actual Figures'!H24<>"",'Actual Figures'!H24-'Budget Figures'!H24,"") -> 100 | I24: =IF('Actual Figures'!I24<>"",'Actual Figures'!I24-'Budget Figures'!I24,"") -> 100 | J24: =IF('Actual Figures'!J24<>"",'Actual Figures'!J24-'Budget Figures'!J24,"") -> 100 | K24: =IF('Actual Figures'!K24<>"",'Actual Figures'!K24-'Budget Figures'!K24,"") -> 100 | ... O24: =IF('Actual Figures'!O24<>"",'Actual Figures'!O24-'Budget Figures'!O24,"") -> 100 | Q24: =SUM(D24:O24) -> 1200
C25: ='Budget Figures'!C25 -> General Expenses | D25: =IF('Actual Figures'!D25<>"",'Actual Figures'!D25-'Budget Figures'!D25,"") | E25: =IF('Actual Figures'!E25<>"",'Actual Figures'!E25-'Budget Figures'!E25,"") | F25: =IF('Actual Figures'!F25<>"",'Actual Figures'!F25-'Budget Figures'!F25,"") | G25: =IF('Actual Figures'!G25<>"",'Actual Figures'!G25-'Budget Figures'!G25,"") | H25: =IF('Actual Figures'!H25<>"",'Actual Figures'!H25-'Budget Figures'!H25,"") | I25: =IF('Actual Figures'!I25<>"",'Actual Figures'!I25-'Budget Figures'!I25,"") | J25: =IF('Actual Figures'!J25<>"",'Actual Figures'!J25-'Budget Figures'!J25,"") | K25: =IF('Actual Figures'!K25<>"",'Actual Figures'!K25-'Budget Figures'!K25,"") | ... O25: =IF('Actual Figures'!O25<>"",'Actual Figures'!O25-'Budget Figures'!O25,"") | Q25: =SUM(D25:O25) -> 0
C26: ='Budget Figures'!C26 -> Printing | D26: =IF('Actual Figures'!D26<>"",'Actual Figures'!D26-'Budget Figures'!D26,"") -> 175 | E26: =IF('Actual Figures'!E26<>"",'Actual Figures'!E26-'Budget Figures'!E26,"") -> 175 | F26: =IF('Actual Figures'!F26<>"",'Actual Figures'!F26-'Budget Figures'!F26,"") -> 175 | G26: =IF('Actual Figures'!G26<>"",'Actual Figures'!G26-'Budget Figures'!G26,"") -> 175 | H26: =IF('Actual Figures'!H26<>"",'Actual Figures'!H26-'Budget Figures'!H26,"") -> 175 | I26: =IF('Actual Figures'!I26<>"",'Actual Figures'!I26-'Budget Figures'!I26,"") -> 175 | J26: =IF('Actual Figures'!J26<>"",'Actual Figures'!J26-'Budget Figures'!J26,"") -> 175 | K26: =IF('Actual Figures'!K26<>"",'Actual Figures'!K26-'Budget Figures'!K26,"") -> 175 | ... O26: =IF('Actual Figures'!O26<>"",'Actual Figures'!O26-'Budget Figures'!O26,"") -> 175 | Q26: =SUM(D26:O26) -> 2100
C27: ='Budget Figures'!C27 -> Stationary & Supplies | D27: =IF('Actual Figures'!D27<>"",'Actual Figures'!D27-'Budget Figures'!D27,"") | E27: =IF('Actual Figures'!E27<>"",'Actual Figures'!E27-'Budget Figures'!E27,"") | F27: =IF('Actual Figures'!F27<>"",'Actual Figures'!F27-'Budget Figures'!F27,"") | G27: =IF('Actual Figures'!G27<>"",'Actual Figures'!G27-'Budget Figures'!G27,"") | H27: =IF('Actual Figures'!H27<>"",'Actual Figures'!H27-'Budget Figures'!H27,"") | I27: =IF('Actual Figures'!I27<>"",'Actual Figures'!I27-'Budget Figures'!I27,"") | J27: =IF('Actual Figures'!J27<>"",'Actual Figures'!J27-'Budget Figures'!J27,"") | K27: =IF('Actual Figures'!K27<>"",'Actual Figures'!K27-'Budget Figures'!K27,"") | ... O27: =IF('Actual Figures'!O27<>"",'Actual Figures'!O27-'Budget Figures'!O27,"") | Q27: =SUM(D27:O27) -> 0
C28: ='Budget Figures'!C28 -> Vehicle Leases | D28: =IF('Actual Figures'!D28<>"",'Actual Figures'!D28-'Budget Figures'!D28,"") -> 50 | E28: =IF('Actual Figures'!E28<>"",'Actual Figures'!E28-'Budget Figures'!E28,"") -> 50 | F28: =IF('Actual Figures'!F28<>"",'Actual Figures'!F28-'Budget Figures'!F28,"") -> 50 | G28: =IF('Actual Figures'!G28<>"",'Actual Figures'!G28-'Budget Figures'!G28,"") -> 50 | H28: =IF('Actual Figures'!H28<>"",'Actual Figures'!H28-'Budget Figures'!H28,"") -> 50 | I28: =IF('Actual Figures'!I28<>"",'Actual Figures'!I28-'Budget Figures'!I28,"") -> 50 | J28: =IF('Actual Figures'!J28<>"",'Actual Figures'!J28-'Budget Figures'!J28,"") -> 50 | K28: =IF('Actual Figures'!K28<>"",'Actual Figures'!K28-'Budget Figures'!K28,"") -> 50 | ... O28: =IF('Actual Figures'!O28<>"",'Actual Figures'!O28-'Budget Figures'!O28,"") -> 50 | Q28: =SUM(D28:O28) -> 600
C29: ='Budget Figures'!C29 -> Telephone, Tolls & E-Mail | D29: =IF('Actual Figures'!D29<>"",'Actual Figures'!D29-'Budget Figures'!D29,"") | E29: =IF('Actual Figures'!E29<>"",'Actual Figures'!E29-'Budget Figures'!E29,"") | F29: =IF('Actual Figures'!F29<>"",'Actual Figures'!F29-'Budget Figures'!F29,"") | G29: =IF('Actual Figures'!G29<>"",'Actual Figures'!G29-'Budget Figures'!G29,"") | H29: =IF('Actual Figures'!H29<>"",'Actual Figures'!H29-'Budget Figures'!H29,"") | I29: =IF('Actual Figures'!I29<>"",'Actual Figures'!I29-'Budget Figures'!I29,"") | J29: =IF('Actual Figures'!J29<>"",'Actual Figures'!J29-'Budget Figures'!J29,"") | K29: =IF('Actual Figures'!K29<>"",'Actual Figures'!K29-'Budget Figures'!K29,"") | ... O29: =IF('Actual Figures'!O29<>"",'Actual Figures'!O29-'Budget Figures'!O29,"") | Q29: =SUM(D29:O29) -> 0
C30: ='Budget Figures'!C30 -> Cell Phone | D30: =IF('Actual Figures'!D30<>"",'Actual Figures'!D30-'Budget Figures'!D30,"") | E30: =IF('Actual Figures'!E30<>"",'Actual Figures'!E30-'Budget Figures'!E30,"") | F30: =IF('Actual Figures'!F30<>"",'Actual Figures'!F30-'Budget Figures'!F30,"") | G30: =IF('Actual Figures'!G30<>"",'Actual Figures'!G30-'Budget Figures'!G30,"") | H30: =IF('Actual Figures'!H30<>"",'Actual Figures'!H30-'Budget Figures'!H30,"") | I30: =IF('Actual Figures'!I30<>"",'Actual Figures'!I30-'Budget Figures'!I30,"") | J30: =IF('Actual Figures'!J30<>"",'Actual Figures'!J30-'Budget Figures'!J30,"") | K30: =IF('Actual Figures'!K30<>"",'Actual Figures'!K30-'Budget Figures'!K30,"") | ... O30: =IF('Actual Figures'!O30<>"",'Actual Figures'!O30-'Budget Figures'!O30,"") | Q30: =SUM(D30:O30) -> 0
C31: ='Budget Figures'!C31 -> Travelling & Accomodation | D31: =IF('Actual Figures'!D31<>"",'Actual Figures'!D31-'Budget Figures'!D31,"") | E31: =IF('Actual Figures'!E31<>"",'Actual Figures'!E31-'Budget Figures'!E31,"") | F31: =IF('Actual Figures'!F31<>"",'Actual Figures'!F31-'Budget Figures'!F31,"") | G31: =IF('Actual Figures'!G31<>"",'Actual Figures'!G31-'Budget Figures'!G31,"") | H31: =IF('Actual Figures'!H31<>"",'Actual Figures'!H31-'Budget Figures'!H31,"") | I31: =IF('Actual Figures'!I31<>"",'Actual Figures'!I31-'Budget Figures'!I31,"") | J31: =IF('Actual Figures'!J31<>"",'Actual Figures'!J31-'Budget Figures'!J31,"") | K31: =IF('Actual Figures'!K31<>"",'Actual Figures'!K31-'Budget Figures'!K31,"") | ... O31: =IF('Actual Figures'!O31<>"",'Actual Figures'!O31-'Budget Figures'!O31,"") | Q31: =SUM(D31:O31) -> 0
... C46: ='Budget Figures'!C46 -> Other 6 | D46: =IF('Actual Figures'!D46<>"",'Actual Figures'!D46-'Budget Figures'!D46,"") | E46: =IF('Actual Figures'!E46<>"",'Actual Figures'!E46-'Budget Figures'!E46,"") | F46: =IF('Actual Figures'!F46<>"",'Actual Figures'!F46-'Budget Figures'!F46,"") | G46: =IF('Actual Figures'!G46<>"",'Actual Figures'!G46-'Budget Figures'!G46,"") | H46: =IF('Actual Figures'!H46<>"",'Actual Figures'!H46-'Budget Figures'!H46,"") | I46: =IF('Actual Figures'!I46<>"",'Actual Figures'!I46-'Budget Figures'!I46,"") | J46: =IF('Actual Figures'!J46<>"",'Actual Figures'!J46-'Budget Figures'!J46,"") | K46: =IF('Actual Figures'!K46<>"",'Actual Figures'!K46-'Budget Figures'!K46,"") | ... O46: =IF('Actual Figures'!O46<>"",'Actual Figures'!O46-'Budget Figures'!O46,"") | Q46: =SUM(D46:O46) -> 0
C47: ='Budget Figures'!C47 | D47: ='Budget Figures'!D47 | E47: ='Budget Figures'!E47 | F47: ='Budget Figures'!F47 | G47: ='Budget Figures'!G47 | H47: ='Budget Figures'!H47 | I47: ='Budget Figures'!I47 | J47: ='Budget Figures'!J47 | ... O47: ='Budget Figures'!O47 | Q47: ='Budget Figures'!Q47
C48: ='Budget Figures'!C48 -> NON GST RELATED WITHDRAWALS
C49: ='Budget Figures'!C49 | D49: ='Budget Figures'!D49 | E49: ='Budget Figures'!E49 | F49: ='Budget Figures'!F49 | G49: ='Budget Figures'!G49 | H49: ='Budget Figures'!H49 | I49: ='Budget Figures'!I49 | J49: ='Budget Figures'!J49 | ... O49: ='Budget Figures'!O49 | Q49: ='Budget Figures'!Q49 | R49: ='Budget Figures'!R49
C50: ='Budget Figures'!C50 -> Wages | D50: =IF('Actual Figures'!D50<>"",'Actual Figures'!D50-'Budget Figures'!D50,"") -> -1500 | E50: =IF('Actual Figures'!E50<>"",'Actual Figures'!E50-'Budget Figures'!E50,"") -> -1500 | F50: =IF('Actual Figures'!F50<>"",'Actual Figures'!F50-'Budget Figures'!F50,"") -> -1500 | G50: =IF('Actual Figures'!G50<>"",'Actual Figures'!G50-'Budget Figures'!G50,"") -> -1500 | H50: =IF('Actual Figures'!H50<>"",'Actual Figures'!H50-'Budget Figures'!H50,"") -> -1500 | I50: =IF('Actual Figures'!I50<>"",'Actual Figures'!I50-'Budget Figures'!I50,"") -> -1500 | J50: =IF('Actual Figures'!J50<>"",'Actual Figures'!J50-'Budget Figures'!J50,"") -> -1500 | K50: =IF('Actual Figures'!K50<>"",'Actual Figures'!K50-'Budget Figures'!K50,"") -> -1500 | ... O50: =IF('Actual Figures'!O50<>"",'Actual Figures'!O50-'Budget Figures'!O50,"") -> -1500 | Q50: =SUM(D50:O50) -> -18000
C51: ='Budget Figures'!C51 -> Interest Only Loan Payments | D51: =IF('Actual Figures'!D51<>"",'Actual Figures'!D51-'Budget Figures'!D51,"") -> 75 | E51: =IF('Actual Figures'!E51<>"",'Actual Figures'!E51-'Budget Figures'!E51,"") -> 75 | F51: =IF('Actual Figures'!F51<>"",'Actual Figures'!F51-'Budget Figures'!F51,"") -> 75 | G51: =IF('Actual Figures'!G51<>"",'Actual Figures'!G51-'Budget Figures'!G51,"") -> 75 | H51: =IF('Actual Figures'!H51<>"",'Actual Figures'!H51-'Budget Figures'!H51,"") -> 75 | I51: =IF('Actual Figures'!I51<>"",'Actual Figures'!I51-'Budget Figures'!I51,"") -> 75 | J51: =IF('Actual Figures'!J51<>"",'Actual Figures'!J51-'Budget Figures'!J51,"") -> 75 | K51: =IF('Actual Figures'!K51<>"",'Actual Figures'!K51-'Budget Figures'!K51,"") -> 75 | ... O51: =IF('Actual Figures'!O51<>"",'Actual Figures'!O51-'Budget Figures'!O51,"") -> 75 | Q51: =SUM(D51:O51) -> 900
C52: ='Budget Figures'!C52 -> Other 1 | D52: =IF('Actual Figures'!D52<>"",'Actual Figures'!D52-'Budget Figures'!D52,"") | E52: =IF('Actual Figures'!E52<>"",'Actual Figures'!E52-'Budget Figures'!E52,"") | F52: =IF('Actual Figures'!F52<>"",'Actual Figures'!F52-'Budget Figures'!F52,"") | G52: =IF('Actual Figures'!G52<>"",'Actual Figures'!G52-'Budget Figures'!G52,"") | H52: =IF('Actual Figures'!H52<>"",'Actual Figures'!H52-'Budget Figures'!H52,"") | I52: =IF('Actual Figures'!I52<>"",'Actual Figures'!I52-'Budget Figures'!I52,"") | J52: =IF('Actual Figures'!J52<>"",'Actual Figures'!J52-'Budget Figures'!J52,"") | K52: =IF('Actual Figures'!K52<>"",'Actual Figures'!K52-'Budget Figures'!K52,"") | ... O52: =IF('Actual Figures'!O52<>"",'Actual Figures'!O52-'Budget Figures'!O52,"") | Q52: =SUM(D52:O52) -> 0
C53: ='Budget Figures'!C53 -> Other 2 | D53: =IF('Actual Figures'!D53<>"",'Actual Figures'!D53-'Budget Figures'!D53,"") | E53: =IF('Actual Figures'!E53<>"",'Actual Figures'!E53-'Budget Figures'!E53,"") | F53: =IF('Actual Figures'!F53<>"",'Actual Figures'!F53-'Budget Figures'!F53,"") | G53: =IF('Actual Figures'!G53<>"",'Actual Figures'!G53-'Budget Figures'!G53,"") | H53: =IF('Actual Figures'!H53<>"",'Actual Figures'!H53-'Budget Figures'!H53,"") | I53: =IF('Actual Figures'!I53<>"",'Actual Figures'!I53-'Budget Figures'!I53,"") | J53: =IF('Actual Figures'!J53<>"",'Actual Figures'!J53-'Budget Figures'!J53,"") | K53: =IF('Actual Figures'!K53<>"",'Actual Figures'!K53-'Budget Figures'!K53,"") | ... O53: =IF('Actual Figures'!O53<>"",'Actual Figures'!O53-'Budget Figures'!O53,"") | Q53: =SUM(D53:O53) -> 0
C54: ='Budget Figures'!C54 -> Other 3 | D54: =IF('Actual Figures'!D54<>"",'Actual Figures'!D54-'Budget Figures'!D54,"") | E54: =IF('Actual Figures'!E54<>"",'Actual Figures'!E54-'Budget Figures'!E54,"") | F54: =IF('Actual Figures'!F54<>"",'Actual Figures'!F54-'Budget Figures'!F54,"") | G54: =IF('Actual Figures'!G54<>"",'Actual Figures'!G54-'Budget Figures'!G54,"") | H54: =IF('Actual Figures'!H54<>"",'Actual Figures'!H54-'Budget Figures'!H54,"") | I54: =IF('Actual Figures'!I54<>"",'Actual Figures'!I54-'Budget Figures'!I54,"") | J54: =IF('Actual Figures'!J54<>"",'Actual Figures'!J54-'Budget Figures'!J54,"") | K54: =IF('Actual Figures'!K54<>"",'Actual Figures'!K54-'Budget Figures'!K54,"") | ... O54: =IF('Actual Figures'!O54<>"",'Actual Figures'!O54-'Budget Figures'!O54,"") | Q54: =SUM(D54:O54) -> 0
C55: ='Budget Figures'!C55
C56: ='Budget Figures'!C56 -> SUBTOTAL WITHDRAWALS: | D56: =SUM(D20:D51) -> -1150 | E56: =SUM(E20:E51) -> -1150 | F56: =SUM(F20:F51) -> -1150 | G56: =SUM(G20:G51) -> -1150 | H56: =SUM(H20:H51) -> -1150 | I56: =SUM(I20:I51) -> -1150 | J56: =SUM(J20:J51) -> -1150 | K56: =SUM(K20:K51) -> -1150 | ... O56: =SUM(O20:O51) -> -1150 | Q56: =SUM(D56:O56) -> -13800
C57: ='Budget Figures'!C57
C58: ='Budget Figures'!C58 -> GST Related Deposits | D58: =IF('Actual Figures'!D58<>"",'Actual Figures'!D58-'Budget Figures'!D58,"") -> -10000 | E58: =IF('Actual Figures'!E58<>"",'Actual Figures'!E58-'Budget Figures'!E58,"") -> -17000 | F58: =IF('Actual Figures'!F58<>"",'Actual Figures'!F58-'Budget Figures'!F58,"") -> -25000 | G58: =IF('Actual Figures'!G58<>"",'Actual Figures'!G58-'Budget Figures'!G58,"") -> -1000 | H58: =IF('Actual Figures'!H58<>"",'Actual Figures'!H58-'Budget Figures'!H58,"") -> 0 | I58: =IF('Actual Figures'!I58<>"",'Actual Figures'!I58-'Budget Figures'!I58,"") -> -4000 | J58: =IF('Actual Figures'!J58<>"",'Actual Figures'!J58-'Budget Figures'!J58,"") -> 14500 | K58: =IF('Actual Figures'!K58<>"",'Actual Figures'!K58-'Budget Figures'!K58,"") -> 3000 | ... O58: =IF('Actual Figures'!O58<>"",'Actual Figures'!O58-'Budget Figures'!O58,"") -> -2800 | Q58: =IF('Actual Figures'!Q$62<>"",'Budget Figures'!Q58-'Actual Figures'!Q58,"") -> 0
C59: ='Budget Figures'!C59 -> GST Related Withdrawals | D59: =IF('Actual Figures'!D59<>"",'Actual Figures'!D59-'Budget Figures'!D59,"") -> 275 | E59: =IF('Actual Figures'!E59<>"",'Actual Figures'!E59-'Budget Figures'!E59,"") -> 275 | F59: =IF('Actual Figures'!F59<>"",'Actual Figures'!F59-'Budget Figures'!F59,"") -> 275 | G59: =IF('Actual Figures'!G59<>"",'Actual Figures'!G59-'Budget Figures'!G59,"") -> 275 | H59: =IF('Actual Figures'!H59<>"",'Actual Figures'!H59-'Budget Figures'!H59,"") -> 275 | I59: =IF('Actual Figures'!I59<>"",'Actual Figures'!I59-'Budget Figures'!I59,"") -> 275 | J59: =IF('Actual Figures'!J59<>"",'Actual Figures'!J59-'Budget Figures'!J59,"") -> 275 | K59: =IF('Actual Figures'!K59<>"",'Actual Figures'!K59-'Budget Figures'!K59,"") -> 275 | ... O59: =IF('Actual Figures'!O59<>"",'Actual Figures'!O59-'Budget Figures'!O59,"") -> 275 | Q59: =IF('Actual Figures'!Q$62<>"",'Budget Figures'!Q59-'Actual Figures'!Q59,"") -> 0
C61: GST MOVEMENTS
C62: Input (Expense Related) | D62: =IF('Actual Figures'!D62<>"",'Actual Figures'!D62-'Budget Figures'!D62,"") -> 35.869565 | E62: =IF('Actual Figures'!E62<>"",'Actual Figures'!E62-'Budget Figures'!E62,"") -> 35.869565 | F62: =IF('Actual Figures'!F62<>"",'Actual Figures'!F62-'Budget Figures'!F62,"") -> 35.869565 | G62: =IF('Actual Figures'!G62<>"",'Actual Figures'!G62-'Budget Figures'!G62,"") -> 35.869565 | H62: =IF('Actual Figures'!H62<>"",'Actual Figures'!H62-'Budget Figures'!H62,"") -> 35.869565 | I62: =IF('Actual Figures'!I62<>"",'Actual Figures'!I62-'Budget Figures'!I62,"") -> 35.869565 | J62: =IF('Actual Figures'!J62<>"",'Actual Figures'!J62-'Budget Figures'!J62,"") -> 35.869565 | K62: =IF('Actual Figures'!K62<>"",'Actual Figures'!K62-'Budget Figures'!K62,"") -> 35.869565 | ... O62: =IF('Actual Figures'!O62<>"",'Actual Figures'!O62-'Budget Figures'!O62,"") -> 35.869565 | Q62: =SUM(D62:O62) -> 430.43478
C63: Output (Income Related) | D63: =IF('Actual Figures'!D63<>"",'Actual Figures'!D63-'Budget Figures'!D63,"") -> -1304.3478 | E63: =IF('Actual Figures'!E63<>"",'Actual Figures'!E63-'Budget Figures'!E63,"") -> -2217.3913 | F63: =IF('Actual Figures'!F63<>"",'Actual Figures'!F63-'Budget Figures'!F63,"") -> -3260.8696 | G63: =IF('Actual Figures'!G63<>"",'Actual Figures'!G63-'Budget Figures'!G63,"") -> -130.43478 | H63: =IF('Actual Figures'!H63<>"",'Actual Figures'!H63-'Budget Figures'!H63,"") -> 0 | I63: =IF('Actual Figures'!I63<>"",'Actual Figures'!I63-'Budget Figures'!I63,"") -> -521.73913 | J63: =IF('Actual Figures'!J63<>"",'Actual Figures'!J63-'Budget Figures'!J63,"") -> 1891.3043 | K63: =IF('Actual Figures'!K63<>"",'Actual Figures'!K63-'Budget Figures'!K63,"") -> 391.30435 | ... O63: =IF('Actual Figures'!O63<>"",'Actual Figures'!O63-'Budget Figures'!O63,"") -> -365.21739 | Q63: =SUM(D63:O63) -> -6430.4348
C64: NET CASH RELATED TO GST | D64: =IF('Actual Figures'!D64<>"",'Actual Figures'!D64-'Budget Figures'!D64,"") -> 1340.2174 | E64: =IF('Actual Figures'!E64<>"",'Actual Figures'!E64-'Budget Figures'!E64,"") -> 2253.2609 | F64: =IF('Actual Figures'!F64<>"",'Actual Figures'!F64-'Budget Figures'!F64,"") -> 3296.7391 | G64: =IF('Actual Figures'!G64<>"",'Actual Figures'!G64-'Budget Figures'!G64,"") -> 166.30435 | H64: =IF('Actual Figures'!H64<>"",'Actual Figures'!H64-'Budget Figures'!H64,"") -> 35.869565 | I64: =IF('Actual Figures'!I64<>"",'Actual Figures'!I64-'Budget Figures'!I64,"") -> 557.6087 | J64: =IF('Actual Figures'!J64<>"",'Actual Figures'!J64-'Budget Figures'!J64,"") -> -1855.4348 | K64: =IF('Actual Figures'!K64<>"",'Actual Figures'!K64-'Budget Figures'!K64,"") -> -355.43478 | ... O64: =IF('Actual Figures'!O64<>"",'Actual Figures'!O64-'Budget Figures'!O64,"") -> 401.08696 | Q64: =SUM(D64:O64) -> 6860.8696
C66: NET CHANGE IN BANK BALANCE | D66: =IF('Actual Figures'!D66<>"",'Actual Figures'!D66-'Budget Figures'!D66,"") -> 2884.7826 | E66: =IF('Actual Figures'!E66<>"",'Actual Figures'!E66-'Budget Figures'!E66,"") -> -5028.2609 | F66: =IF('Actual Figures'!F66<>"",'Actual Figures'!F66-'Budget Figures'!F66,"") -> -14071.739 | G66: =IF('Actual Figures'!G66<>"",'Actual Figures'!G66-'Budget Figures'!G66,"") -> 13058.696 | H66: =IF('Actual Figures'!H66<>"",'Actual Figures'!H66-'Budget Figures'!H66,"") -> 14189.13 | I66: =IF('Actual Figures'!I66<>"",'Actual Figures'!I66-'Budget Figures'!I66,"") -> 9667.3913 | J66: =IF('Actual Figures'!J66<>"",'Actual Figures'!J66-'Budget Figures'!J66,"") -> 30580.435 | K66: =IF('Actual Figures'!K66<>"",'Actual Figures'!K66-'Budget Figures'!K66,"") -> 17580.435 | ... O66: =IF('Actual Figures'!O66<>"",'Actual Figures'!O66-'Budget Figures'!O66,"") -> 11023.913 | Q66: =SUM(D66:O66) -> 114539.13
C68: Opening Bank Balance: | D68: =IF('Actual Figures'!D68<>"",'Actual Figures'!D68-'Budget Figures'!D68,"") -> -3500 | E68: =IF('Actual Figures'!E68<>"",'Actual Figures'!E68-'Budget Figures'!E68,"") -> -615.21739 | F68: =IF('Actual Figures'!F68<>"",'Actual Figures'!F68-'Budget Figures'!F68,"") -> -5643.4783 | G68: =IF('Actual Figures'!G68<>"",'Actual Figures'!G68-'Budget Figures'!G68,"") -> -19715.217 | H68: =IF('Actual Figures'!H68<>"",'Actual Figures'!H68-'Budget Figures'!H68,"") -> -6656.5217 | I68: =IF('Actual Figures'!I68<>"",'Actual Figures'!I68-'Budget Figures'!I68,"") -> 7532.6087 | J68: =IF('Actual Figures'!J68<>"",'Actual Figures'!J68-'Budget Figures'!J68,"") -> 17200 | K68: =IF('Actual Figures'!K68<>"",'Actual Figures'!K68-'Budget Figures'!K68,"") -> 47780.435 | ... O68: =IF('Actual Figures'!O68<>"",'Actual Figures'!O68-'Budget Figures'!O68,"") -> 100015.22
C69: Add Total Deposits | D69: =IF('Actual Figures'!D69<>"",'Actual Figures'!D69-'Budget Figures'!D69,"") -> -11554.348 | E69: =IF('Actual Figures'!E69<>"",'Actual Figures'!E69-'Budget Figures'!E69,"") -> -19467.391 | F69: =IF('Actual Figures'!F69<>"",'Actual Figures'!F69-'Budget Figures'!F69,"") -> -28510.87 | G69: =IF('Actual Figures'!G69<>"",'Actual Figures'!G69-'Budget Figures'!G69,"") -> -1380.4348 | H69: =IF('Actual Figures'!H69<>"",'Actual Figures'!H69-'Budget Figures'!H69,"") -> -250 | I69: =IF('Actual Figures'!I69<>"",'Actual Figures'!I69-'Budget Figures'!I69,"") -> -4771.7391 | J69: =IF('Actual Figures'!J69<>"",'Actual Figures'!J69-'Budget Figures'!J69,"") -> 16141.304 | K69: =IF('Actual Figures'!K69<>"",'Actual Figures'!K69-'Budget Figures'!K69,"") -> 3141.3043 | ... O69: =IF('Actual Figures'!O69<>"",'Actual Figures'!O69-'Budget Figures'!O69,"") -> -3415.2174
D70: =IF('Actual Figures'!D70<>"",'Actual Figures'!D70-'Budget Figures'!D70,"") -> -15054.348 | E70: =IF('Actual Figures'!E70<>"",'Actual Figures'!E70-'Budget Figures'!E70,"") -> -20082.609 | F70: =IF('Actual Figures'!F70<>"",'Actual Figures'!F70-'Budget Figures'!F70,"") -> -34154.348 | G70: =IF('Actual Figures'!G70<>"",'Actual Figures'!G70-'Budget Figures'!G70,"") -> -21095.652 | H70: =IF('Actual Figures'!H70<>"",'Actual Figures'!H70-'Budget Figures'!H70,"") -> -6906.5217 | I70: =IF('Actual Figures'!I70<>"",'Actual Figures'!I70-'Budget Figures'!I70,"") -> 2760.8696 | J70: =IF('Actual Figures'!J70<>"",'Actual Figures'!J70-'Budget Figures'!J70,"") -> 33341.304 | K70: =IF('Actual Figures'!K70<>"",'Actual Figures'!K70-'Budget Figures'!K70,"") -> 50921.739 | ... O70: =IF('Actual Figures'!O70<>"",'Actual Figures'!O70-'Budget Figures'!O70,"") -> 96600
C71: Less Total Withdrawals | D71: =IF('Actual Figures'!D71<>"",'Actual Figures'!D71-'Budget Figures'!D71,"") -> -14439.13 | E71: =IF('Actual Figures'!E71<>"",'Actual Figures'!E71-'Budget Figures'!E71,"") -> -14439.13 | F71: =IF('Actual Figures'!F71<>"",'Actual Figures'!F71-'Budget Figures'!F71,"") -> -14439.13 | G71: =IF('Actual Figures'!G71<>"",'Actual Figures'!G71-'Budget Figures'!G71,"") -> -14439.13 | H71: =IF('Actual Figures'!H71<>"",'Actual Figures'!H71-'Budget Figures'!H71,"") -> -14439.13 | I71: =IF('Actual Figures'!I71<>"",'Actual Figures'!I71-'Budget Figures'!I71,"") -> -14439.13 | J71: =IF('Actual Figures'!J71<>"",'Actual Figures'!J71-'Budget Figures'!J71,"") -> -14439.13 | K71: =IF('Actual Figures'!K71<>"",'Actual Figures'!K71-'Budget Figures'!K71,"") -> -14439.13 | ... O71: =IF('Actual Figures'!O71<>"",'Actual Figures'!O71-'Budget Figures'!O71,"") -> -14439.13
C72: Closing Bank Balance | D72: =IF('Actual Figures'!D72<>"",'Actual Figures'!D72-'Budget Figures'!D72,"") -> -615.21739 | E72: =IF('Actual Figures'!E72<>"",'Actual Figures'!E72-'Budget Figures'!E72,"") -> -5643.4783 | F72: =IF('Actual Figures'!F72<>"",'Actual Figures'!F72-'Budget Figures'!F72,"") -> -19715.217 | G72: =IF('Actual Figures'!G72<>"",'Actual Figures'!G72-'Budget Figures'!G72,"") -> -6656.5217 | H72: =IF('Actual Figures'!H72<>"",'Actual Figures'!H72-'Budget Figures'!H72,"") -> 7532.6087 | I72: =IF('Actual Figures'!I72<>"",'Actual Figures'!I72-'Budget Figures'!I72,"") -> 17200 | J72: =IF('Actual Figures'!J72<>"",'Actual Figures'!J72-'Budget Figures'!J72,"") -> 47780.435 | K72: =IF('Actual Figures'!K72<>"",'Actual Figures'!K72-'Budget Figures'!K72,"") -> 65360.87 | ... O72: =IF('Actual Figures'!O72<>"",'Actual Figures'!O72-'Budget Figures'!O72,"") -> 111039.13

Sheet Reports
E64: ='Budget Figures'!D6 -> 44287 | F64: ='Budget Figures'!E6 -> 44317 | G64: ='Budget Figures'!F6 -> 44348 | H64: ='Budget Figures'!G6 -> 44378 | I64: ='Budget Figures'!H6 -> 44409 | J64: ='Budget Figures'!I6 -> 44440 | K64: ='Budget Figures'!J6 -> 44470 | L64: ='Budget Figures'!K6 -> 44501 | ... P64: ='Budget Figures'!O6 -> 44621
D65: Budget Revenue | E65: ='Budget Figures'!D16 -> 25250 | F65: ='Budget Figures'!E16 -> 35250 | G65: ='Budget Figures'!F16 -> 45250 | H65: ='Budget Figures'!G16 -> 15250 | I65: ='Budget Figures'!H16 -> 25250 | J65: ='Budget Figures'!I16 -> 30250 | K65: ='Budget Figures'!J16 -> 12750 | L65: ='Budget Figures'!K16 -> 25250 | ... P65: ='Budget Figures'!O16 -> 36050
D66: Actual Revenue | E66: ='Actual Figures'!D16 -> 15000 | F66: ='Actual Figures'!E16 -> 18000 | G66: ='Actual Figures'!F16 -> 20000 | H66: ='Actual Figures'!G16 -> 14000 | I66: ='Actual Figures'!H16 -> 25000 | J66: ='Actual Figures'!I16 -> 26000 | K66: ='Actual Figures'!J16 -> 27000 | L66: ='Actual Figures'!K16 -> 28000 | ... P66: ='Actual Figures'!O16 -> 33000
E70: =E64 -> 44287 | F70: =F64 -> 44317 | G70: =G64 -> 44348 | H70: =H64 -> 44378 | I70: =I64 -> 44409 | J70: =J64 -> 44440 | K70: =K64 -> 44470 | L70: =L64 -> 44501 | ... P70: =P64 -> 44621
D71: Budget Expenses | E71: ='Budget Figures'!D56 -> 17500 | F71: ='Budget Figures'!E56 -> 17500 | G71: ='Budget Figures'!F56 -> 17500 | H71: ='Budget Figures'!G56 -> 17500 | I71: ='Budget Figures'!H56 -> 17500 | J71: ='Budget Figures'!I56 -> 17500 | K71: ='Budget Figures'!J56 -> 17500 | L71: ='Budget Figures'!K56 -> 17500 | ... P71: ='Budget Figures'!O56 -> 17500
D72: Actual Expenses | E72: ='Actual Figures'!D56 -> 3025 | F72: ='Actual Figures'!E56 -> 3025 | G72: ='Actual Figures'!F56 -> 3025 | H72: ='Actual Figures'!G56 -> 3025 | I72: ='Actual Figures'!H56 -> 3025 | J72: ='Actual Figures'!I56 -> 3025 | K72: ='Actual Figures'!J56 -> 3025 | L72: ='Actual Figures'!K56 -> 3025 | ... P72: ='Actual Figures'!O56 -> 3025
