Workbook

Sheet Supplier 1 Inputs
F3: Total Days Elapsed From Order to Retail | K3: =F6+K5+F13 -> 154 | L3: =F6+L5+F13 -> 149 | M3: =F6+M5+F13 -> 144
U4: Stock Turn Days | W4: Shipment % | AO4: Yes | AP4: =K6 -> Sea | AQ4: =W5 -> SkyRockets
H5: Refrigerated Surcharge | J5: Container Size | K5: 25 | L5: 20 | M5: 15 | N5: Total Shipping Days | W5: SkyRockets | X5: Steady Eddy | Y5: Slow Burn | AO5: No | AP5: =L6 -> Air | AQ5: =X5 -> Steady Eddy
D6: Manufacture Days | F6: 120 | K6: Sea | L6: Air | M6: Express | AP6: =M6 -> Express | AQ6: =Y5 -> Slow Burn
D7: Order Deposit % | F7: 0.6 | H7: 2500 | J7: 10 ft | K7: 3500 | L7: 5000 | M7: 6500 | U7: 30 | W7: 0.4 | X7: 0.2 | Y7: 0.1
D8: Interest Cover % | F8: 0.06 | H8: 4000 | J8: 20 ft | K8: 8000 | L8: 10000 | M8: 11500 | U8: 60 | W8: 0.25 | X8: 0.3 | Y8: 0.3
D9: Currency Movement % | F9: 0.1 | H9: 6000 | J9: 40 ft | K9: 12000 | L9: 14000 | M9: 15500 | U9: 90 | W9: 0.2 | X9: 0.2 | Y9: 0.4
D10: Order Balance Due Days | F10: 91 | U10: 120 | W10: 0.15 | X10: 0.3 | Y10: 0.2
H12: Deposit Pmts | J12: =J54 -> 64585.8 | K12: =K54 -> 23379.6 | L12: =L54 -> 56586.6 | M12: =M54 -> 33959.4 | N12: =N54 -> 47503.8 | O12: =O54 -> 60406.2 | P12: =P54 -> 17821.8 | Q12: =Q54 -> 17206.2 | ... U12: =U54 -> 8024.4 | W12: =100%-sum(W7:W10) -> 0 | X12: =100%-sum(X7:X10) -> 0 | Y12: =100%-sum(Y7:Y10) -> 0
D13: Pre-Retail Prep Days | F13: 9 | H13: Balance Pmts | J13: =J75 -> 0 | K13: =K75 -> 0 | L13: =L75 -> 0 | M13: =M75 -> 44798.625 | N13: =N75 -> 16216.783 | O13: =O75 -> 39250.142 | P13: =P75 -> 23555.246 | Q13: =Q75 -> 32950.043 | ... U13: =U75 -> 32683.273 | W13: Up to | X13: Up to | Y13: Up to | AA13: =U4 -> Stock Turn Days
H15: Total Import Pmts | J15: =sum(J12:J13) -> 64585.8 | K15: =sum(K12:K13) -> 23379.6 | L15: =sum(L12:L13) -> 56586.6 | M15: =sum(M12:M13) -> 78758.025 | N15: =sum(N12:N13) -> 63720.583 | O15: =sum(O12:O13) -> 99656.342 | P15: =sum(P12:P13) -> 41377.046 | Q15: =sum(Q12:Q13) -> 50156.243 | ... U15: =sum(U12:U13) -> 40707.673 | W15: =U8 -> 60 | X15: =U9 -> 90 | Y15: =U10 -> 120
H17: Projected Sales
D19: Stock Items | F19: Unit Cost | H19: Item Popularity | J19: Jan | K19: Feb | L19: Mar | M19: Apr | N19: May | O19: Jun | P19: Jul | Q19: Aug | R19: Sep | S19: Oct | T19: Nov | U19: Dec | W19: New Stock Retail Markup % | X19: Std Retail Markup % | Y19: Runout Stock Markup % | AA19: New Stock Retail Price | AB19: Std Retail Price | AC19: Runout Stock Price
D21: Stock 1 | F21: 145 | H21: SkyRockets | J21: 34 | K21: 12 | L21: 35 | M21: 24 | N21: 12 | O21: 46 | P21: 14 | Q21: 12 | R21: 36 | S21: 4 | T21: 2 | U21: 16 | W21: 1.85 | X21: 1.52 | Y21: 1.22 | AA21: =(F21*W21)+F21 -> 413.25 | AB21: =(F21*X21)+F21 -> 365.4 | AC21: =(F21*Y21)+F21 -> 321.9
D22: Stock 2 | F22: 146 | H22: Steady Eddy | J22: 33 | K22: 14 | L22: 35 | M22: 23 | N22: 14 | O22: 45 | P22: 13 | R22: 25 | S22: 3 | U22: 15 | W22: 1.85 | X22: 1.52 | Y22: 1.22 | AA22: =(F22*W22)+F22 -> 416.1 | AB22: =(F22*X22)+F22 -> 367.92 | AC22: =(F22*Y22)+F22 -> 324.12
D23: Stock 3 | F23: 147 | H23: Slow Burn | J23: 35 | L23: 34 | N23: 16 | O23: 44 | P23: 15 | S23: 5 | W23: 1.85 | X23: 1.52 | Y23: 1.22 | AA23: =(F23*W23)+F23 -> 418.95 | AB23: =(F23*X23)+F23 -> 370.44 | AC23: =(F23*Y23)+F23 -> 326.34
D24: Stock 4 | F24: 148 | H24: Steady Eddy | J24: 38 | L24: 39 | N24: 18 | O24: 49 | S24: 8 | T24: 18 | W24: 1.85 | X24: 1.52 | Y24: 1.22 | AA24: =(F24*W24)+F24 -> 421.8 | AB24: =(F24*X24)+F24 -> 372.96 | AC24: =(F24*Y24)+F24 -> 328.56
D25: Stock 5 | F25: 149 | H25: SkyRockets | J25: 36 | L25: 38 | M25: 26 | N25: 11 | O25: 48 | Q25: 11 | R25: 28 | S25: 6 | T25: 17 | W25: 1.85 | X25: 1.52 | Y25: 1.22 | AA25: =(F25*W25)+F25 -> 424.65 | AB25: =(F25*X25)+F25 -> 375.48 | AC25: =(F25*Y25)+F25 -> 330.78
D26: Stock 6 | F26: 150 | H26: Slow Burn | J26: 35 | K26: 13 | M26: 25 | O26: 47 | Q26: 13 | R26: 37 | T26: 13 | U26: 17 | W26: 1.85 | X26: 1.52 | Y26: 1.22 | AA26: =(F26*W26)+F26 -> 427.5 | AB26: =(F26*X26)+F26 -> 378 | AC26: =(F26*Y26)+F26 -> 333
D27: Stock 7 | F27: 151 | H27: SkyRockets | J27: 34 | K27: 15 | M27: 24 | Q27: 15 | R27: 33 | T27: 15 | U27: 3 | W27: 1.85 | X27: 1.52 | Y27: 1.22 | AA27: =(F27*W27)+F27 -> 430.35 | AB27: =(F27*X27)+F27 -> 380.52 | AC27: =(F27*Y27)+F27 -> 335.22
D28: Stock 8 | F28: 152 | H28: SkyRockets | J28: 37 | K28: 17 | M28: 27 | N28: 37 | Q28: 17 | S28: 27 | T28: 17 | U28: 5 | W28: 1.85 | X28: 1.52 | Y28: 1.22 | AA28: =(F28*W28)+F28 -> 433.2 | AB28: =(F28*X28)+F28 -> 383.04 | AC28: =(F28*Y28)+F28 -> 337.44
D29: Stock 9 | F29: 153 | H29: Steady Eddy | J29: 34 | K29: 12 | L29: 37 | M29: 24 | N29: 32 | Q29: 12 | S29: 24 | T29: 12 | U29: 7 | W29: 1.85 | X29: 1.52 | Y29: 1.22 | AA29: =(F29*W29)+F29 -> 436.05 | AB29: =(F29*X29)+F29 -> 385.56 | AC29: =(F29*Y29)+F29 -> 339.66
D30: Stock 10 | F30: 154 | H30: Steady Eddy | J30: 33 | K30: 14 | L30: 31 | M30: 23 | N30: 34 | O30: 31 | Q30: 14 | R30: 41 | S30: 23 | U30: 1 | W30: 1.85 | X30: 1.52 | Y30: 1.22 | AA30: =(F30*W30)+F30 -> 438.9 | AB30: =(F30*X30)+F30 -> 388.08 | AC30: =(F30*Y30)+F30 -> 341.88
D31: Stock 11 | F31: 155 | H31: Steady Eddy | J31: 35 | K31: 16 | L31: 35 | N31: 36 | O31: 35 | P31: 15 | Q31: 16 | R31: 55 | S31: 25 | U31: 5 | W31: 1.85 | X31: 1.52 | Y31: 1.22 | AA31: =(F31*W31)+F31 -> 441.75 | AB31: =(F31*X31)+F31 -> 390.6 | AC31: =(F31*Y31)+F31 -> 344.1
D32: Stock 12 | F32: 156 | H32: Steady Eddy | J32: 38 | K32: 18 | L32: 39 | N32: 38 | O32: 39 | P32: 18 | Q32: 18 | R32: 69 | S32: 28 | T32: 18 | W32: 1.85 | X32: 1.52 | Y32: 1.22 | AA32: =(F32*W32)+F32 -> 444.6 | AB32: =(F32*X32)+F32 -> 393.12 | AC32: =(F32*Y32)+F32 -> 346.32
D33: Stock 13 | F33: 157 | H33: Steady Eddy | J33: 36 | K33: 13 | L33: 38 | N33: 33 | O33: 38 | P33: 16 | Q33: 13 | S33: 26 | T33: 13 | W33: 1.85 | X33: 1.52 | Y33: 1.22 | AA33: =(F33*W33)+F33 -> 447.45 | AB33: =(F33*X33)+F33 -> 395.64 | AC33: =(F33*Y33)+F33 -> 348.54
D34: Stock 14 | F34: 158 | H34: SkyRockets | J34: 35 | K34: 15 | L34: 35 | M34: 25 | P34: 15 | T34: 15 | W34: 1.85 | X34: 1.52 | Y34: 1.22 | AA34: =(F34*W34)+F34 -> 450.3 | AB34: =(F34*X34)+F34 -> 398.16 | AC34: =(F34*Y34)+F34 -> 350.76
D35: Stock 15 | F35: 159 | H35: SkyRockets | J35: 34 | K35: 17 | L35: 32 | M35: 24 | P35: 14 | R35: 42 | T35: 17 | W35: 1.85 | X35: 1.52 | Y35: 1.22 | AA35: =(F35*W35)+F35 -> 453.15 | AB35: =(F35*X35)+F35 -> 400.68 | AC35: =(F35*Y35)+F35 -> 352.98
D36: Stock 16 | F36: 160 | H36: SkyRockets | J36: 37 | K36: 19 | L36: 36 | M36: 27 | N36: 49 | O36: 46 | P36: 17 | R36: 36 | T36: 19 | W36: 1.85 | X36: 1.52 | Y36: 1.22 | AA36: =(F36*W36)+F36 -> 456 | AB36: =(F36*X36)+F36 -> 403.2 | AC36: =(F36*Y36)+F36 -> 355.2
D37: Stock 17 | F37: 161 | H37: Slow Burn | J37: 36 | K37: 11 | L37: 35 | M37: 26 | N37: 41 | O37: 45 | P37: 16 | R37: 25 | S37: 6 | T37: 11 | W37: 1.85 | X37: 1.52 | Y37: 1.22 | AA37: =(F37*W37)+F37 -> 458.85 | AB37: =(F37*X37)+F37 -> 405.72 | AC37: =(F37*Y37)+F37 -> 357.42
D38: Stock 18 | F38: 162 | H38: Slow Burn | J38: 32 | K38: 12 | L38: 34 | M38: 22 | N38: 42 | O38: 44 | P38: 12 | Q38: 12 | R38: 24 | S38: 2 | T38: 12 | U38: 4 | W38: 1.85 | X38: 1.52 | Y38: 1.22 | AA38: =(F38*W38)+F38 -> 461.7 | AB38: =(F38*X38)+F38 -> 408.24 | AC38: =(F38*Y38)+F38 -> 359.64
D39: Stock 19 | F39: 163 | H39: SkyRockets | J39: 31 | K39: 14 | L39: 37 | M39: 21 | N39: 44 | O39: 47 | P39: 11 | Q39: 14 | R39: 17 | S39: 1 | T39: 14 | U39: 7 | W39: 1.85 | X39: 1.52 | Y39: 1.22 | AA39: =(F39*W39)+F39 -> 464.55 | AB39: =(F39*X39)+F39 -> 410.76 | AC39: =(F39*Y39)+F39 -> 361.86
D40: Stock 20 | F40: 164 | H40: Steady Eddy | J40: 34 | K40: 18 | L40: 38 | M40: 24 | N40: 48 | O40: 48 | P40: 14 | Q40: 18 | R40: 38 | S40: 4 | T40: 18 | U40: 8 | W40: 1.85 | X40: 1.52 | Y40: 1.22 | AA40: =(F40*W40)+F40 -> 467.4 | AB40: =(F40*X40)+F40 -> 413.28 | AC40: =(F40*Y40)+F40 -> 364.08
H42: Refrigerated | J42: Yes | K42: No | L42: Yes | M42: Yes | N42: No | O42: No | P42: No | Q42: Yes | R42: No | S42: No | T42: Yes | U42: No
H43: Container Size | J43: 10 ft | K43: 20 ft | L43: 40 ft | M43: 20 ft | N43: 10 ft | O43: 20 ft | P43: 40 ft | Q43: 10 ft | R43: 10 ft | S43: 20 ft | T43: 40 ft | U43: 20 ft
H44: Shipping Speed | J44: Air | K44: Sea | L44: Express | M44: Express | N44: Sea | O44: Air | P44: Express | Q44: Sea | R44: Air | S44: Express | T44: Sea | U44: Express
H45: # of Containers | J45: 1 | K45: 1.5 | L45: 2 | M45: 1 | N45: 1.5 | O45: 2 | P45: 1 | Q45: 1.25 | R45: 1 | S45: 1 | T45: 1 | U45: 1
H47: Shipping Costs | J47: =J98 -> 0 | K47: =K98 -> 0 | L47: =L98 -> 0 | M47: =M98 -> 7500 | N47: =N98 -> 12000 | O47: =O98 -> 43000 | P47: =P98 -> 11500 | Q47: =Q98 -> 5250 | ... U47: =U98 -> 7500
D50: Stock/ Manufacture Pmts
F51: =sum(J51:U51) -> 4469 | H51: Total Units | J51: =sum(J21:J40) -> 697 | K51: =sum(K21:K40) -> 250 | L51: =sum(L21:L40) -> 608 | M51: =sum(M21:M40) -> 365 | N51: =sum(N21:N40) -> 505 | O51: =sum(O21:O40) -> 652 | P51: =sum(P21:P40) -> 190 | Q51: =sum(Q21:Q40) -> 185 | ... U51: =sum(U21:U40) -> 88
F52: =sum(J52:U52) -> 693271 | H52: Total Unit Cost | J52: =J21*$F$21+J22*$F$22+J23*$F$23+J24*$F$24+J25*$F$25+J26*$F$26+J27*$F$27+J28*$F$28+J29*$F$29+J30*$F$30+J31*$F$31+J32*$F$32+J33*$F$33+J34*$F$34+J35*$F$35+J36*$F$36+J37*$F$37+J38*$F$38+J39*$F$39+J40*$F$40 -> 107643 | K52: =K21*$F$21+K22*$F$22+K23*$F$23+K24*$F$24+K25*$F$25+K26*$F$26+K27*$F$27+K28*$F$28+K29*$F$29+K30*$F$30+K31*$F$31+K32*$F$32+K33*$F$33+K34*$F$34+K35*$F$35+K36*$F$36+K37*$F$37+K38*$F$38+K39*$F$39+K40*$F$40 -> 38966 | L52: =L21*$F$21+L22*$F$22+L23*$F$23+L24*$F$24+L25*$F$25+L26*$F$26+L27*$F$27+L28*$F$28+L29*$F$29+L30*$F$30+L31*$F$31+L32*$F$32+L33*$F$33+L34*$F$34+L35*$F$35+L36*$F$36+L37*$F$37+L38*$F$38+L39*$F$39+L40*$F$40 -> 94311 | M52: =M21*$F$21+M22*$F$22+M23*$F$23+M24*$F$24+M25*$F$25+M26*$F$26+M27*$F$27+M28*$F$28+M29*$F$29+M30*$F$30+M31*$F$31+M32*$F$32+M33*$F$33+M34*$F$34+M35*$F$35+M36*$F$36+M37*$F$37+M38*$F$38+M39*$F$39+M40*$F$40 -> 56599 | N52: =N21*$F$21+N22*$F$22+N23*$F$23+N24*$F$24+N25*$F$25+N26*$F$26+N27*$F$27+N28*$F$28+N29*$F$29+N30*$F$30+N31*$F$31+N32*$F$32+N33*$F$33+N34*$F$34+N35*$F$35+N36*$F$36+N37*$F$37+N38*$F$38+N39*$F$39+N40*$F$40 -> 79173 | O52: =O21*$F$21+O22*$F$22+O23*$F$23+O24*$F$24+O25*$F$25+O26*$F$26+O27*$F$27+O28*$F$28+O29*$F$29+O30*$F$30+O31*$F$31+O32*$F$32+O33*$F$33+O34*$F$34+O35*$F$35+O36*$F$36+O37*$F$37+O38*$F$38+O39*$F$39+O40*$F$40 -> 100677 | P52: =P21*$F$21+P22*$F$22+P23*$F$23+P24*$F$24+P25*$F$25+P26*$F$26+P27*$F$27+P28*$F$28+P29*$F$29+P30*$F$30+P31*$F$31+P32*$F$32+P33*$F$33+P34*$F$34+P35*$F$35+P36*$F$36+P37*$F$37+P38*$F$38+P39*$F$39+P40*$F$40 -> 29703 | Q52: =Q21*$F$21+Q22*$F$22+Q23*$F$23+Q24*$F$24+Q25*$F$25+Q26*$F$26+Q27*$F$27+Q28*$F$28+Q29*$F$29+Q30*$F$30+Q31*$F$31+Q32*$F$32+Q33*$F$33+Q34*$F$34+Q35*$F$35+Q36*$F$36+Q37*$F$37+Q38*$F$38+Q39*$F$39+Q40*$F$40 -> 28677 | ... U52: =U21*$F$21+U22*$F$22+U23*$F$23+U24*$F$24+U25*$F$25+U26*$F$26+U27*$F$27+U28*$F$28+U29*$F$29+U30*$F$30+U31*$F$31+U32*$F$32+U33*$F$33+U34*$F$34+U35*$F$35+U36*$F$36+U37*$F$37+U38*$F$38+U39*$F$39+U40*$F$40 -> 13374
F54: =sum(J54:U54) -> 415962.6 | H54: Deposit | J54: =J52*$F$7 -> 64585.8 | K54: =K52*$F$7 -> 23379.6 | L54: =L52*$F$7 -> 56586.6 | M54: =M52*$F$7 -> 33959.4 | N54: =N52*$F$7 -> 47503.8 | O54: =O52*$F$7 -> 60406.2 | P54: =P52*$F$7 -> 17821.8 | Q54: =Q52*$F$7 -> 17206.2 | ... U54: =U52*$F$7 -> 8024.4
D56: =F54+F56 -> 671612.7 | F56: =sum(J75:U75) -> 255650.1 | H56: Balance Due | J56: =J52-J54 -> 43057.2 | K56: =K52-K54 -> 15586.4 | L56: =L52-L54 -> 37724.4 | M56: =M52-M54 -> 22639.6 | N56: =N52-N54 -> 31669.2 | O56: =O52-O54 -> 40270.8 | P56: =P52-P54 -> 11881.2 | Q56: =Q52-Q54 -> 11470.8 | ... U56: =U52-U54 -> 5349.6
H58: Balance Interest | J58: =J56*$F$8/12*$F$10/30 -> 653.0342 | K58: =K56*$F$8/12*$F$10/30 -> 236.39373 | L58: =L56*$F$8/12*$F$10/30 -> 572.1534 | M58: =M56*$F$8/12*$F$10/30 -> 343.36727 | N58: =N56*$F$8/12*$F$10/30 -> 480.3162 | O58: =O56*$F$8/12*$F$10/30 -> 610.7738 | P58: =P56*$F$8/12*$F$10/30 -> 180.1982 | Q58: =Q56*$F$8/12*$F$10/30 -> 173.9738 | ... U58: =U56*$F$8/12*$F$10/30 -> 81.1356
H59: FX Loss | J59: =J56*$F$9/12*$F$10/30 -> 1088.3903 | K59: =K56*$F$9/12*$F$10/30 -> 393.98956 | L59: =L56*$F$9/12*$F$10/30 -> 953.589 | M59: =M56*$F$9/12*$F$10/30 -> 572.27878 | N59: =N56*$F$9/12*$F$10/30 -> 800.527 | O59: =O56*$F$9/12*$F$10/30 -> 1017.9563 | P59: =P56*$F$9/12*$F$10/30 -> 300.33033 | Q59: =Q56*$F$9/12*$F$10/30 -> 289.95633 | ... U59: =U56*$F$9/12*$F$10/30 -> 135.226
H60: Interest Total | J60: =J58+J59 -> 1741.4245 | K60: =K58+K59 -> 630.38329 | L60: =L58+L59 -> 1525.7424 | M60: =M58+M59 -> 915.64604 | N60: =N58+N59 -> 1280.8432 | O60: =O58+O59 -> 1628.7301 | P60: =P58+P59 -> 480.52853 | Q60: =Q58+Q59 -> 463.93013 | ... U60: =U58+U59 -> 216.3616
G62: 1 | H62: 30 | J62: =if($F$10<=$H$62,J56+J60,0) -> 0 | K62: =if($F$10<=$H$62,K56+K60,0) -> 0 | L62: =if($F$10<=$H$62,L56+L60,0) -> 0 | M62: =if($F$10<=$H$62,M56+M60,0) -> 0 | N62: =if($F$10<=$H$62,N56+N60,0) -> 0 | O62: =if($F$10<=$H$62,O56+O60,0) -> 0 | P62: =if($F$10<=$H$62,P56+P60,0) -> 0 | Q62: =if($F$10<=$H$62,Q56+Q60,0) -> 0 | ... U62: =if($F$10<=$H$62,U56+U60,0) -> 0
G63: 2 | H63: 60 | K63: =if(and($F$10>$H$62,$F$10<=$H$63),J56+J60,0) -> 0 | L63: =if(and($F$10>$H$62,$F$10<=$H$63),K56+K60,0) -> 0 | M63: =if(and($F$10>$H$62,$F$10<=$H$63),L56+L60,0) -> 0 | N63: =if(and($F$10>$H$62,$F$10<=$H$63),M56+M60,0) -> 0 | O63: =if(and($F$10>$H$62,$F$10<=$H$63),N56+N60,0) -> 0 | P63: =if(and($F$10>$H$62,$F$10<=$H$63),O56+O60,0) -> 0 | Q63: =if(and($F$10>$H$62,$F$10<=$H$63),P56+P60,0) -> 0 | R63: =if(and($F$10>$H$62,$F$10<=$H$63),Q56+Q60,0) -> 0 | ... V63: =if(and($F$10>$H$62,$F$10<=$H$63),U56+U60,0) -> 0
G64: 3 | H64: 90 | L64: =if(and($F$10>$H$63,$F$10<=$H$64),J56+J60,0) -> 0 | M64: =if(and($F$10>$H$63,$F$10<=$H$64),K56+K60,0) -> 0 | N64: =if(and($F$10>$H$63,$F$10<=$H$64),L56+L60,0) -> 0 | O64: =if(and($F$10>$H$63,$F$10<=$H$64),M56+M60,0) -> 0 | P64: =if(and($F$10>$H$63,$F$10<=$H$64),N56+N60,0) -> 0 | Q64: =if(and($F$10>$H$63,$F$10<=$H$64),O56+O60,0) -> 0 | R64: =if(and($F$10>$H$63,$F$10<=$H$64),P56+P60,0) -> 0 | S64: =if(and($F$10>$H$63,$F$10<=$H$64),Q56+Q60,0) -> 0 | ... W64: =if(and($F$10>$H$63,$F$10<=$H$64),U56+U60,0) -> 0
G65: 4 | H65: 120 | M65: =if(and($F$10>$H$64,$F$10<=$H$65),J56+J60,0) -> 44798.625 | N65: =if(and($F$10>$H$64,$F$10<=$H$65),K56+K60,0) -> 16216.783 | O65: =if(and($F$10>$H$64,$F$10<=$H$65),L56+L60,0) -> 39250.142 | P65: =if(and($F$10>$H$64,$F$10<=$H$65),M56+M60,0) -> 23555.246 | Q65: =if(and($F$10>$H$64,$F$10<=$H$65),N56+N60,0) -> 32950.043 | R65: =if(and($F$10>$H$64,$F$10<=$H$65),O56+O60,0) -> 41899.53 | S65: =if(and($F$10>$H$64,$F$10<=$H$65),P56+P60,0) -> 12361.729 | T65: =if(and($F$10>$H$64,$F$10<=$H$65),Q56+Q60,0) -> 11934.73 | ... X65: =if(and($F$10>$H$64,$F$10<=$H$65),U56+U60,0) -> 5565.9616
G66: 5 | H66: 150 | N66: =if(and($F$10>$H$65,$F$10<=$H$66),J56+J60,0) -> 0 | O66: =if(and($F$10>$H$65,$F$10<=$H$66),K56+K60,0) -> 0 | P66: =if(and($F$10>$H$65,$F$10<=$H$66),L56+L60,0) -> 0 | Q66: =if(and($F$10>$H$65,$F$10<=$H$66),M56+M60,0) -> 0 | R66: =if(and($F$10>$H$65,$F$10<=$H$66),N56+N60,0) -> 0 | S66: =if(and($F$10>$H$65,$F$10<=$H$66),O56+O60,0) -> 0 | T66: =if(and($F$10>$H$65,$F$10<=$H$66),P56+P60,0) -> 0 | U66: =if(and($F$10>$H$65,$F$10<=$H$66),Q56+Q60,0) -> 0 | ... Y66: =if(and($F$10>$H$65,$F$10<=$H$66),U56+U60,0) -> 0
G67: 6 | H67: 180 | O67: =if(and($F$10>$H$66,$F$10<=$H$67),J56+J60,0) -> 0 | P67: =if(and($F$10>$H$66,$F$10<=$H$67),K56+K60,0) -> 0 | Q67: =if(and($F$10>$H$66,$F$10<=$H$67),L56+L60,0) -> 0 | R67: =if(and($F$10>$H$66,$F$10<=$H$67),M56+M60,0) -> 0 | S67: =if(and($F$10>$H$66,$F$10<=$H$67),N56+N60,0) -> 0 | T67: =if(and($F$10>$H$66,$F$10<=$H$67),O56+O60,0) -> 0 | U67: =if(and($F$10>$H$66,$F$10<=$H$67),P56+P60,0) -> 0 | V67: =if(and($F$10>$H$66,$F$10<=$H$67),Q56+Q60,0) -> 0 | ... Z67: =if(and($F$10>$H$66,$F$10<=$H$67),U56+U60,0) -> 0
G68: 7 | H68: 210 | P68: =if(and($F$10>$H$67,$F$10<=$H$68),J56+J60,0) -> 0 | Q68: =if(and($F$10>$H$67,$F$10<=$H$68),K56+K60,0) -> 0 | R68: =if(and($F$10>$H$67,$F$10<=$H$68),L56+L60,0) -> 0 | S68: =if(and($F$10>$H$67,$F$10<=$H$68),M56+M60,0) -> 0 | T68: =if(and($F$10>$H$67,$F$10<=$H$68),N56+N60,0) -> 0 | U68: =if(and($F$10>$H$67,$F$10<=$H$68),O56+O60,0) -> 0 | V68: =if(and($F$10>$H$67,$F$10<=$H$68),P56+P60,0) -> 0 | W68: =if(and($F$10>$H$67,$F$10<=$H$68),Q56+Q60,0) -> 0 | ... AA68: =if(and($F$10>$H$67,$F$10<=$H$68),U56+U60,0) -> 0
G69: 8 | H69: 240 | Q69: =if(and($F$10>$H$68,$F$10<=$H$69),J56+J60,0) -> 0 | R69: =if(and($F$10>$H$68,$F$10<=$H$69),K56+K60,0) -> 0 | S69: =if(and($F$10>$H$68,$F$10<=$H$69),L56+L60,0) -> 0 | T69: =if(and($F$10>$H$68,$F$10<=$H$69),M56+M60,0) -> 0 | U69: =if(and($F$10>$H$68,$F$10<=$H$69),N56+N60,0) -> 0 | V69: =if(and($F$10>$H$68,$F$10<=$H$69),O56+O60,0) -> 0 | W69: =if(and($F$10>$H$68,$F$10<=$H$69),P56+P60,0) -> 0 | X69: =if(and($F$10>$H$68,$F$10<=$H$69),Q56+Q60,0) -> 0 | ... AB69: =if(and($F$10>$H$68,$F$10<=$H$69),U56+U60,0) -> 0
G70: 9 | H70: 270 | R70: =if(and($F$10>$H$69,$F$10<=$H$70),J56+J60,0) -> 0 | S70: =if(and($F$10>$H$69,$F$10<=$H$70),K56+K60,0) -> 0 | T70: =if(and($F$10>$H$69,$F$10<=$H$70),L56+L60,0) -> 0 | U70: =if(and($F$10>$H$69,$F$10<=$H$70),M56+M60,0) -> 0 | V70: =if(and($F$10>$H$69,$F$10<=$H$70),N56+N60,0) -> 0 | W70: =if(and($F$10>$H$69,$F$10<=$H$70),O56+O60,0) -> 0 | X70: =if(and($F$10>$H$69,$F$10<=$H$70),P56+P60,0) -> 0 | Y70: =if(and($F$10>$H$69,$F$10<=$H$70),Q56+Q60,0) -> 0 | ... AC70: =if(and($F$10>$H$69,$F$10<=$H$70),U56+U60,0) -> 0
G71: 10 | H71: 300 | S71: =if(and($F$10>$H$70,$F$10<=$H$71),J56+J60,0) -> 0 | T71: =if(and($F$10>$H$70,$F$10<=$H$71),K56+K60,0) -> 0 | U71: =if(and($F$10>$H$70,$F$10<=$H$71),L56+L60,0) -> 0 | V71: =if(and($F$10>$H$70,$F$10<=$H$71),M56+M60,0) -> 0 | W71: =if(and($F$10>$H$70,$F$10<=$H$71),N56+N60,0) -> 0 | X71: =if(and($F$10>$H$70,$F$10<=$H$71),O56+O60,0) -> 0 | Y71: =if(and($F$10>$H$70,$F$10<=$H$71),P56+P60,0) -> 0 | Z71: =if(and($F$10>$H$70,$F$10<=$H$71),Q56+Q60,0) -> 0 | ... AD71: =if(and($F$10>$H$70,$F$10<=$H$71),U56+U60,0) -> 0
G72: 11 | H72: 330 | T72: =if(and($F$10>$H$71,$F$10<=$H$72),J56+J60,0) -> 0 | U72: =if(and($F$10>$H$71,$F$10<=$H$72),K56+K60,0) -> 0 | V72: =if(and($F$10>$H$71,$F$10<=$H$72),L56+L60,0) -> 0 | W72: =if(and($F$10>$H$71,$F$10<=$H$72),M56+M60,0) -> 0 | X72: =if(and($F$10>$H$71,$F$10<=$H$72),N56+N60,0) -> 0 | Y72: =if(and($F$10>$H$71,$F$10<=$H$72),O56+O60,0) -> 0 | Z72: =if(and($F$10>$H$71,$F$10<=$H$72),P56+P60,0) -> 0 | AA72: =if(and($F$10>$H$71,$F$10<=$H$72),Q56+Q60,0) -> 0 | ... AE72: =if(and($F$10>$H$71,$F$10<=$H$72),U56+U60,0) -> 0
G73: 12 | H73: 360 | U73: =if(and($F$10>$H$72,$F$10<=$H$73),J56+J60,0) -> 0 | V73: =if(and($F$10>$H$72,$F$10<=$H$73),K56+K60,0) -> 0 | W73: =if(and($F$10>$H$72,$F$10<=$H$73),L56+L60,0) -> 0 | X73: =if(and($F$10>$H$72,$F$10<=$H$73),M56+M60,0) -> 0 | Y73: =if(and($F$10>$H$72,$F$10<=$H$73),N56+N60,0) -> 0 | Z73: =if(and($F$10>$H$72,$F$10<=$H$73),O56+O60,0) -> 0 | AA73: =if(and($F$10>$H$72,$F$10<=$H$73),P56+P60,0) -> 0 | AB73: =if(and($F$10>$H$72,$F$10<=$H$73),Q56+Q60,0) -> 0 | ... AF73: =if(and($F$10>$H$72,$F$10<=$H$73),U56+U60,0) -> 0
H75: =H56 -> Balance Due | J75: =sum(J62:J73) -> 0 | K75: =sum(K62:K73) -> 0 | L75: =sum(L62:L73) -> 0 | M75: =sum(M62:M73) -> 44798.625 | N75: =sum(N62:N73) -> 16216.783 | O75: =sum(O62:O73) -> 39250.142 | P75: =sum(P62:P73) -> 23555.246 | Q75: =sum(Q62:Q73) -> 32950.043 | ... AF75: =sum(AF62:AF73) -> 0
D78: Shipping Speed Calculations | H78: =J7 -> 10 ft | J78: =if(J45=0,0,if(J44="Sea",$K$7,if(J44="Air",$L$7,$M$7)+if($J$42="yes",$H$7,0))) -> 7500 | K78: =if(K45=0,0,if(K44="Sea",$K$7,if(K44="Air",$L$7,$M$7)+if($J$42="yes",$H$7,0))) -> 3500 | L78: =if(L45=0,0,if(L44="Sea",$K$7,if(L44="Air",$L$7,$M$7)+if($J$42="yes",$H$7,0))) -> 9000 | M78: =if(M45=0,0,if(M44="Sea",$K$7,if(M44="Air",$L$7,$M$7)+if($J$42="yes",$H$7,0))) -> 9000 | N78: =if(N45=0,0,if(N44="Sea",$K$7,if(N44="Air",$L$7,$M$7)+if($J$42="yes",$H$7,0))) -> 3500 | O78: =if(O45=0,0,if(O44="Sea",$K$7,if(O44="Air",$L$7,$M$7)+if($J$42="yes",$H$7,0))) -> 7500 | P78: =if(P45=0,0,if(P44="Sea",$K$7,if(P44="Air",$L$7,$M$7)+if($J$42="yes",$H$7,0))) -> 9000 | Q78: =if(Q45=0,0,if(Q44="Sea",$K$7,if(Q44="Air",$L$7,$M$7)+if($J$42="yes",$H$7,0))) -> 3500 | ... U78: =if(U45=0,0,if(U44="Sea",$K$7,if(U44="Air",$L$7,$M$7)+if($J$42="yes",$H$7,0))) -> 9000
H79: =J8 -> 20 ft | J79: =if(J45=0,0,if(J44="Sea",$K$8,if(J44="Air",$L$8,$M$8)+if($J$42="yes",$H$8,0))) -> 14000 | K79: =if(K45=0,0,if(K44="Sea",$K$8,if(K44="Air",$L$8,$M$8))) -> 8000 | L79: =if(L45=0,0,if(L44="Sea",$K$8,if(L44="Air",$L$8,$M$8))) -> 11500 | M79: =if(M45=0,0,if(M44="Sea",$K$8,if(M44="Air",$L$8,$M$8))) -> 11500 | N79: =if(N45=0,0,if(N44="Sea",$K$8,if(N44="Air",$L$8,$M$8))) -> 8000 | O79: =if(O45=0,0,if(O44="Sea",$K$8,if(O44="Air",$L$8,$M$8))) -> 10000 | P79: =if(P45=0,0,if(P44="Sea",$K$8,if(P44="Air",$L$8,$M$8))) -> 11500 | Q79: =if(Q45=0,0,if(Q44="Sea",$K$8,if(Q44="Air",$L$8,$M$8))) -> 8000 | R79: =if(R45=0,0,if(R44="Sea",$K$8,if(R44="Air",$L$8,$M$8))) -> 10000 | ... U79: =if(U45=0,0,if(U44="Sea",$K$8,if(U44="Air",$L$8,$M$8))) -> 11500
H80: =J9 -> 40 ft | J80: =if(J45=0,0,if(J44="Sea",$K$9,if(J44="Air",$L$9,$M$9)+if($J$42="yes",$H$9,0))) -> 20000 | K80: =if(K45=0,0,if(K44="Sea",$K$9,if(K44="Air",$L$9,$M$9)+if($J$42="yes",$H$9,0))) -> 12000 | L80: =if(L45=0,0,if(L44="Sea",$K$9,if(L44="Air",$L$9,$M$9)+if($J$42="yes",$H$9,0))) -> 21500 | M80: =if(M45=0,0,if(M44="Sea",$K$9,if(M44="Air",$L$9,$M$9)+if($J$42="yes",$H$9,0))) -> 21500 | N80: =if(N45=0,0,if(N44="Sea",$K$9,if(N44="Air",$L$9,$M$9)+if($J$42="yes",$H$9,0))) -> 12000 | O80: =if(O45=0,0,if(O44="Sea",$K$9,if(O44="Air",$L$9,$M$9)+if($J$42="yes",$H$9,0))) -> 20000 | P80: =if(P45=0,0,if(P44="Sea",$K$9,if(P44="Air",$L$9,$M$9)+if($J$42="yes",$H$9,0))) -> 21500 | Q80: =if(Q45=0,0,if(Q44="Sea",$K$9,if(Q44="Air",$L$9,$M$9)+if($J$42="yes",$H$9,0))) -> 12000 | ... U80: =if(U45=0,0,if(U44="Sea",$K$9,if(U44="Air",$L$9,$M$9)+if($J$42="yes",$H$9,0))) -> 21500
D83: Shipping Payments | H83: Shipping Cost | J83: =if(J45=0,0,if(J43="10 ft",J78*J45,if(J43="20 ft",J79*J45,J80*J45))) -> 7500 | K83: =if(K45=0,0,if(K43="10 ft",K78*K45,if(K43="20 ft",K79*K45,K80*K45))) -> 12000 | L83: =if(L45=0,0,if(L43="10 ft",L78*L45,if(L43="20 ft",L79*L45,L80*L45))) -> 43000 | M83: =if(M45=0,0,if(M43="10 ft",M78*M45,if(M43="20 ft",M79*M45,M80*M45))) -> 11500 | N83: =if(N45=0,0,if(N43="10 ft",N78*N45,if(N43="20 ft",N79*N45,N80*N45))) -> 5250 | O83: =if(O45=0,0,if(O43="10 ft",O78*O45,if(O43="20 ft",O79*O45,O80*O45))) -> 20000 | P83: =if(P45=0,0,if(P43="10 ft",P78*P45,if(P43="20 ft",P79*P45,P80*P45))) -> 21500 | Q83: =if(Q45=0,0,if(Q43="10 ft",Q78*Q45,if(Q43="20 ft",Q79*Q45,Q80*Q45))) -> 4375 | ... U83: =if(U45=0,0,if(U43="10 ft",U78*U45,if(U43="20 ft",U79*U45,U80*U45))) -> 11500
G85: 1 | H85: 30 | J85: =if($F$6<=$H$85,J83,0) -> 0 | K85: =if($F$6<=$H$85,K83,0) -> 0 | L85: =if($F$6<=$H$85,L83,0) -> 0 | M85: =if($F$6<=$H$85,M83,0) -> 0 | N85: =if($F$6<=$H$85,N83,0) -> 0 | O85: =if($F$6<=$H$85,O83,0) -> 0 | P85: =if($F$6<=$H$85,P83,0) -> 0 | Q85: =if($F$6<=$H$85,Q83,0) -> 0 | ... U85: =if($F$6<=$H$85,U83,0) -> 0
G86: 2 | H86: 60 | K86: =if(and($F$6>$H$85,$F$6<=$H$86),J83,0) -> 0 | L86: =if(and($F$6>$H$85,$F$6<=$H$86),K83,0) -> 0 | M86: =if(and($F$6>$H$85,$F$6<=$H$86),L83,0) -> 0 | N86: =if(and($F$6>$H$85,$F$6<=$H$86),M83,0) -> 0 | O86: =if(and($F$6>$H$85,$F$6<=$H$86),N83,0) -> 0 | P86: =if(and($F$6>$H$85,$F$6<=$H$86),O83,0) -> 0 | Q86: =if(and($F$6>$H$85,$F$6<=$H$86),P83,0) -> 0 | R86: =if(and($F$6>$H$85,$F$6<=$H$86),Q83,0) -> 0 | ... V86: =if(and($F$6>$H$85,$F$6<=$H$86),U83,0) -> 0
G87: 3 | H87: 90 | L87: =if(and($F$6>$H$86,$F$6<=$H$87),J83,0) -> 0 | M87: =if(and($F$6>$H$86,$F$6<=$H$87),K83,0) -> 0 | N87: =if(and($F$6>$H$86,$F$6<=$H$87),L83,0) -> 0 | O87: =if(and($F$6>$H$86,$F$6<=$H$87),M83,0) -> 0 | P87: =if(and($F$6>$H$86,$F$6<=$H$87),N83,0) -> 0 | Q87: =if(and($F$6>$H$86,$F$6<=$H$87),O83,0) -> 0 | R87: =if(and($F$6>$H$86,$F$6<=$H$87),P83,0) -> 0 | S87: =if(and($F$6>$H$86,$F$6<=$H$87),Q83,0) -> 0 | ... W87: =if(and($F$6>$H$86,$F$6<=$H$87),U83,0) -> 0
G88: 4 | H88: 120 | M88: =if(and($F$6>$H$87,$F$6<=$H$88),J83,0) -> 7500 | N88: =if(and($F$6>$H$87,$F$6<=$H$88),K83,0) -> 12000 | O88: =if(and($F$6>$H$87,$F$6<=$H$88),L83,0) -> 43000 | P88: =if(and($F$6>$H$87,$F$6<=$H$88),M83,0) -> 11500 | Q88: =if(and($F$6>$H$87,$F$6<=$H$88),N83,0) -> 5250 | R88: =if(and($F$6>$H$87,$F$6<=$H$88),O83,0) -> 20000 | S88: =if(and($F$6>$H$87,$F$6<=$H$88),P83,0) -> 21500 | T88: =if(and($F$6>$H$87,$F$6<=$H$88),Q83,0) -> 4375 | ... X88: =if(and($F$6>$H$87,$F$6<=$H$88),U83,0) -> 11500
G89: 5 | H89: 150 | N89: =if(and($F$6>$H$88,$F$6<=$H$89),J83,0) -> 0 | O89: =if(and($F$6>$H$88,$F$6<=$H$89),K83,0) -> 0 | P89: =if(and($F$6>$H$88,$F$6<=$H$89),L83,0) -> 0 | Q89: =if(and($F$6>$H$88,$F$6<=$H$89),M83,0) -> 0 | R89: =if(and($F$6>$H$88,$F$6<=$H$89),N83,0) -> 0 | S89: =if(and($F$6>$H$88,$F$6<=$H$89),O83,0) -> 0 | T89: =if(and($F$6>$H$88,$F$6<=$H$89),P83,0) -> 0 | U89: =if(and($F$6>$H$88,$F$6<=$H$89),Q83,0) -> 0 | ... Y89: =if(and($F$6>$H$88,$F$6<=$H$89),U83,0) -> 0
G90: 6 | H90: 180 | O90: =if(and($F$6>$H$89,$F$6<=$H$90),J83,0) -> 0 | P90: =if(and($F$6>$H$89,$F$6<=$H$90),K83,0) -> 0 | Q90: =if(and($F$6>$H$89,$F$6<=$H$90),L83,0) -> 0 | R90: =if(and($F$6>$H$89,$F$6<=$H$90),M83,0) -> 0 | S90: =if(and($F$6>$H$89,$F$6<=$H$90),N83,0) -> 0 | T90: =if(and($F$6>$H$89,$F$6<=$H$90),O83,0) -> 0 | U90: =if(and($F$6>$H$89,$F$6<=$H$90),P83,0) -> 0 | V90: =if(and($F$6>$H$89,$F$6<=$H$90),Q83,0) -> 0 | ... Z90: =if(and($F$6>$H$89,$F$6<=$H$90),U83,0) -> 0
G91: 7 | H91: 210 | P91: =if(and($F$6>$H$90,$F$6<=$H$91),J83,0) -> 0 | Q91: =if(and($F$6>$H$90,$F$6<=$H$91),K83,0) -> 0 | R91: =if(and($F$6>$H$90,$F$6<=$H$91),L83,0) -> 0 | S91: =if(and($F$6>$H$90,$F$6<=$H$91),M83,0) -> 0 | T91: =if(and($F$6>$H$90,$F$6<=$H$91),N83,0) -> 0 | U91: =if(and($F$6>$H$90,$F$6<=$H$91),O83,0) -> 0 | V91: =if(and($F$6>$H$90,$F$6<=$H$91),P83,0) -> 0 | W91: =if(and($F$6>$H$90,$F$6<=$H$91),Q83,0) -> 0 | ... AA91: =if(and($F$6>$H$90,$F$6<=$H$91),U83,0) -> 0
G92: 8 | H92: 240 | Q92: =if(and($F$6>$H$91,$F$6<=$H$92),J83,0) -> 0 | R92: =if(and($F$6>$H$91,$F$6<=$H$92),K83,0) -> 0 | S92: =if(and($F$6>$H$91,$F$6<=$H$92),L83,0) -> 0 | T92: =if(and($F$6>$H$91,$F$6<=$H$92),M83,0) -> 0 | U92: =if(and($F$6>$H$91,$F$6<=$H$92),N83,0) -> 0 | V92: =if(and($F$6>$H$91,$F$6<=$H$92),O83,0) -> 0 | W92: =if(and($F$6>$H$91,$F$6<=$H$92),P83,0) -> 0 | X92: =if(and($F$6>$H$91,$F$6<=$H$92),Q83,0) -> 0 | ... AB92: =if(and($F$6>$H$91,$F$6<=$H$92),U83,0) -> 0
G93: 9 | H93: 270 | R93: =if(and($F$6>$H$92,$F$6<=$H$93),J83,0) -> 0 | S93: =if(and($F$6>$H$92,$F$6<=$H$93),K83,0) -> 0 | T93: =if(and($F$6>$H$92,$F$6<=$H$93),L83,0) -> 0 | U93: =if(and($F$6>$H$92,$F$6<=$H$93),M83,0) -> 0 | V93: =if(and($F$6>$H$92,$F$6<=$H$93),N83,0) -> 0 | W93: =if(and($F$6>$H$92,$F$6<=$H$93),O83,0) -> 0 | X93: =if(and($F$6>$H$92,$F$6<=$H$93),P83,0) -> 0 | Y93: =if(and($F$6>$H$92,$F$6<=$H$93),Q83,0) -> 0 | ... AC93: =if(and($F$6>$H$92,$F$6<=$H$93),U83,0) -> 0
G94: 10 | H94: 300 | S94: =if(and($F$6>$H$93,$F$6<=$H$94),J83,0) -> 0 | T94: =if(and($F$6>$H$93,$F$6<=$H$94),K83,0) -> 0 | U94: =if(and($F$6>$H$93,$F$6<=$H$94),L83,0) -> 0 | V94: =if(and($F$6>$H$93,$F$6<=$H$94),M83,0) -> 0 | W94: =if(and($F$6>$H$93,$F$6<=$H$94),N83,0) -> 0 | X94: =if(and($F$6>$H$93,$F$6<=$H$94),O83,0) -> 0 | Y94: =if(and($F$6>$H$93,$F$6<=$H$94),P83,0) -> 0 | Z94: =if(and($F$6>$H$93,$F$6<=$H$94),Q83,0) -> 0 | ... AD94: =if(and($F$6>$H$93,$F$6<=$H$94),U83,0) -> 0
G95: 11 | H95: 330 | T95: =if(and($F$6>$H$94,$F$6<=$H$95),J83,0) -> 0 | U95: =if(and($F$6>$H$94,$F$6<=$H$95),K83,0) -> 0 | V95: =if(and($F$6>$H$94,$F$6<=$H$95),L83,0) -> 0 | W95: =if(and($F$6>$H$94,$F$6<=$H$95),M83,0) -> 0 | X95: =if(and($F$6>$H$94,$F$6<=$H$95),N83,0) -> 0 | Y95: =if(and($F$6>$H$94,$F$6<=$H$95),O83,0) -> 0 | Z95: =if(and($F$6>$H$94,$F$6<=$H$95),P83,0) -> 0 | AA95: =if(and($F$6>$H$94,$F$6<=$H$95),Q83,0) -> 0 | ... AE95: =if(and($F$6>$H$94,$F$6<=$H$95),U83,0) -> 0
G96: 12 | H96: 360 | U96: =if(and($F$6>$H$95,$F$6<=$H$96),J83,0) -> 0 | V96: =if(and($F$6>$H$95,$F$6<=$H$96),K83,0) -> 0 | W96: =if(and($F$6>$H$95,$F$6<=$H$96),L83,0) -> 0 | X96: =if(and($F$6>$H$95,$F$6<=$H$96),M83,0) -> 0 | Y96: =if(and($F$6>$H$95,$F$6<=$H$96),N83,0) -> 0 | Z96: =if(and($F$6>$H$95,$F$6<=$H$96),O83,0) -> 0 | AA96: =if(and($F$6>$H$95,$F$6<=$H$96),P83,0) -> 0 | AB96: =if(and($F$6>$H$95,$F$6<=$H$96),Q83,0) -> 0 | ... AF96: =if(and($F$6>$H$95,$F$6<=$H$96),U83,0) -> 0
J98: =sum(J85:J96) -> 0 | K98: =sum(K85:K96) -> 0 | L98: =sum(L85:L96) -> 0 | M98: =sum(M85:M96) -> 7500 | N98: =sum(N85:N96) -> 12000 | O98: =sum(O85:O96) -> 43000 | P98: =sum(P85:P96) -> 11500 | Q98: =sum(Q85:Q96) -> 5250 | ... AF98: =sum(AF85:AF96) -> 0
D102: Calculations | F102: 30 day bands
D103: =D21 -> Stock 1 | H103: =H21 -> SkyRockets | J103: =if($H$103="",0,if($H$103="Sky Rockets",J21*$W$7*$AA$21,if($H$103="Steady Eddy",J21*$X$7*$AA$21,J21*$Y$7*$AA$21))) -> 1405.05 | K103: =if($H$103="",0,if($H$103="Sky Rockets",K21*$W$7*$AA$21,if($H$103="Steady Eddy",K21*$X$7*$AA$21,K21*$Y$7*$AA$21))) -> 495.9 | L103: =if($H$103="",0,if($H$103="Sky Rockets",L21*$W$7*$AA$21,if($H$103="Steady Eddy",L21*$X$7*$AA$21,L21*$Y$7*$AA$21))) -> 1446.375 | M103: =if($H$103="",0,if($H$103="Sky Rockets",M21*$W$7*$AA$21,if($H$103="Steady Eddy",M21*$X$7*$AA$21,M21*$Y$7*$AA$21))) -> 991.8 | N103: =if($H$103="",0,if($H$103="Sky Rockets",N21*$W$7*$AA$21,if($H$103="Steady Eddy",N21*$X$7*$AA$21,N21*$Y$7*$AA$21))) -> 495.9 | O103: =if($H$103="",0,if($H$103="Sky Rockets",O21*$W$7*$AA$21,if($H$103="Steady Eddy",O21*$X$7*$AA$21,O21*$Y$7*$AA$21))) -> 1900.95 | P103: =if($H$103="",0,if($H$103="Sky Rockets",P21*$W$7*$AA$21,if($H$103="Steady Eddy",P21*$X$7*$AA$21,P21*$Y$7*$AA$21))) -> 578.55 | Q103: =if($H$103="",0,if($H$103="Sky Rockets",Q21*$W$7*$AA$21,if($H$103="Steady Eddy",Q21*$X$7*$AA$21,Q21*$Y$7*$AA$21))) -> 495.9 | ... U103: =if($H$103="",0,if($H$103="Sky Rockets",U21*$W$7*$AA$21,if($H$103="Steady Eddy",U21*$X$7*$AA$21,U21*$Y$7*$AA$21))) -> 661.2
D104: =D22 -> Stock 2 | H104: =H22 -> Steady Eddy | J104: =if($H$104="",0,if($H$104="Sky Rockets",J22*$W$7*$AA$22,if($H$104="Steady Eddy",J22*$X$7*$AA$22,J22*$Y$7*$AA$22))) -> 2746.26 | K104: =if($H$104="",0,if($H$104="Sky Rockets",K22*$W$7*$AA$22,if($H$104="Steady Eddy",K22*$X$7*$AA$22,K22*$Y$7*$AA$22))) -> 1165.08 | L104: =if($H$104="",0,if($H$104="Sky Rockets",L22*$W$7*$AA$22,if($H$104="Steady Eddy",L22*$X$7*$AA$22,L22*$Y$7*$AA$22))) -> 2912.7 | M104: =if($H$104="",0,if($H$104="Sky Rockets",M22*$W$7*$AA$22,if($H$104="Steady Eddy",M22*$X$7*$AA$22,M22*$Y$7*$AA$22))) -> 1914.06 | N104: =if($H$104="",0,if($H$104="Sky Rockets",N22*$W$7*$AA$22,if($H$104="Steady Eddy",N22*$X$7*$AA$22,N22*$Y$7*$AA$22))) -> 1165.08 | O104: =if($H$104="",0,if($H$104="Sky Rockets",O22*$W$7*$AA$22,if($H$104="Steady Eddy",O22*$X$7*$AA$22,O22*$Y$7*$AA$22))) -> 3744.9 | P104: =if($H$104="",0,if($H$104="Sky Rockets",P22*$W$7*$AA$22,if($H$104="Steady Eddy",P22*$X$7*$AA$22,P22*$Y$7*$AA$22))) -> 1081.86 | Q104: =if($H$104="",0,if($H$104="Sky Rockets",Q22*$W$7*$AA$22,if($H$104="Steady Eddy",Q22*$X$7*$AA$22,Q22*$Y$7*$AA$22))) -> 0 | ... U104: =if($H$104="",0,if($H$104="Sky Rockets",U22*$W$7*$AA$22,if($H$104="Steady Eddy",U22*$X$7*$AA$22,U22*$Y$7*$AA$22))) -> 1248.3
D105: =D23 -> Stock 3 | H105: =H23 -> Slow Burn | J105: =if($H$105="",0,if($H$105="Sky Rockets",J23*$W$7*$AA$23,if($H$105="Steady Eddy",J23*$X$7*$AA$23,J23*$Y$7*$AA$23))) -> 1466.325 | K105: =if($H$105="",0,if($H$105="Sky Rockets",K23*$W$7*$AA$23,if($H$105="Steady Eddy",K23*$X$7*$AA$23,K23*$Y$7*$AA$23))) -> 0 | L105: =if($H$105="",0,if($H$105="Sky Rockets",L23*$W$7*$AA$23,if($H$105="Steady Eddy",L23*$X$7*$AA$23,L23*$Y$7*$AA$23))) -> 1424.43 | M105: =if($H$105="",0,if($H$105="Sky Rockets",M23*$W$7*$AA$23,if($H$105="Steady Eddy",M23*$X$7*$AA$23,M23*$Y$7*$AA$23))) -> 0 | N105: =if($H$105="",0,if($H$105="Sky Rockets",N23*$W$7*$AA$23,if($H$105="Steady Eddy",N23*$X$7*$AA$23,N23*$Y$7*$AA$23))) -> 670.32 | O105: =if($H$105="",0,if($H$105="Sky Rockets",O23*$W$7*$AA$23,if($H$105="Steady Eddy",O23*$X$7*$AA$23,O23*$Y$7*$AA$23))) -> 1843.38 | P105: =if($H$105="",0,if($H$105="Sky Rockets",P23*$W$7*$AA$23,if($H$105="Steady Eddy",P23*$X$7*$AA$23,P23*$Y$7*$AA$23))) -> 628.425 | Q105: =if($H$105="",0,if($H$105="Sky Rockets",Q23*$W$7*$AA$23,if($H$105="Steady Eddy",Q23*$X$7*$AA$23,Q23*$Y$7*$AA$23))) -> 0 | ... U105: =if($H$105="",0,if($H$105="Sky Rockets",U23*$W$7*$AA$23,if($H$105="Steady Eddy",U23*$X$7*$AA$23,U23*$Y$7*$AA$23))) -> 0
D106: =D24 -> Stock 4 | H106: =H24 -> Steady Eddy | J106: =if($H$106="",0,if($H$106="Sky Rockets",J24*$W$7*$AA$24,if($H$106="Steady Eddy",J24*$X$7*$AA$24,J24*$Y$7*$AA$24))) -> 3205.68 | K106: =if($H$106="",0,if($H$106="Sky Rockets",K24*$W$7*$AA$24,if($H$106="Steady Eddy",K24*$X$7*$AA$24,K24*$Y$7*$AA$24))) -> 0 | L106: =if($H$106="",0,if($H$106="Sky Rockets",L24*$W$7*$AA$24,if($H$106="Steady Eddy",L24*$X$7*$AA$24,L24*$Y$7*$AA$24))) -> 3290.04 | M106: =if($H$106="",0,if($H$106="Sky Rockets",M24*$W$7*$AA$24,if($H$106="Steady Eddy",M24*$X$7*$AA$24,M24*$Y$7*$AA$24))) -> 0 | N106: =if($H$106="",0,if($H$106="Sky Rockets",N24*$W$7*$AA$24,if($H$106="Steady Eddy",N24*$X$7*$AA$24,N24*$Y$7*$AA$24))) -> 1518.48 | O106: =if($H$106="",0,if($H$106="Sky Rockets",O24*$W$7*$AA$24,if($H$106="Steady Eddy",O24*$X$7*$AA$24,O24*$Y$7*$AA$24))) -> 4133.64 | P106: =if($H$106="",0,if($H$106="Sky Rockets",P24*$W$7*$AA$24,if($H$106="Steady Eddy",P24*$X$7*$AA$24,P24*$Y$7*$AA$24))) -> 0 | Q106: =if($H$106="",0,if($H$106="Sky Rockets",Q24*$W$7*$AA$24,if($H$106="Steady Eddy",Q24*$X$7*$AA$24,Q24*$Y$7*$AA$24))) -> 0 | ... U106: =if($H$106="",0,if($H$106="Sky Rockets",U24*$W$7*$AA$24,if($H$106="Steady Eddy",U24*$X$7*$AA$24,U24*$Y$7*$AA$24))) -> 0
D107: =D25 -> Stock 5 | H107: =H25 -> SkyRockets | J107: =if($H$107="",0,if($H$107="Sky Rockets",J25*$W$7*$AA$25,if($H$107="Steady Eddy",J25*$X$7*$AA$25,J25*$Y$7*$AA$25))) -> 1528.74 | K107: =if($H$107="",0,if($H$107="Sky Rockets",K25*$W$7*$AA$25,if($H$107="Steady Eddy",K25*$X$7*$AA$25,K25*$Y$7*$AA$25))) -> 0 | L107: =if($H$107="",0,if($H$107="Sky Rockets",L25*$W$7*$AA$25,if($H$107="Steady Eddy",L25*$X$7*$AA$25,L25*$Y$7*$AA$25))) -> 1613.67 | M107: =if($H$107="",0,if($H$107="Sky Rockets",M25*$W$7*$AA$25,if($H$107="Steady Eddy",M25*$X$7*$AA$25,M25*$Y$7*$AA$25))) -> 1104.09 | N107: =if($H$107="",0,if($H$107="Sky Rockets",N25*$W$7*$AA$25,if($H$107="Steady Eddy",N25*$X$7*$AA$25,N25*$Y$7*$AA$25))) -> 467.115 | O107: =if($H$107="",0,if($H$107="Sky Rockets",O25*$W$7*$AA$25,if($H$107="Steady Eddy",O25*$X$7*$AA$25,O25*$Y$7*$AA$25))) -> 2038.32 | P107: =if($H$107="",0,if($H$107="Sky Rockets",P25*$W$7*$AA$25,if($H$107="Steady Eddy",P25*$X$7*$AA$25,P25*$Y$7*$AA$25))) -> 0 | Q107: =if($H$107="",0,if($H$107="Sky Rockets",Q25*$W$7*$AA$25,if($H$107="Steady Eddy",Q25*$X$7*$AA$25,Q25*$Y$7*$AA$25))) -> 467.115 | ... U107: =if($H$107="",0,if($H$107="Sky Rockets",U25*$W$7*$AA$25,if($H$107="Steady Eddy",U25*$X$7*$AA$25,U25*$Y$7*$AA$25))) -> 0
D108: =D26 -> Stock 6 | H108: =H26 -> Slow Burn | J108: =if($H$108="",0,if($H$108="Sky Rockets",J26*$W$7*$AA$26,if($H$108="Steady Eddy",J26*$X$7*$AA$26,J26*$Y$7*$AA$26))) -> 1496.25 | K108: =if($H$108="",0,if($H$108="Sky Rockets",K26*$W$7*$AA$26,if($H$108="Steady Eddy",K26*$X$7*$AA$26,K26*$Y$7*$AA$26))) -> 555.75 | L108: =if($H$108="",0,if($H$108="Sky Rockets",L26*$W$7*$AA$26,if($H$108="Steady Eddy",L26*$X$7*$AA$26,L26*$Y$7*$AA$26))) -> 0 | M108: =if($H$108="",0,if($H$108="Sky Rockets",M26*$W$7*$AA$26,if($H$108="Steady Eddy",M26*$X$7*$AA$26,M26*$Y$7*$AA$26))) -> 1068.75 | N108: =if($H$108="",0,if($H$108="Sky Rockets",N26*$W$7*$AA$26,if($H$108="Steady Eddy",N26*$X$7*$AA$26,N26*$Y$7*$AA$26))) -> 0 | O108: =if($H$108="",0,if($H$108="Sky Rockets",O26*$W$7*$AA$26,if($H$108="Steady Eddy",O26*$X$7*$AA$26,O26*$Y$7*$AA$26))) -> 2009.25 | P108: =if($H$108="",0,if($H$108="Sky Rockets",P26*$W$7*$AA$26,if($H$108="Steady Eddy",P26*$X$7*$AA$26,P26*$Y$7*$AA$26))) -> 0 | Q108: =if($H$108="",0,if($H$108="Sky Rockets",Q26*$W$7*$AA$26,if($H$108="Steady Eddy",Q26*$X$7*$AA$26,Q26*$Y$7*$AA$26))) -> 555.75 | ... U108: =if($H$108="",0,if($H$108="Sky Rockets",U26*$W$7*$AA$26,if($H$108="Steady Eddy",U26*$X$7*$AA$26,U26*$Y$7*$AA$26))) -> 726.75
D109: =D27 -> Stock 7 | H109: =H27 -> SkyRockets | J109: =if($H$109="",0,if($H$109="Sky Rockets",J27*$W$7*$AA$27,if($H$109="Steady Eddy",J27*$X$7*$AA$27,J27*$Y$7*$AA$27))) -> 1463.19 | K109: =if($H$109="",0,if($H$109="Sky Rockets",K27*$W$7*$AA$27,if($H$109="Steady Eddy",K27*$X$7*$AA$27,K27*$Y$7*$AA$27))) -> 645.525 | L109: =if($H$109="",0,if($H$109="Sky Rockets",L27*$W$7*$AA$27,if($H$109="Steady Eddy",L27*$X$7*$AA$27,L27*$Y$7*$AA$27))) -> 0 | M109: =if($H$109="",0,if($H$109="Sky Rockets",M27*$W$7*$AA$27,if($H$109="Steady Eddy",M27*$X$7*$AA$27,M27*$Y$7*$AA$27))) -> 1032.84 | N109: =if($H$109="",0,if($H$109="Sky Rockets",N27*$W$7*$AA$27,if($H$109="Steady Eddy",N27*$X$7*$AA$27,N27*$Y$7*$AA$27))) -> 0 | O109: =if($H$109="",0,if($H$109="Sky Rockets",O27*$W$7*$AA$27,if($H$109="Steady Eddy",O27*$X$7*$AA$27,O27*$Y$7*$AA$27))) -> 0 | P109: =if($H$109="",0,if($H$109="Sky Rockets",P27*$W$7*$AA$27,if($H$109="Steady Eddy",P27*$X$7*$AA$27,P27*$Y$7*$AA$27))) -> 0 | Q109: =if($H$109="",0,if($H$109="Sky Rockets",Q27*$W$7*$AA$27,if($H$109="Steady Eddy",Q27*$X$7*$AA$27,Q27*$Y$7*$AA$27))) -> 645.525 | ... U109: =if($H$109="",0,if($H$109="Sky Rockets",U27*$W$7*$AA$27,if($H$109="Steady Eddy",U27*$X$7*$AA$27,U27*$Y$7*$AA$27))) -> 129.105
D110: =D28 -> Stock 8 | H110: =H28 -> SkyRockets | J110: =if($H$110="",0,if($H$110="Sky Rockets",J28*$W$7*$AA$28,if($H$110="Steady Eddy",J28*$X$7*$AA$28,J28*$Y$7*$AA$28))) -> 1602.84 | K110: =if($H$110="",0,if($H$110="Sky Rockets",K28*$W$7*$AA$28,if($H$110="Steady Eddy",K28*$X$7*$AA$28,K28*$Y$7*$AA$28))) -> 736.44 | L110: =if($H$110="",0,if($H$110="Sky Rockets",L28*$W$7*$AA$28,if($H$110="Steady Eddy",L28*$X$7*$AA$28,L28*$Y$7*$AA$28))) -> 0 | M110: =if($H$110="",0,if($H$110="Sky Rockets",M28*$W$7*$AA$28,if($H$110="Steady Eddy",M28*$X$7*$AA$28,M28*$Y$7*$AA$28))) -> 1169.64 | N110: =if($H$110="",0,if($H$110="Sky Rockets",N28*$W$7*$AA$28,if($H$110="Steady Eddy",N28*$X$7*$AA$28,N28*$Y$7*$AA$28))) -> 1602.84 | O110: =if($H$110="",0,if($H$110="Sky Rockets",O28*$W$7*$AA$28,if($H$110="Steady Eddy",O28*$X$7*$AA$28,O28*$Y$7*$AA$28))) -> 0 | P110: =if($H$110="",0,if($H$110="Sky Rockets",P28*$W$7*$AA$28,if($H$110="Steady Eddy",P28*$X$7*$AA$28,P28*$Y$7*$AA$28))) -> 0 | Q110: =if($H$110="",0,if($H$110="Sky Rockets",Q28*$W$7*$AA$28,if($H$110="Steady Eddy",Q28*$X$7*$AA$28,Q28*$Y$7*$AA$28))) -> 736.44 | ... U110: =if($H$110="",0,if($H$110="Sky Rockets",U28*$W$7*$AA$28,if($H$110="Steady Eddy",U28*$X$7*$AA$28,U28*$Y$7*$AA$28))) -> 216.6
D111: =D29 -> Stock 9 | H111: =H29 -> Steady Eddy | J111: =if($H$111="",0,if($H$111="Sky Rockets",J29*$W$7*$AA$29,if($H$111="Steady Eddy",J29*$X$7*$AA$29,J29*$Y$7*$AA$29))) -> 2965.14 | K111: =if($H$111="",0,if($H$111="Sky Rockets",K29*$W$7*$AA$29,if($H$111="Steady Eddy",K29*$X$7*$AA$29,K29*$Y$7*$AA$29))) -> 1046.52 | L111: =if($H$111="",0,if($H$111="Sky Rockets",L29*$W$7*$AA$29,if($H$111="Steady Eddy",L29*$X$7*$AA$29,L29*$Y$7*$AA$29))) -> 3226.77 | M111: =if($H$111="",0,if($H$111="Sky Rockets",M29*$W$7*$AA$29,if($H$111="Steady Eddy",M29*$X$7*$AA$29,M29*$Y$7*$AA$29))) -> 2093.04 | N111: =if($H$111="",0,if($H$111="Sky Rockets",N29*$W$7*$AA$29,if($H$111="Steady Eddy",N29*$X$7*$AA$29,N29*$Y$7*$AA$29))) -> 2790.72 | O111: =if($H$111="",0,if($H$111="Sky Rockets",O29*$W$7*$AA$29,if($H$111="Steady Eddy",O29*$X$7*$AA$29,O29*$Y$7*$AA$29))) -> 0 | P111: =if($H$111="",0,if($H$111="Sky Rockets",P29*$W$7*$AA$29,if($H$111="Steady Eddy",P29*$X$7*$AA$29,P29*$Y$7*$AA$29))) -> 0 | Q111: =if($H$111="",0,if($H$111="Sky Rockets",Q29*$W$7*$AA$29,if($H$111="Steady Eddy",Q29*$X$7*$AA$29,Q29*$Y$7*$AA$29))) -> 1046.52 | ... U111: =if($H$111="",0,if($H$111="Sky Rockets",U29*$W$7*$AA$29,if($H$111="Steady Eddy",U29*$X$7*$AA$29,U29*$Y$7*$AA$29))) -> 610.47
D112: =D30 -> Stock 10 | H112: =H30 -> Steady Eddy | J112: =if($H$112="",0,if($H$112="Sky Rockets",J30*$W$7*$AA$30,if($H$112="Steady Eddy",J30*$X$7*$AA$30,J30*$Y$7*$AA$30))) -> 2896.74 | K112: =if($H$112="",0,if($H$112="Sky Rockets",K30*$W$7*$AA$30,if($H$112="Steady Eddy",K30*$X$7*$AA$30,K30*$Y$7*$AA$30))) -> 1228.92 | L112: =if($H$112="",0,if($H$112="Sky Rockets",L30*$W$7*$AA$30,if($H$112="Steady Eddy",L30*$X$7*$AA$30,L30*$Y$7*$AA$30))) -> 2721.18 | M112: =if($H$112="",0,if($H$112="Sky Rockets",M30*$W$7*$AA$30,if($H$112="Steady Eddy",M30*$X$7*$AA$30,M30*$Y$7*$AA$30))) -> 2018.94 | N112: =if($H$112="",0,if($H$112="Sky Rockets",N30*$W$7*$AA$30,if($H$112="Steady Eddy",N30*$X$7*$AA$30,N30*$Y$7*$AA$30))) -> 2984.52 | O112: =if($H$112="",0,if($H$112="Sky Rockets",O30*$W$7*$AA$30,if($H$112="Steady Eddy",O30*$X$7*$AA$30,O30*$Y$7*$AA$30))) -> 2721.18 | P112: =if($H$112="",0,if($H$112="Sky Rockets",P30*$W$7*$AA$30,if($H$112="Steady Eddy",P30*$X$7*$AA$30,P30*$Y$7*$AA$30))) -> 0 | Q112: =if($H$112="",0,if($H$112="Sky Rockets",Q30*$W$7*$AA$30,if($H$112="Steady Eddy",Q30*$X$7*$AA$30,Q30*$Y$7*$AA$30))) -> 1228.92 | ... U112: =if($H$112="",0,if($H$112="Sky Rockets",U30*$W$7*$AA$30,if($H$112="Steady Eddy",U30*$X$7*$AA$30,U30*$Y$7*$AA$30))) -> 87.78
D113: =D31 -> Stock 11 | H113: =H31 -> Steady Eddy | J113: =if($H$113="",0,if($H$113="Sky Rockets",J31*$W$7*$AA$31,if($H$113="Steady Eddy",J31*$X$7*$AA$31,J31*$Y$7*$AA$31))) -> 3092.25 | K113: =if($H$113="",0,if($H$113="Sky Rockets",K31*$W$7*$AA$31,if($H$113="Steady Eddy",K31*$X$7*$AA$31,K31*$Y$7*$AA$31))) -> 1413.6 | L113: =if($H$113="",0,if($H$113="Sky Rockets",L31*$W$7*$AA$31,if($H$113="Steady Eddy",L31*$X$7*$AA$31,L31*$Y$7*$AA$31))) -> 3092.25 | M113: =if($H$113="",0,if($H$113="Sky Rockets",M31*$W$7*$AA$31,if($H$113="Steady Eddy",M31*$X$7*$AA$31,M31*$Y$7*$AA$31))) -> 0 | N113: =if($H$113="",0,if($H$113="Sky Rockets",N31*$W$7*$AA$31,if($H$113="Steady Eddy",N31*$X$7*$AA$31,N31*$Y$7*$AA$31))) -> 3180.6 | O113: =if($H$113="",0,if($H$113="Sky Rockets",O31*$W$7*$AA$31,if($H$113="Steady Eddy",O31*$X$7*$AA$31,O31*$Y$7*$AA$31))) -> 3092.25 | P113: =if($H$113="",0,if($H$113="Sky Rockets",P31*$W$7*$AA$31,if($H$113="Steady Eddy",P31*$X$7*$AA$31,P31*$Y$7*$AA$31))) -> 1325.25 | Q113: =if($H$113="",0,if($H$113="Sky Rockets",Q31*$W$7*$AA$31,if($H$113="Steady Eddy",Q31*$X$7*$AA$31,Q31*$Y$7*$AA$31))) -> 1413.6 | ... U113: =if($H$113="",0,if($H$113="Sky Rockets",U31*$W$7*$AA$31,if($H$113="Steady Eddy",U31*$X$7*$AA$31,U31*$Y$7*$AA$31))) -> 441.75
D114: =D32 -> Stock 12 | H114: =H32 -> Steady Eddy | J114: =if($H$114="",0,if($H$114="Sky Rockets",J32*$W$7*$AA$32,if($H$114="Steady Eddy",J32*$X$7*$AA$32,J32*$Y$7*$AA$32))) -> 3378.96 | K114: =if($H$114="",0,if($H$114="Sky Rockets",K32*$W$7*$AA$32,if($H$114="Steady Eddy",K32*$X$7*$AA$32,K32*$Y$7*$AA$32))) -> 1600.56 | L114: =if($H$114="",0,if($H$114="Sky Rockets",L32*$W$7*$AA$32,if($H$114="Steady Eddy",L32*$X$7*$AA$32,L32*$Y$7*$AA$32))) -> 3467.88 | M114: =if($H$114="",0,if($H$114="Sky Rockets",M32*$W$7*$AA$32,if($H$114="Steady Eddy",M32*$X$7*$AA$32,M32*$Y$7*$AA$32))) -> 0 | N114: =if($H$114="",0,if($H$114="Sky Rockets",N32*$W$7*$AA$32,if($H$114="Steady Eddy",N32*$X$7*$AA$32,N32*$Y$7*$AA$32))) -> 3378.96 | O114: =if($H$114="",0,if($H$114="Sky Rockets",O32*$W$7*$AA$32,if($H$114="Steady Eddy",O32*$X$7*$AA$32,O32*$Y$7*$AA$32))) -> 3467.88 | P114: =if($H$114="",0,if($H$114="Sky Rockets",P32*$W$7*$AA$32,if($H$114="Steady Eddy",P32*$X$7*$AA$32,P32*$Y$7*$AA$32))) -> 1600.56 | Q114: =if($H$114="",0,if($H$114="Sky Rockets",Q32*$W$7*$AA$32,if($H$114="Steady Eddy",Q32*$X$7*$AA$32,Q32*$Y$7*$AA$32))) -> 1600.56 | ... U114: =if($H$114="",0,if($H$114="Sky Rockets",U32*$W$7*$AA$32,if($H$114="Steady Eddy",U32*$X$7*$AA$32,U32*$Y$7*$AA$32))) -> 0
D115: =D33 -> Stock 13 | H115: =H33 -> Steady Eddy | J115: =if($H$115="",0,if($H$115="Sky Rockets",J33*$W$7*$AA$33,if($H$115="Steady Eddy",J33*$X$7*$AA$33,J33*$Y$7*$AA$33))) -> 3221.64 | K115: =if($H$115="",0,if($H$115="Sky Rockets",K33*$W$7*$AA$33,if($H$115="Steady Eddy",K33*$X$7*$AA$33,K33*$Y$7*$AA$33))) -> 1163.37 | L115: =if($H$115="",0,if($H$115="Sky Rockets",L33*$W$7*$AA$33,if($H$115="Steady Eddy",L33*$X$7*$AA$33,L33*$Y$7*$AA$33))) -> 3400.62 | M115: =if($H$115="",0,if($H$115="Sky Rockets",M33*$W$7*$AA$33,if($H$115="Steady Eddy",M33*$X$7*$AA$33,M33*$Y$7*$AA$33))) -> 0 | N115: =if($H$115="",0,if($H$115="Sky Rockets",N33*$W$7*$AA$33,if($H$115="Steady Eddy",N33*$X$7*$AA$33,N33*$Y$7*$AA$33))) -> 2953.17 | O115: =if($H$115="",0,if($H$115="Sky Rockets",O33*$W$7*$AA$33,if($H$115="Steady Eddy",O33*$X$7*$AA$33,O33*$Y$7*$AA$33))) -> 3400.62 | P115: =if($H$115="",0,if($H$115="Sky Rockets",P33*$W$7*$AA$33,if($H$115="Steady Eddy",P33*$X$7*$AA$33,P33*$Y$7*$AA$33))) -> 1431.84 | Q115: =if($H$115="",0,if($H$115="Sky Rockets",Q33*$W$7*$AA$33,if($H$115="Steady Eddy",Q33*$X$7*$AA$33,Q33*$Y$7*$AA$33))) -> 1163.37 | ... U115: =if($H$115="",0,if($H$115="Sky Rockets",U33*$W$7*$AA$33,if($H$115="Steady Eddy",U33*$X$7*$AA$33,U33*$Y$7*$AA$33))) -> 0
D116: =D34 -> Stock 14 | H116: =H34 -> SkyRockets | J116: =if($H$116="",0,if($H$116="Sky Rockets",J34*$W$7*$AA$34,if($H$116="Steady Eddy",J34*$X$7*$AA$34,J34*$Y$7*$AA$34))) -> 1576.05 | K116: =if($H$116="",0,if($H$116="Sky Rockets",K34*$W$7*$AA$34,if($H$116="Steady Eddy",K34*$X$7*$AA$34,K34*$Y$7*$AA$34))) -> 675.45 | L116: =if($H$116="",0,if($H$116="Sky Rockets",L34*$W$7*$AA$34,if($H$116="Steady Eddy",L34*$X$7*$AA$34,L34*$Y$7*$AA$34))) -> 1576.05 | M116: =if($H$116="",0,if($H$116="Sky Rockets",M34*$W$7*$AA$34,if($H$116="Steady Eddy",M34*$X$7*$AA$34,M34*$Y$7*$AA$34))) -> 1125.75 | N116: =if($H$116="",0,if($H$116="Sky Rockets",N34*$W$7*$AA$34,if($H$116="Steady Eddy",N34*$X$7*$AA$34,N34*$Y$7*$AA$34))) -> 0 | O116: =if($H$116="",0,if($H$116="Sky Rockets",O34*$W$7*$AA$34,if($H$116="Steady Eddy",O34*$X$7*$AA$34,O34*$Y$7*$AA$34))) -> 0 | P116: =if($H$116="",0,if($H$116="Sky Rockets",P34*$W$7*$AA$34,if($H$116="Steady Eddy",P34*$X$7*$AA$34,P34*$Y$7*$AA$34))) -> 675.45 | Q116: =if($H$116="",0,if($H$116="Sky Rockets",Q34*$W$7*$AA$34,if($H$116="Steady Eddy",Q34*$X$7*$AA$34,Q34*$Y$7*$AA$34))) -> 0 | ... U116: =if($H$116="",0,if($H$116="Sky Rockets",U34*$W$7*$AA$34,if($H$116="Steady Eddy",U34*$X$7*$AA$34,U34*$Y$7*$AA$34))) -> 0
D117: =D35 -> Stock 15 | H117: =H35 -> SkyRockets | J117: =if($H$117="",0,if($H$117="Sky Rockets",J35*$W$7*$AA$35,if($H$117="Steady Eddy",J35*$X$7*$AA$35,J35*$Y$7*$AA$35))) -> 1540.71 | K117: =if($H$117="",0,if($H$117="Sky Rockets",K35*$W$7*$AA$35,if($H$117="Steady Eddy",K35*$X$7*$AA$35,K35*$Y$7*$AA$35))) -> 770.355 | L117: =if($H$117="",0,if($H$117="Sky Rockets",L35*$W$7*$AA$35,if($H$117="Steady Eddy",L35*$X$7*$AA$35,L35*$Y$7*$AA$35))) -> 1450.08 | M117: =if($H$117="",0,if($H$117="Sky Rockets",M35*$W$7*$AA$35,if($H$117="Steady Eddy",M35*$X$7*$AA$35,M35*$Y$7*$AA$35))) -> 1087.56 | N117: =if($H$117="",0,if($H$117="Sky Rockets",N35*$W$7*$AA$35,if($H$117="Steady Eddy",N35*$X$7*$AA$35,N35*$Y$7*$AA$35))) -> 0 | O117: =if($H$117="",0,if($H$117="Sky Rockets",O35*$W$7*$AA$35,if($H$117="Steady Eddy",O35*$X$7*$AA$35,O35*$Y$7*$AA$35))) -> 0 | P117: =if($H$117="",0,if($H$117="Sky Rockets",P35*$W$7*$AA$35,if($H$117="Steady Eddy",P35*$X$7*$AA$35,P35*$Y$7*$AA$35))) -> 634.41 | Q117: =if($H$117="",0,if($H$117="Sky Rockets",Q35*$W$7*$AA$35,if($H$117="Steady Eddy",Q35*$X$7*$AA$35,Q35*$Y$7*$AA$35))) -> 0 | ... U117: =if($H$117="",0,if($H$117="Sky Rockets",U35*$W$7*$AA$35,if($H$117="Steady Eddy",U35*$X$7*$AA$35,U35*$Y$7*$AA$35))) -> 0
D118: =D36 -> Stock 16 | H118: =H36 -> SkyRockets | J118: =if($H$118="",0,if($H$118="Sky Rockets",J36*$W$7*$AA$36,if($H$118="Steady Eddy",J36*$X$7*$AA$36,J36*$Y$7*$AA$36))) -> 1687.2 | K118: =if($H$118="",0,if($H$118="Sky Rockets",K36*$W$7*$AA$36,if($H$118="Steady Eddy",K36*$X$7*$AA$36,K36*$Y$7*$AA$36))) -> 866.4 | L118: =if($H$118="",0,if($H$118="Sky Rockets",L36*$W$7*$AA$36,if($H$118="Steady Eddy",L36*$X$7*$AA$36,L36*$Y$7*$AA$36))) -> 1641.6 | M118: =if($H$118="",0,if($H$118="Sky Rockets",M36*$W$7*$AA$36,if($H$118="Steady Eddy",M36*$X$7*$AA$36,M36*$Y$7*$AA$36))) -> 1231.2 | N118: =if($H$118="",0,if($H$118="Sky Rockets",N36*$W$7*$AA$36,if($H$118="Steady Eddy",N36*$X$7*$AA$36,N36*$Y$7*$AA$36))) -> 2234.4 | O118: =if($H$118="",0,if($H$118="Sky Rockets",O36*$W$7*$AA$36,if($H$118="Steady Eddy",O36*$X$7*$AA$36,O36*$Y$7*$AA$36))) -> 2097.6 | P118: =if($H$118="",0,if($H$118="Sky Rockets",P36*$W$7*$AA$36,if($H$118="Steady Eddy",P36*$X$7*$AA$36,P36*$Y$7*$AA$36))) -> 775.2 | Q118: =if($H$118="",0,if($H$118="Sky Rockets",Q36*$W$7*$AA$36,if($H$118="Steady Eddy",Q36*$X$7*$AA$36,Q36*$Y$7*$AA$36))) -> 0 | ... U118: =if($H$118="",0,if($H$118="Sky Rockets",U36*$W$7*$AA$36,if($H$118="Steady Eddy",U36*$X$7*$AA$36,U36*$Y$7*$AA$36))) -> 0
D119: =D37 -> Stock 17 | H119: =H37 -> Slow Burn | J119: =if($H$119="",0,if($H$119="Sky Rockets",J37*$W$7*$AA$37,if($H$119="Steady Eddy",J37*$X$7*$AA$37,J37*$Y$7*$AA$37))) -> 1651.86 | K119: =if($H$119="",0,if($H$119="Sky Rockets",K37*$W$7*$AA$37,if($H$119="Steady Eddy",K37*$X$7*$AA$37,K37*$Y$7*$AA$37))) -> 504.735 | L119: =if($H$119="",0,if($H$119="Sky Rockets",L37*$W$7*$AA$37,if($H$119="Steady Eddy",L37*$X$7*$AA$37,L37*$Y$7*$AA$37))) -> 1605.975 | M119: =if($H$119="",0,if($H$119="Sky Rockets",M37*$W$7*$AA$37,if($H$119="Steady Eddy",M37*$X$7*$AA$37,M37*$Y$7*$AA$37))) -> 1193.01 | N119: =if($H$119="",0,if($H$119="Sky Rockets",N37*$W$7*$AA$37,if($H$119="Steady Eddy",N37*$X$7*$AA$37,N37*$Y$7*$AA$37))) -> 1881.285 | O119: =if($H$119="",0,if($H$119="Sky Rockets",O37*$W$7*$AA$37,if($H$119="Steady Eddy",O37*$X$7*$AA$37,O37*$Y$7*$AA$37))) -> 2064.825 | P119: =if($H$119="",0,if($H$119="Sky Rockets",P37*$W$7*$AA$37,if($H$119="Steady Eddy",P37*$X$7*$AA$37,P37*$Y$7*$AA$37))) -> 734.16 | Q119: =if($H$119="",0,if($H$119="Sky Rockets",Q37*$W$7*$AA$37,if($H$119="Steady Eddy",Q37*$X$7*$AA$37,Q37*$Y$7*$AA$37))) -> 0 | ... U119: =if($H$119="",0,if($H$119="Sky Rockets",U37*$W$7*$AA$37,if($H$119="Steady Eddy",U37*$X$7*$AA$37,U37*$Y$7*$AA$37))) -> 0
D120: =D38 -> Stock 18 | H120: =H38 -> Slow Burn | J120: =if($H$120="",0,if($H$120="Sky Rockets",J38*$W$7*$AA$38,if($H$120="Steady Eddy",J38*$X$7*$AA$38,J38*$Y$7*$AA$38))) -> 1477.44 | K120: =if($H$120="",0,if($H$120="Sky Rockets",K38*$W$7*$AA$38,if($H$120="Steady Eddy",K38*$X$7*$AA$38,K38*$Y$7*$AA$38))) -> 554.04 | L120: =if($H$120="",0,if($H$120="Sky Rockets",L38*$W$7*$AA$38,if($H$120="Steady Eddy",L38*$X$7*$AA$38,L38*$Y$7*$AA$38))) -> 1569.78 | M120: =if($H$120="",0,if($H$120="Sky Rockets",M38*$W$7*$AA$38,if($H$120="Steady Eddy",M38*$X$7*$AA$38,M38*$Y$7*$AA$38))) -> 1015.74 | N120: =if($H$120="",0,if($H$120="Sky Rockets",N38*$W$7*$AA$38,if($H$120="Steady Eddy",N38*$X$7*$AA$38,N38*$Y$7*$AA$38))) -> 1939.14 | O120: =if($H$120="",0,if($H$120="Sky Rockets",O38*$W$7*$AA$38,if($H$120="Steady Eddy",O38*$X$7*$AA$38,O38*$Y$7*$AA$38))) -> 2031.48 | P120: =if($H$120="",0,if($H$120="Sky Rockets",P38*$W$7*$AA$38,if($H$120="Steady Eddy",P38*$X$7*$AA$38,P38*$Y$7*$AA$38))) -> 554.04 | Q120: =if($H$120="",0,if($H$120="Sky Rockets",Q38*$W$7*$AA$38,if($H$120="Steady Eddy",Q38*$X$7*$AA$38,Q38*$Y$7*$AA$38))) -> 554.04 | ... U120: =if($H$120="",0,if($H$120="Sky Rockets",U38*$W$7*$AA$38,if($H$120="Steady Eddy",U38*$X$7*$AA$38,U38*$Y$7*$AA$38))) -> 184.68
D121: =D39 -> Stock 19 | H121: =H39 -> SkyRockets | J121: =if($H$121="",0,if($H$121="Sky Rockets",J39*$W$7*$AA$39,if($H$121="Steady Eddy",J39*$X$7*$AA$39,J39*$Y$7*$AA$39))) -> 1440.105 | K121: =if($H$121="",0,if($H$121="Sky Rockets",K39*$W$7*$AA$39,if($H$121="Steady Eddy",K39*$X$7*$AA$39,K39*$Y$7*$AA$39))) -> 650.37 | L121: =if($H$121="",0,if($H$121="Sky Rockets",L39*$W$7*$AA$39,if($H$121="Steady Eddy",L39*$X$7*$AA$39,L39*$Y$7*$AA$39))) -> 1718.835 | M121: =if($H$121="",0,if($H$121="Sky Rockets",M39*$W$7*$AA$39,if($H$121="Steady Eddy",M39*$X$7*$AA$39,M39*$Y$7*$AA$39))) -> 975.555 | N121: =if($H$121="",0,if($H$121="Sky Rockets",N39*$W$7*$AA$39,if($H$121="Steady Eddy",N39*$X$7*$AA$39,N39*$Y$7*$AA$39))) -> 2044.02 | O121: =if($H$121="",0,if($H$121="Sky Rockets",O39*$W$7*$AA$39,if($H$121="Steady Eddy",O39*$X$7*$AA$39,O39*$Y$7*$AA$39))) -> 2183.385 | P121: =if($H$121="",0,if($H$121="Sky Rockets",P39*$W$7*$AA$39,if($H$121="Steady Eddy",P39*$X$7*$AA$39,P39*$Y$7*$AA$39))) -> 511.005 | Q121: =if($H$121="",0,if($H$121="Sky Rockets",Q39*$W$7*$AA$39,if($H$121="Steady Eddy",Q39*$X$7*$AA$39,Q39*$Y$7*$AA$39))) -> 650.37 | ... U121: =if($H$121="",0,if($H$121="Sky Rockets",U39*$W$7*$AA$39,if($H$121="Steady Eddy",U39*$X$7*$AA$39,U39*$Y$7*$AA$39))) -> 325.185
D122: =D40 -> Stock 20 | H122: =H40 -> Steady Eddy | J122: =if($H$122="",0,if($H$122="Sky Rockets",J40*$W$7*$AA$40,if($H$122="Steady Eddy",J40*$X$7*$AA$40,J40*$Y$7*$AA$40))) -> 3178.32 | K122: =if($H$122="",0,if($H$122="Sky Rockets",K40*$W$7*$AA$40,if($H$122="Steady Eddy",K40*$X$7*$AA$40,K40*$Y$7*$AA$40))) -> 1682.64 | L122: =if($H$122="",0,if($H$122="Sky Rockets",L40*$W$7*$AA$40,if($H$122="Steady Eddy",L40*$X$7*$AA$40,L40*$Y$7*$AA$40))) -> 3552.24 | M122: =if($H$122="",0,if($H$122="Sky Rockets",M40*$W$7*$AA$40,if($H$122="Steady Eddy",M40*$X$7*$AA$40,M40*$Y$7*$AA$40))) -> 2243.52 | N122: =if($H$122="",0,if($H$122="Sky Rockets",N40*$W$7*$AA$40,if($H$122="Steady Eddy",N40*$X$7*$AA$40,N40*$Y$7*$AA$40))) -> 4487.04 | O122: =if($H$122="",0,if($H$122="Sky Rockets",O40*$W$7*$AA$40,if($H$122="Steady Eddy",O40*$X$7*$AA$40,O40*$Y$7*$AA$40))) -> 4487.04 | P122: =if($H$122="",0,if($H$122="Sky Rockets",P40*$W$7*$AA$40,if($H$122="Steady Eddy",P40*$X$7*$AA$40,P40*$Y$7*$AA$40))) -> 1308.72 | Q122: =if($H$122="",0,if($H$122="Sky Rockets",Q40*$W$7*$AA$40,if($H$122="Steady Eddy",Q40*$X$7*$AA$40,Q40*$Y$7*$AA$40))) -> 1682.64 | ... U122: =if($H$122="",0,if($H$122="Sky Rockets",U40*$W$7*$AA$40,if($H$122="Steady Eddy",U40*$X$7*$AA$40,U40*$Y$7*$AA$40))) -> 747.84
D124: Calculations | F124: 60 day bands | H124: 30 | J124: =sum(J103:J122) -> 43020.75 | K124: =sum(K103:K122) -> 15755.655 | L124: =sum(L103:L122) -> 39710.475 | M124: =sum(M103:M122) -> 20265.495 | N124: =sum(N103:N122) -> 33793.59 | O124: =sum(O103:O122) -> 41216.7 | P124: =sum(P103:P122) -> 11839.47 | Q124: =sum(Q103:Q122) -> 12240.75 | ... U124: =sum(U103:U122) -> 5379.66
D126: =D103 -> Stock 1 | H126: =H103 -> SkyRockets | J126: =if($H$126="",0,if($H$126="Sky Rockets",J21*$W$8*$AA$21,if($H$126="Steady Eddy",J21*$X$8*$AA$21,J21*$Y$8*$AA$21))) -> 4215.15 | K126: =if($H$126="",0,if($H$126="Sky Rockets",K21*$W$8*$AA$21,if($H$126="Steady Eddy",K21*$X$8*$AA$21,K21*$Y$8*$AA$21))) -> 1487.7 | L126: =if($H$126="",0,if($H$126="Sky Rockets",L21*$W$8*$AA$21,if($H$126="Steady Eddy",L21*$X$8*$AA$21,L21*$Y$8*$AA$21))) -> 4339.125 | M126: =if($H$126="",0,if($H$126="Sky Rockets",M21*$W$8*$AA$21,if($H$126="Steady Eddy",M21*$X$8*$AA$21,M21*$Y$8*$AA$21))) -> 2975.4 | N126: =if($H$126="",0,if($H$126="Sky Rockets",N21*$W$8*$AA$21,if($H$126="Steady Eddy",N21*$X$8*$AA$21,N21*$Y$8*$AA$21))) -> 1487.7 | O126: =if($H$126="",0,if($H$126="Sky Rockets",O21*$W$8*$AA$21,if($H$126="Steady Eddy",O21*$X$8*$AA$21,O21*$Y$8*$AA$21))) -> 5702.85 | P126: =if($H$126="",0,if($H$126="Sky Rockets",P21*$W$8*$AA$21,if($H$126="Steady Eddy",P21*$X$8*$AA$21,P21*$Y$8*$AA$21))) -> 1735.65 | Q126: =if($H$126="",0,if($H$126="Sky Rockets",Q21*$W$8*$AA$21,if($H$126="Steady Eddy",Q21*$X$8*$AA$21,Q21*$Y$8*$AA$21))) -> 1487.7 | ... U126: =if($H$126="",0,if($H$126="Sky Rockets",U21*$W$8*$AA$21,if($H$126="Steady Eddy",U21*$X$8*$AA$21,U21*$Y$8*$AA$21))) -> 1983.6
D127: =D104 -> Stock 2 | H127: =H104 -> Steady Eddy | J127: =if($H$127="",0,if($H$127="Sky Rockets",J22*$W$8*$AA$22,if($H$127="Steady Eddy",J22*$X$8*$AA$22,J22*$Y$8*$AA$22))) -> 4119.39 | K127: =if($H$127="",0,if($H$127="Sky Rockets",K22*$W$8*$AA$22,if($H$127="Steady Eddy",K22*$X$8*$AA$22,K22*$Y$8*$AA$22))) -> 1747.62 | L127: =if($H$127="",0,if($H$127="Sky Rockets",L22*$W$8*$AA$22,if($H$127="Steady Eddy",L22*$X$8*$AA$22,L22*$Y$8*$AA$22))) -> 4369.05 | M127: =if($H$127="",0,if($H$127="Sky Rockets",M22*$W$8*$AA$22,if($H$127="Steady Eddy",M22*$X$8*$AA$22,M22*$Y$8*$AA$22))) -> 2871.09 | N127: =if($H$127="",0,if($H$127="Sky Rockets",N22*$W$8*$AA$22,if($H$127="Steady Eddy",N22*$X$8*$AA$22,N22*$Y$8*$AA$22))) -> 1747.62 | O127: =if($H$127="",0,if($H$127="Sky Rockets",O22*$W$8*$AA$22,if($H$127="Steady Eddy",O22*$X$8*$AA$22,O22*$Y$8*$AA$22))) -> 5617.35 | P127: =if($H$127="",0,if($H$127="Sky Rockets",P22*$W$8*$AA$22,if($H$127="Steady Eddy",P22*$X$8*$AA$22,P22*$Y$8*$AA$22))) -> 1622.79 | Q127: =if($H$127="",0,if($H$127="Sky Rockets",Q22*$W$8*$AA$22,if($H$127="Steady Eddy",Q22*$X$8*$AA$22,Q22*$Y$8*$AA$22))) -> 0 | ... U127: =if($H$127="",0,if($H$127="Sky Rockets",U22*$W$8*$AA$22,if($H$127="Steady Eddy",U22*$X$8*$AA$22,U22*$Y$8*$AA$22))) -> 1872.45
...

Sheet Supplier 2 Inputs
F3: Total Days Elapsed From Order to Retail | K3: =F6+K5+F13 -> 154 | L3: =F6+L5+F13 -> 149 | M3: =F6+M5+F13 -> 144
U4: Stock Turn Days | W4: Shipment % | AO4: Yes | AP4: =K6 -> Sea | AQ4: =W5 -> SkyRockets
H5: Refrigerated Surcharge | J5: Container Size | K5: 25 | L5: 20 | M5: 15 | N5: Total Shipping Days | W5: SkyRockets | X5: Steady Eddy | Y5: Slow Burn | AO5: No | AP5: =L6 -> Air | AQ5: =X5 -> Steady Eddy
D6: Manufacture Days | F6: 120 | K6: Sea | L6: Air | M6: Express | AP6: =M6 -> Express | AQ6: =Y5 -> Slow Burn
D7: Order Deposit % | F7: 0.6 | H7: 2500 | J7: 10 ft | K7: 3500 | L7: 5000 | M7: 6500 | U7: 30 | W7: 0.4 | X7: 0.2 | Y7: 0.1
D8: Interest Cover % | F8: 0.06 | H8: 4000 | J8: 20 ft | K8: 8000 | L8: 10000 | M8: 11500 | U8: 60 | W8: 0.25 | X8: 0.3 | Y8: 0.3
D9: Currency Movement % | F9: 0.1 | H9: 6000 | J9: 40 ft | K9: 12000 | L9: 14000 | M9: 15500 | U9: 90 | W9: 0.2 | X9: 0.2 | Y9: 0.4
D10: Order Balance Due Days | F10: 91 | U10: 120 | W10: 0.15 | X10: 0.3 | Y10: 0.2
H12: Deposit Pmts | J12: =J54 -> 64585.8 | K12: =K54 -> 23379.6 | L12: =L54 -> 56586.6 | M12: =M54 -> 33959.4 | N12: =N54 -> 47503.8 | O12: =O54 -> 60406.2 | P12: =P54 -> 17821.8 | Q12: =Q54 -> 17206.2 | ... U12: =U54 -> 8024.4 | W12: =100%-sum(W7:W10) -> 0 | X12: =100%-sum(X7:X10) -> 0 | Y12: =100%-sum(Y7:Y10) -> 0
D13: Pre-Retail Prep Days | F13: 9 | H13: Balance Pmts | J13: =J75 -> 0 | K13: =K75 -> 0 | L13: =L75 -> 0 | M13: =M75 -> 44798.625 | N13: =N75 -> 16216.783 | O13: =O75 -> 39250.142 | P13: =P75 -> 23555.246 | Q13: =Q75 -> 32950.043 | ... U13: =U75 -> 32683.273 | W13: Up to | X13: Up to | Y13: Up to | AA13: =U4 -> Stock Turn Days
H15: Total Import Pmts | J15: =sum(J12:J13) -> 64585.8 | K15: =sum(K12:K13) -> 23379.6 | L15: =sum(L12:L13) -> 56586.6 | M15: =sum(M12:M13) -> 78758.025 | N15: =sum(N12:N13) -> 63720.583 | O15: =sum(O12:O13) -> 99656.342 | P15: =sum(P12:P13) -> 41377.046 | Q15: =sum(Q12:Q13) -> 50156.243 | ... U15: =sum(U12:U13) -> 40707.673 | W15: =U8 -> 60 | X15: =U9 -> 90 | Y15: =U10 -> 120
H17: Projected Sales
D19: Stock Items | F19: Unit Cost | H19: Item Popularity | J19: ='Supplier 1 Inputs'!J19 -> Jan | K19: ='Supplier 1 Inputs'!K19 -> Feb | L19: ='Supplier 1 Inputs'!L19 -> Mar | M19: ='Supplier 1 Inputs'!M19 -> Apr | N19: ='Supplier 1 Inputs'!N19 -> May | O19: ='Supplier 1 Inputs'!O19 -> Jun | P19: ='Supplier 1 Inputs'!P19 -> Jul | Q19: ='Supplier 1 Inputs'!Q19 -> Aug | ... U19: ='Supplier 1 Inputs'!U19 -> Dec | W19: New Stock Retail Markup % | X19: Std Retail Markup % | Y19: Runout Stock Markup % | AA19: New Stock Retail Price | AB19: Std Retail Price | AC19: Runout Stock Price
D21: Stock 1 | F21: 145 | H21: SkyRockets | J21: 34 | K21: 12 | L21: 35 | M21: 24 | N21: 12 | O21: 46 | P21: 14 | Q21: 12 | R21: 36 | S21: 4 | T21: 2 | U21: 16 | W21: 1.85 | X21: 1.52 | Y21: 1.22 | AA21: =(F21*W21)+F21 -> 413.25 | AB21: =(F21*X21)+F21 -> 365.4 | AC21: =(F21*Y21)+F21 -> 321.9
D22: Stock 2 | F22: 146 | H22: Steady Eddy | J22: 33 | K22: 14 | L22: 35 | M22: 23 | N22: 14 | O22: 45 | P22: 13 | R22: 25 | S22: 3 | U22: 15 | W22: 1.85 | X22: 1.52 | Y22: 1.22 | AA22: =(F22*W22)+F22 -> 416.1 | AB22: =(F22*X22)+F22 -> 367.92 | AC22: =(F22*Y22)+F22 -> 324.12
D23: Stock 3 | F23: 147 | H23: Slow Burn | J23: 35 | L23: 34 | N23: 16 | O23: 44 | P23: 15 | S23: 5 | W23: 1.85 | X23: 1.52 | Y23: 1.22 | AA23: =(F23*W23)+F23 -> 418.95 | AB23: =(F23*X23)+F23 -> 370.44 | AC23: =(F23*Y23)+F23 -> 326.34
D24: Stock 4 | F24: 148 | H24: Steady Eddy | J24: 38 | L24: 39 | N24: 18 | O24: 49 | S24: 8 | T24: 18 | W24: 1.85 | X24: 1.52 | Y24: 1.22 | AA24: =(F24*W24)+F24 -> 421.8 | AB24: =(F24*X24)+F24 -> 372.96 | AC24: =(F24*Y24)+F24 -> 328.56
D25: Stock 5 | F25: 149 | H25: SkyRockets | J25: 36 | L25: 38 | M25: 26 | N25: 11 | O25: 48 | Q25: 11 | R25: 28 | S25: 6 | T25: 17 | W25: 1.85 | X25: 1.52 | Y25: 1.22 | AA25: =(F25*W25)+F25 -> 424.65 | AB25: =(F25*X25)+F25 -> 375.48 | AC25: =(F25*Y25)+F25 -> 330.78
D26: Stock 6 | F26: 150 | H26: Slow Burn | J26: 35 | K26: 13 | M26: 25 | O26: 47 | Q26: 13 | R26: 37 | T26: 13 | U26: 17 | W26: 1.85 | X26: 1.52 | Y26: 1.22 | AA26: =(F26*W26)+F26 -> 427.5 | AB26: =(F26*X26)+F26 -> 378 | AC26: =(F26*Y26)+F26 -> 333
D27: Stock 7 | F27: 151 | H27: SkyRockets | J27: 34 | K27: 15 | M27: 24 | Q27: 15 | R27: 33 | T27: 15 | U27: 3 | W27: 1.85 | X27: 1.52 | Y27: 1.22 | AA27: =(F27*W27)+F27 -> 430.35 | AB27: =(F27*X27)+F27 -> 380.52 | AC27: =(F27*Y27)+F27 -> 335.22
D28: Stock 8 | F28: 152 | H28: SkyRockets | J28: 37 | K28: 17 | M28: 27 | N28: 37 | Q28: 17 | S28: 27 | T28: 17 | U28: 5 | W28: 1.85 | X28: 1.52 | Y28: 1.22 | AA28: =(F28*W28)+F28 -> 433.2 | AB28: =(F28*X28)+F28 -> 383.04 | AC28: =(F28*Y28)+F28 -> 337.44
D29: Stock 9 | F29: 153 | H29: Steady Eddy | J29: 34 | K29: 12 | L29: 37 | M29: 24 | N29: 32 | Q29: 12 | S29: 24 | T29: 12 | U29: 7 | W29: 1.85 | X29: 1.52 | Y29: 1.22 | AA29: =(F29*W29)+F29 -> 436.05 | AB29: =(F29*X29)+F29 -> 385.56 | AC29: =(F29*Y29)+F29 -> 339.66
D30: Stock 10 | F30: 154 | H30: Steady Eddy | J30: 33 | K30: 14 | L30: 31 | M30: 23 | N30: 34 | O30: 31 | Q30: 14 | R30: 41 | S30: 23 | U30: 1 | W30: 1.85 | X30: 1.52 | Y30: 1.22 | AA30: =(F30*W30)+F30 -> 438.9 | AB30: =(F30*X30)+F30 -> 388.08 | AC30: =(F30*Y30)+F30 -> 341.88
D31: Stock 11 | F31: 155 | H31: Steady Eddy | J31: 35 | K31: 16 | L31: 35 | N31: 36 | O31: 35 | P31: 15 | Q31: 16 | R31: 55 | S31: 25 | U31: 5 | W31: 1.85 | X31: 1.52 | Y31: 1.22 | AA31: =(F31*W31)+F31 -> 441.75 | AB31: =(F31*X31)+F31 -> 390.6 | AC31: =(F31*Y31)+F31 -> 344.1
D32: Stock 12 | F32: 156 | H32: Steady Eddy | J32: 38 | K32: 18 | L32: 39 | N32: 38 | O32: 39 | P32: 18 | Q32: 18 | R32: 69 | S32: 28 | T32: 18 | W32: 1.85 | X32: 1.52 | Y32: 1.22 | AA32: =(F32*W32)+F32 -> 444.6 | AB32: =(F32*X32)+F32 -> 393.12 | AC32: =(F32*Y32)+F32 -> 346.32
D33: Stock 13 | F33: 157 | H33: Steady Eddy | J33: 36 | K33: 13 | L33: 38 | N33: 33 | O33: 38 | P33: 16 | Q33: 13 | S33: 26 | T33: 13 | W33: 1.85 | X33: 1.52 | Y33: 1.22 | AA33: =(F33*W33)+F33 -> 447.45 | AB33: =(F33*X33)+F33 -> 395.64 | AC33: =(F33*Y33)+F33 -> 348.54
D34: Stock 14 | F34: 158 | H34: SkyRockets | J34: 35 | K34: 15 | L34: 35 | M34: 25 | P34: 15 | T34: 15 | W34: 1.85 | X34: 1.52 | Y34: 1.22 | AA34: =(F34*W34)+F34 -> 450.3 | AB34: =(F34*X34)+F34 -> 398.16 | AC34: =(F34*Y34)+F34 -> 350.76
D35: Stock 15 | F35: 159 | H35: SkyRockets | J35: 34 | K35: 17 | L35: 32 | M35: 24 | P35: 14 | R35: 42 | T35: 17 | W35: 1.85 | X35: 1.52 | Y35: 1.22 | AA35: =(F35*W35)+F35 -> 453.15 | AB35: =(F35*X35)+F35 -> 400.68 | AC35: =(F35*Y35)+F35 -> 352.98
D36: Stock 16 | F36: 160 | H36: SkyRockets | J36: 37 | K36: 19 | L36: 36 | M36: 27 | N36: 49 | O36: 46 | P36: 17 | R36: 36 | T36: 19 | W36: 1.85 | X36: 1.52 | Y36: 1.22 | AA36: =(F36*W36)+F36 -> 456 | AB36: =(F36*X36)+F36 -> 403.2 | AC36: =(F36*Y36)+F36 -> 355.2
D37: Stock 17 | F37: 161 | H37: Slow Burn | J37: 36 | K37: 11 | L37: 35 | M37: 26 | N37: 41 | O37: 45 | P37: 16 | R37: 25 | S37: 6 | T37: 11 | W37: 1.85 | X37: 1.52 | Y37: 1.22 | AA37: =(F37*W37)+F37 -> 458.85 | AB37: =(F37*X37)+F37 -> 405.72 | AC37: =(F37*Y37)+F37 -> 357.42
D38: Stock 18 | F38: 162 | H38: Slow Burn | J38: 32 | K38: 12 | L38: 34 | M38: 22 | N38: 42 | O38: 44 | P38: 12 | Q38: 12 | R38: 24 | S38: 2 | T38: 12 | U38: 4 | W38: 1.85 | X38: 1.52 | Y38: 1.22 | AA38: =(F38*W38)+F38 -> 461.7 | AB38: =(F38*X38)+F38 -> 408.24 | AC38: =(F38*Y38)+F38 -> 359.64
D39: Stock 19 | F39: 163 | H39: SkyRockets | J39: 31 | K39: 14 | L39: 37 | M39: 21 | N39: 44 | O39: 47 | P39: 11 | Q39: 14 | R39: 17 | S39: 1 | T39: 14 | U39: 7 | W39: 1.85 | X39: 1.52 | Y39: 1.22 | AA39: =(F39*W39)+F39 -> 464.55 | AB39: =(F39*X39)+F39 -> 410.76 | AC39: =(F39*Y39)+F39 -> 361.86
D40: Stock 20 | F40: 164 | H40: Steady Eddy | J40: 34 | K40: 18 | L40: 38 | M40: 24 | N40: 48 | O40: 48 | P40: 14 | Q40: 18 | R40: 38 | S40: 4 | T40: 18 | U40: 8 | W40: 1.85 | X40: 1.52 | Y40: 1.22 | AA40: =(F40*W40)+F40 -> 467.4 | AB40: =(F40*X40)+F40 -> 413.28 | AC40: =(F40*Y40)+F40 -> 364.08
H42: Refrigerated | J42: Yes | K42: No | L42: Yes | M42: Yes | N42: No | O42: No | P42: No | Q42: Yes | R42: No | S42: No | T42: Yes | U42: No
H43: Container Size | J43: 10 ft | K43: 20 ft | L43: 40 ft | M43: 20 ft | N43: 10 ft | O43: 20 ft | P43: 40 ft | Q43: 10 ft | R43: 10 ft | S43: 20 ft | T43: 40 ft | U43: 20 ft
H44: Shipping Speed | J44: Air | K44: Sea | L44: Express | M44: Express | N44: Sea | O44: Air | P44: Express | Q44: Sea | R44: Air | S44: Express | T44: Sea | U44: Express
H45: # of Containers | J45: 1 | K45: 1.5 | L45: 2 | M45: 1 | N45: 1.5 | O45: 2 | P45: 1 | Q45: 1.25 | R45: 1 | S45: 1 | T45: 1 | U45: 1
H47: Shipping Costs | J47: =J98 -> 0 | K47: =K98 -> 0 | L47: =L98 -> 0 | M47: =M98 -> 7500 | N47: =N98 -> 12000 | O47: =O98 -> 43000 | P47: =P98 -> 11500 | Q47: =Q98 -> 5250 | ... U47: =U98 -> 7500
D50: Stock/ Manufacture Pmts
F51: =sum(J51:U51) -> 4469 | H51: Total Units | J51: =sum(J21:J40) -> 697 | K51: =sum(K21:K40) -> 250 | L51: =sum(L21:L40) -> 608 | M51: =sum(M21:M40) -> 365 | N51: =sum(N21:N40) -> 505 | O51: =sum(O21:O40) -> 652 | P51: =sum(P21:P40) -> 190 | Q51: =sum(Q21:Q40) -> 185 | ... U51: =sum(U21:U40) -> 88
F52: =sum(J52:U52) -> 693271 | H52: Total Unit Cost | J52: =J21*$F$21+J22*$F$22+J23*$F$23+J24*$F$24+J25*$F$25+J26*$F$26+J27*$F$27+J28*$F$28+J29*$F$29+J30*$F$30+J31*$F$31+J32*$F$32+J33*$F$33+J34*$F$34+J35*$F$35+J36*$F$36+J37*$F$37+J38*$F$38+J39*$F$39+J40*$F$40 -> 107643 | K52: =K21*$F$21+K22*$F$22+K23*$F$23+K24*$F$24+K25*$F$25+K26*$F$26+K27*$F$27+K28*$F$28+K29*$F$29+K30*$F$30+K31*$F$31+K32*$F$32+K33*$F$33+K34*$F$34+K35*$F$35+K36*$F$36+K37*$F$37+K38*$F$38+K39*$F$39+K40*$F$40 -> 38966 | L52: =L21*$F$21+L22*$F$22+L23*$F$23+L24*$F$24+L25*$F$25+L26*$F$26+L27*$F$27+L28*$F$28+L29*$F$29+L30*$F$30+L31*$F$31+L32*$F$32+L33*$F$33+L34*$F$34+L35*$F$35+L36*$F$36+L37*$F$37+L38*$F$38+L39*$F$39+L40*$F$40 -> 94311 | M52: =M21*$F$21+M22*$F$22+M23*$F$23+M24*$F$24+M25*$F$25+M26*$F$26+M27*$F$27+M28*$F$28+M29*$F$29+M30*$F$30+M31*$F$31+M32*$F$32+M33*$F$33+M34*$F$34+M35*$F$35+M36*$F$36+M37*$F$37+M38*$F$38+M39*$F$39+M40*$F$40 -> 56599 | N52: =N21*$F$21+N22*$F$22+N23*$F$23+N24*$F$24+N25*$F$25+N26*$F$26+N27*$F$27+N28*$F$28+N29*$F$29+N30*$F$30+N31*$F$31+N32*$F$32+N33*$F$33+N34*$F$34+N35*$F$35+N36*$F$36+N37*$F$37+N38*$F$38+N39*$F$39+N40*$F$40 -> 79173 | O52: =O21*$F$21+O22*$F$22+O23*$F$23+O24*$F$24+O25*$F$25+O26*$F$26+O27*$F$27+O28*$F$28+O29*$F$29+O30*$F$30+O31*$F$31+O32*$F$32+O33*$F$33+O34*$F$34+O35*$F$35+O36*$F$36+O37*$F$37+O38*$F$38+O39*$F$39+O40*$F$40 -> 100677 | P52: =P21*$F$21+P22*$F$22+P23*$F$23+P24*$F$24+P25*$F$25+P26*$F$26+P27*$F$27+P28*$F$28+P29*$F$29+P30*$F$30+P31*$F$31+P32*$F$32+P33*$F$33+P34*$F$34+P35*$F$35+P36*$F$36+P37*$F$37+P38*$F$38+P39*$F$39+P40*$F$40 -> 29703 | Q52: =Q21*$F$21+Q22*$F$22+Q23*$F$23+Q24*$F$24+Q25*$F$25+Q26*$F$26+Q27*$F$27+Q28*$F$28+Q29*$F$29+Q30*$F$30+Q31*$F$31+Q32*$F$32+Q33*$F$33+Q34*$F$34+Q35*$F$35+Q36*$F$36+Q37*$F$37+Q38*$F$38+Q39*$F$39+Q40*$F$40 -> 28677 | ... U52: =U21*$F$21+U22*$F$22+U23*$F$23+U24*$F$24+U25*$F$25+U26*$F$26+U27*$F$27+U28*$F$28+U29*$F$29+U30*$F$30+U31*$F$31+U32*$F$32+U33*$F$33+U34*$F$34+U35*$F$35+U36*$F$36+U37*$F$37+U38*$F$38+U39*$F$39+U40*$F$40 -> 13374
F54: =sum(J54:U54) -> 415962.6 | H54: Deposit | J54: =J52*$F$7 -> 64585.8 | K54: =K52*$F$7 -> 23379.6 | L54: =L52*$F$7 -> 56586.6 | M54: =M52*$F$7 -> 33959.4 | N54: =N52*$F$7 -> 47503.8 | O54: =O52*$F$7 -> 60406.2 | P54: =P52*$F$7 -> 17821.8 | Q54: =Q52*$F$7 -> 17206.2 | ... U54: =U52*$F$7 -> 8024.4
D56: =F54+F56 -> 671612.7 | F56: =sum(J75:U75) -> 255650.1 | H56: Balance Due | J56: =J52-J54 -> 43057.2 | K56: =K52-K54 -> 15586.4 | L56: =L52-L54 -> 37724.4 | M56: =M52-M54 -> 22639.6 | N56: =N52-N54 -> 31669.2 | O56: =O52-O54 -> 40270.8 | P56: =P52-P54 -> 11881.2 | Q56: =Q52-Q54 -> 11470.8 | ... U56: =U52-U54 -> 5349.6
H58: Balance Interest | J58: =J56*$F$8/12*$F$10/30 -> 653.0342 | K58: =K56*$F$8/12*$F$10/30 -> 236.39373 | L58: =L56*$F$8/12*$F$10/30 -> 572.1534 | M58: =M56*$F$8/12*$F$10/30 -> 343.36727 | N58: =N56*$F$8/12*$F$10/30 -> 480.3162 | O58: =O56*$F$8/12*$F$10/30 -> 610.7738 | P58: =P56*$F$8/12*$F$10/30 -> 180.1982 | Q58: =Q56*$F$8/12*$F$10/30 -> 173.9738 | ... U58: =U56*$F$8/12*$F$10/30 -> 81.1356
H59: FX Loss | J59: =J56*$F$9/12*$F$10/30 -> 1088.3903 | K59: =K56*$F$9/12*$F$10/30 -> 393.98956 | L59: =L56*$F$9/12*$F$10/30 -> 953.589 | M59: =M56*$F$9/12*$F$10/30 -> 572.27878 | N59: =N56*$F$9/12*$F$10/30 -> 800.527 | O59: =O56*$F$9/12*$F$10/30 -> 1017.9563 | P59: =P56*$F$9/12*$F$10/30 -> 300.33033 | Q59: =Q56*$F$9/12*$F$10/30 -> 289.95633 | ... U59: =U56*$F$9/12*$F$10/30 -> 135.226
H60: Interest Total | J60: =J58+J59 -> 1741.4245 | K60: =K58+K59 -> 630.38329 | L60: =L58+L59 -> 1525.7424 | M60: =M58+M59 -> 915.64604 | N60: =N58+N59 -> 1280.8432 | O60: =O58+O59 -> 1628.7301 | P60: =P58+P59 -> 480.52853 | Q60: =Q58+Q59 -> 463.93013 | ... U60: =U58+U59 -> 216.3616
G62: 1 | H62: 30 | J62: =if($F$10<=$H$62,J56+J60,0) -> 0 | K62: =if($F$10<=$H$62,K56+K60,0) -> 0 | L62: =if($F$10<=$H$62,L56+L60,0) -> 0 | M62: =if($F$10<=$H$62,M56+M60,0) -> 0 | N62: =if($F$10<=$H$62,N56+N60,0) -> 0 | O62: =if($F$10<=$H$62,O56+O60,0) -> 0 | P62: =if($F$10<=$H$62,P56+P60,0) -> 0 | Q62: =if($F$10<=$H$62,Q56+Q60,0) -> 0 | ... U62: =if($F$10<=$H$62,U56+U60,0) -> 0
G63: 2 | H63: 60 | K63: =if(and($F$10>$H$62,$F$10<=$H$63),J56+J60,0) -> 0 | L63: =if(and($F$10>$H$62,$F$10<=$H$63),K56+K60,0) -> 0 | M63: =if(and($F$10>$H$62,$F$10<=$H$63),L56+L60,0) -> 0 | N63: =if(and($F$10>$H$62,$F$10<=$H$63),M56+M60,0) -> 0 | O63: =if(and($F$10>$H$62,$F$10<=$H$63),N56+N60,0) -> 0 | P63: =if(and($F$10>$H$62,$F$10<=$H$63),O56+O60,0) -> 0 | Q63: =if(and($F$10>$H$62,$F$10<=$H$63),P56+P60,0) -> 0 | R63: =if(and($F$10>$H$62,$F$10<=$H$63),Q56+Q60,0) -> 0 | ... V63: =if(and($F$10>$H$62,$F$10<=$H$63),U56+U60,0) -> 0
G64: 3 | H64: 90 | L64: =if(and($F$10>$H$63,$F$10<=$H$64),J56+J60,0) -> 0 | M64: =if(and($F$10>$H$63,$F$10<=$H$64),K56+K60,0) -> 0 | N64: =if(and($F$10>$H$63,$F$10<=$H$64),L56+L60,0) -> 0 | O64: =if(and($F$10>$H$63,$F$10<=$H$64),M56+M60,0) -> 0 | P64: =if(and($F$10>$H$63,$F$10<=$H$64),N56+N60,0) -> 0 | Q64: =if(and($F$10>$H$63,$F$10<=$H$64),O56+O60,0) -> 0 | R64: =if(and($F$10>$H$63,$F$10<=$H$64),P56+P60,0) -> 0 | S64: =if(and($F$10>$H$63,$F$10<=$H$64),Q56+Q60,0) -> 0 | ... W64: =if(and($F$10>$H$63,$F$10<=$H$64),U56+U60,0) -> 0
G65: 4 | H65: 120 | M65: =if(and($F$10>$H$64,$F$10<=$H$65),J56+J60,0) -> 44798.625 | N65: =if(and($F$10>$H$64,$F$10<=$H$65),K56+K60,0) -> 16216.783 | O65: =if(and($F$10>$H$64,$F$10<=$H$65),L56+L60,0) -> 39250.142 | P65: =if(and($F$10>$H$64,$F$10<=$H$65),M56+M60,0) -> 23555.246 | Q65: =if(and($F$10>$H$64,$F$10<=$H$65),N56+N60,0) -> 32950.043 | R65: =if(and($F$10>$H$64,$F$10<=$H$65),O56+O60,0) -> 41899.53 | S65: =if(and($F$10>$H$64,$F$10<=$H$65),P56+P60,0) -> 12361.729 | T65: =if(and($F$10>$H$64,$F$10<=$H$65),Q56+Q60,0) -> 11934.73 | ... X65: =if(and($F$10>$H$64,$F$10<=$H$65),U56+U60,0) -> 5565.9616
G66: 5 | H66: 150 | N66: =if(and($F$10>$H$65,$F$10<=$H$66),J56+J60,0) -> 0 | O66: =if(and($F$10>$H$65,$F$10<=$H$66),K56+K60,0) -> 0 | P66: =if(and($F$10>$H$65,$F$10<=$H$66),L56+L60,0) -> 0 | Q66: =if(and($F$10>$H$65,$F$10<=$H$66),M56+M60,0) -> 0 | R66: =if(and($F$10>$H$65,$F$10<=$H$66),N56+N60,0) -> 0 | S66: =if(and($F$10>$H$65,$F$10<=$H$66),O56+O60,0) -> 0 | T66: =if(and($F$10>$H$65,$F$10<=$H$66),P56+P60,0) -> 0 | U66: =if(and($F$10>$H$65,$F$10<=$H$66),Q56+Q60,0) -> 0 | ... Y66: =if(and($F$10>$H$65,$F$10<=$H$66),U56+U60,0) -> 0
G67: 6 | H67: 180 | O67: =if(and($F$10>$H$66,$F$10<=$H$67),J56+J60,0) -> 0 | P67: =if(and($F$10>$H$66,$F$10<=$H$67),K56+K60,0) -> 0 | Q67: =if(and($F$10>$H$66,$F$10<=$H$67),L56+L60,0) -> 0 | R67: =if(and($F$10>$H$66,$F$10<=$H$67),M56+M60,0) -> 0 | S67: =if(and($F$10>$H$66,$F$10<=$H$67),N56+N60,0) -> 0 | T67: =if(and($F$10>$H$66,$F$10<=$H$67),O56+O60,0) -> 0 | U67: =if(and($F$10>$H$66,$F$10<=$H$67),P56+P60,0) -> 0 | V67: =if(and($F$10>$H$66,$F$10<=$H$67),Q56+Q60,0) -> 0 | ... Z67: =if(and($F$10>$H$66,$F$10<=$H$67),U56+U60,0) -> 0
G68: 7 | H68: 210 | P68: =if(and($F$10>$H$67,$F$10<=$H$68),J56+J60,0) -> 0 | Q68: =if(and($F$10>$H$67,$F$10<=$H$68),K56+K60,0) -> 0 | R68: =if(and($F$10>$H$67,$F$10<=$H$68),L56+L60,0) -> 0 | S68: =if(and($F$10>$H$67,$F$10<=$H$68),M56+M60,0) -> 0 | T68: =if(and($F$10>$H$67,$F$10<=$H$68),N56+N60,0) -> 0 | U68: =if(and($F$10>$H$67,$F$10<=$H$68),O56+O60,0) -> 0 | V68: =if(and($F$10>$H$67,$F$10<=$H$68),P56+P60,0) -> 0 | W68: =if(and($F$10>$H$67,$F$10<=$H$68),Q56+Q60,0) -> 0 | ... AA68: =if(and($F$10>$H$67,$F$10<=$H$68),U56+U60,0) -> 0
G69: 8 | H69: 240 | Q69: =if(and($F$10>$H$68,$F$10<=$H$69),J56+J60,0) -> 0 | R69: =if(and($F$10>$H$68,$F$10<=$H$69),K56+K60,0) -> 0 | S69: =if(and($F$10>$H$68,$F$10<=$H$69),L56+L60,0) -> 0 | T69: =if(and($F$10>$H$68,$F$10<=$H$69),M56+M60,0) -> 0 | U69: =if(and($F$10>$H$68,$F$10<=$H$69),N56+N60,0) -> 0 | V69: =if(and($F$10>$H$68,$F$10<=$H$69),O56+O60,0) -> 0 | W69: =if(and($F$10>$H$68,$F$10<=$H$69),P56+P60,0) -> 0 | X69: =if(and($F$10>$H$68,$F$10<=$H$69),Q56+Q60,0) -> 0 | ... AB69: =if(and($F$10>$H$68,$F$10<=$H$69),U56+U60,0) -> 0
G70: 9 | H70: 270 | R70: =if(and($F$10>$H$69,$F$10<=$H$70),J56+J60,0) -> 0 | S70: =if(and($F$10>$H$69,$F$10<=$H$70),K56+K60,0) -> 0 | T70: =if(and($F$10>$H$69,$F$10<=$H$70),L56+L60,0) -> 0 | U70: =if(and($F$10>$H$69,$F$10<=$H$70),M56+M60,0) -> 0 | V70: =if(and($F$10>$H$69,$F$10<=$H$70),N56+N60,0) -> 0 | W70: =if(and($F$10>$H$69,$F$10<=$H$70),O56+O60,0) -> 0 | X70: =if(and($F$10>$H$69,$F$10<=$H$70),P56+P60,0) -> 0 | Y70: =if(and($F$10>$H$69,$F$10<=$H$70),Q56+Q60,0) -> 0 | ... AC70: =if(and($F$10>$H$69,$F$10<=$H$70),U56+U60,0) -> 0
G71: 10 | H71: 300 | S71: =if(and($F$10>$H$70,$F$10<=$H$71),J56+J60,0) -> 0 | T71: =if(and($F$10>$H$70,$F$10<=$H$71),K56+K60,0) -> 0 | U71: =if(and($F$10>$H$70,$F$10<=$H$71),L56+L60,0) -> 0 | V71: =if(and($F$10>$H$70,$F$10<=$H$71),M56+M60,0) -> 0 | W71: =if(and($F$10>$H$70,$F$10<=$H$71),N56+N60,0) -> 0 | X71: =if(and($F$10>$H$70,$F$10<=$H$71),O56+O60,0) -> 0 | Y71: =if(and($F$10>$H$70,$F$10<=$H$71),P56+P60,0) -> 0 | Z71: =if(and($F$10>$H$70,$F$10<=$H$71),Q56+Q60,0) -> 0 | ... AD71: =if(and($F$10>$H$70,$F$10<=$H$71),U56+U60,0) -> 0
G72: 11 | H72: 330 | T72: =if(and($F$10>$H$71,$F$10<=$H$72),J56+J60,0) -> 0 | U72: =if(and($F$10>$H$71,$F$10<=$H$72),K56+K60,0) -> 0 | V72: =if(and($F$10>$H$71,$F$10<=$H$72),L56+L60,0) -> 0 | W72: =if(and($F$10>$H$71,$F$10<=$H$72),M56+M60,0) -> 0 | X72: =if(and($F$10>$H$71,$F$10<=$H$72),N56+N60,0) -> 0 | Y72: =if(and($F$10>$H$71,$F$10<=$H$72),O56+O60,0) -> 0 | Z72: =if(and($F$10>$H$71,$F$10<=$H$72),P56+P60,0) -> 0 | AA72: =if(and($F$10>$H$71,$F$10<=$H$72),Q56+Q60,0) -> 0 | ... AE72: =if(and($F$10>$H$71,$F$10<=$H$72),U56+U60,0) -> 0
G73: 12 | H73: 360 | U73: =if(and($F$10>$H$72,$F$10<=$H$73),J56+J60,0) -> 0 | V73: =if(and($F$10>$H$72,$F$10<=$H$73),K56+K60,0) -> 0 | W73: =if(and($F$10>$H$72,$F$10<=$H$73),L56+L60,0) -> 0 | X73: =if(and($F$10>$H$72,$F$10<=$H$73),M56+M60,0) -> 0 | Y73: =if(and($F$10>$H$72,$F$10<=$H$73),N56+N60,0) -> 0 | Z73: =if(and($F$10>$H$72,$F$10<=$H$73),O56+O60,0) -> 0 | AA73: =if(and($F$10>$H$72,$F$10<=$H$73),P56+P60,0) -> 0 | AB73: =if(and($F$10>$H$72,$F$10<=$H$73),Q56+Q60,0) -> 0 | ... AF73: =if(and($F$10>$H$72,$F$10<=$H$73),U56+U60,0) -> 0
H75: =H56 -> Balance Due | J75: =sum(J62:J73) -> 0 | K75: =sum(K62:K73) -> 0 | L75: =sum(L62:L73) -> 0 | M75: =sum(M62:M73) -> 44798.625 | N75: =sum(N62:N73) -> 16216.783 | O75: =sum(O62:O73) -> 39250.142 | P75: =sum(P62:P73) -> 23555.246 | Q75: =sum(Q62:Q73) -> 32950.043 | ... AF75: =sum(AF62:AF73) -> 0
D78: Shipping Speed Calculations | H78: =J7 -> 10 ft | J78: =if(J45=0,0,if(J44="Sea",$K$7,if(J44="Air",$L$7,$M$7)+if($J$42="yes",$H$7,0))) -> 7500 | K78: =if(K45=0,0,if(K44="Sea",$K$7,if(K44="Air",$L$7,$M$7)+if($J$42="yes",$H$7,0))) -> 3500 | L78: =if(L45=0,0,if(L44="Sea",$K$7,if(L44="Air",$L$7,$M$7)+if($J$42="yes",$H$7,0))) -> 9000 | M78: =if(M45=0,0,if(M44="Sea",$K$7,if(M44="Air",$L$7,$M$7)+if($J$42="yes",$H$7,0))) -> 9000 | N78: =if(N45=0,0,if(N44="Sea",$K$7,if(N44="Air",$L$7,$M$7)+if($J$42="yes",$H$7,0))) -> 3500 | O78: =if(O45=0,0,if(O44="Sea",$K$7,if(O44="Air",$L$7,$M$7)+if($J$42="yes",$H$7,0))) -> 7500 | P78: =if(P45=0,0,if(P44="Sea",$K$7,if(P44="Air",$L$7,$M$7)+if($J$42="yes",$H$7,0))) -> 9000 | Q78: =if(Q45=0,0,if(Q44="Sea",$K$7,if(Q44="Air",$L$7,$M$7)+if($J$42="yes",$H$7,0))) -> 3500 | ... U78: =if(U45=0,0,if(U44="Sea",$K$7,if(U44="Air",$L$7,$M$7)+if($J$42="yes",$H$7,0))) -> 9000
H79: =J8 -> 20 ft | J79: =if(J45=0,0,if(J44="Sea",$K$8,if(J44="Air",$L$8,$M$8)+if($J$42="yes",$H$8,0))) -> 14000 | K79: =if(K45=0,0,if(K44="Sea",$K$8,if(K44="Air",$L$8,$M$8))) -> 8000 | L79: =if(L45=0,0,if(L44="Sea",$K$8,if(L44="Air",$L$8,$M$8))) -> 11500 | M79: =if(M45=0,0,if(M44="Sea",$K$8,if(M44="Air",$L$8,$M$8))) -> 11500 | N79: =if(N45=0,0,if(N44="Sea",$K$8,if(N44="Air",$L$8,$M$8))) -> 8000 | O79: =if(O45=0,0,if(O44="Sea",$K$8,if(O44="Air",$L$8,$M$8))) -> 10000 | P79: =if(P45=0,0,if(P44="Sea",$K$8,if(P44="Air",$L$8,$M$8))) -> 11500 | Q79: =if(Q45=0,0,if(Q44="Sea",$K$8,if(Q44="Air",$L$8,$M$8))) -> 8000 | R79: =if(R45=0,0,if(R44="Sea",$K$8,if(R44="Air",$L$8,$M$8))) -> 10000 | ... U79: =if(U45=0,0,if(U44="Sea",$K$8,if(U44="Air",$L$8,$M$8))) -> 11500
H80: =J9 -> 40 ft | J80: =if(J45=0,0,if(J44="Sea",$K$9,if(J44="Air",$L$9,$M$9)+if($J$42="yes",$H$9,0))) -> 20000 | K80: =if(K45=0,0,if(K44="Sea",$K$9,if(K44="Air",$L$9,$M$9)+if($J$42="yes",$H$9,0))) -> 12000 | L80: =if(L45=0,0,if(L44="Sea",$K$9,if(L44="Air",$L$9,$M$9)+if($J$42="yes",$H$9,0))) -> 21500 | M80: =if(M45=0,0,if(M44="Sea",$K$9,if(M44="Air",$L$9,$M$9)+if($J$42="yes",$H$9,0))) -> 21500 | N80: =if(N45=0,0,if(N44="Sea",$K$9,if(N44="Air",$L$9,$M$9)+if($J$42="yes",$H$9,0))) -> 12000 | O80: =if(O45=0,0,if(O44="Sea",$K$9,if(O44="Air",$L$9,$M$9)+if($J$42="yes",$H$9,0))) -> 20000 | P80: =if(P45=0,0,if(P44="Sea",$K$9,if(P44="Air",$L$9,$M$9)+if($J$42="yes",$H$9,0))) -> 21500 | Q80: =if(Q45=0,0,if(Q44="Sea",$K$9,if(Q44="Air",$L$9,$M$9)+if($J$42="yes",$H$9,0))) -> 12000 | ... U80: =if(U45=0,0,if(U44="Sea",$K$9,if(U44="Air",$L$9,$M$9)+if($J$42="yes",$H$9,0))) -> 21500
D83: Shipping Payments | H83: Shipping Cost | J83: =if(J45=0,0,if(J43="10 ft",J78*J45,if(J43="20 ft",J79*J45,J80*J45))) -> 7500 | K83: =if(K45=0,0,if(K43="10 ft",K78*K45,if(K43="20 ft",K79*K45,K80*K45))) -> 12000 | L83: =if(L45=0,0,if(L43="10 ft",L78*L45,if(L43="20 ft",L79*L45,L80*L45))) -> 43000 | M83: =if(M45=0,0,if(M43="10 ft",M78*M45,if(M43="20 ft",M79*M45,M80*M45))) -> 11500 | N83: =if(N45=0,0,if(N43="10 ft",N78*N45,if(N43="20 ft",N79*N45,N80*N45))) -> 5250 | O83: =if(O45=0,0,if(O43="10 ft",O78*O45,if(O43="20 ft",O79*O45,O80*O45))) -> 20000 | P83: =if(P45=0,0,if(P43="10 ft",P78*P45,if(P43="20 ft",P79*P45,P80*P45))) -> 21500 | Q83: =if(Q45=0,0,if(Q43="10 ft",Q78*Q45,if(Q43="20 ft",Q79*Q45,Q80*Q45))) -> 4375 | ... U83: =if(U45=0,0,if(U43="10 ft",U78*U45,if(U43="20 ft",U79*U45,U80*U45))) -> 11500
G85: 1 | H85: 30 | J85: =if($F$6<=$H$85,J83,0) -> 0 | K85: =if($F$6<=$H$85,K83,0) -> 0 | L85: =if($F$6<=$H$85,L83,0) -> 0 | M85: =if($F$6<=$H$85,M83,0) -> 0 | N85: =if($F$6<=$H$85,N83,0) -> 0 | O85: =if($F$6<=$H$85,O83,0) -> 0 | P85: =if($F$6<=$H$85,P83,0) -> 0 | Q85: =if($F$6<=$H$85,Q83,0) -> 0 | ... U85: =if($F$6<=$H$85,U83,0) -> 0
G86: 2 | H86: 60 | K86: =if(and($F$6>$H$85,$F$6<=$H$86),J83,0) -> 0 | L86: =if(and($F$6>$H$85,$F$6<=$H$86),K83,0) -> 0 | M86: =if(and($F$6>$H$85,$F$6<=$H$86),L83,0) -> 0 | N86: =if(and($F$6>$H$85,$F$6<=$H$86),M83,0) -> 0 | O86: =if(and($F$6>$H$85,$F$6<=$H$86),N83,0) -> 0 | P86: =if(and($F$6>$H$85,$F$6<=$H$86),O83,0) -> 0 | Q86: =if(and($F$6>$H$85,$F$6<=$H$86),P83,0) -> 0 | R86: =if(and($F$6>$H$85,$F$6<=$H$86),Q83,0) -> 0 | ... V86: =if(and($F$6>$H$85,$F$6<=$H$86),U83,0) -> 0
G87: 3 | H87: 90 | L87: =if(and($F$6>$H$86,$F$6<=$H$87),J83,0) -> 0 | M87: =if(and($F$6>$H$86,$F$6<=$H$87),K83,0) -> 0 | N87: =if(and($F$6>$H$86,$F$6<=$H$87),L83,0) -> 0 | O87: =if(and($F$6>$H$86,$F$6<=$H$87),M83,0) -> 0 | P87: =if(and($F$6>$H$86,$F$6<=$H$87),N83,0) -> 0 | Q87: =if(and($F$6>$H$86,$F$6<=$H$87),O83,0) -> 0 | R87: =if(and($F$6>$H$86,$F$6<=$H$87),P83,0) -> 0 | S87: =if(and($F$6>$H$86,$F$6<=$H$87),Q83,0) -> 0 | ... W87: =if(and($F$6>$H$86,$F$6<=$H$87),U83,0) -> 0
G88: 4 | H88: 120 | M88: =if(and($F$6>$H$87,$F$6<=$H$88),J83,0) -> 7500 | N88: =if(and($F$6>$H$87,$F$6<=$H$88),K83,0) -> 12000 | O88: =if(and($F$6>$H$87,$F$6<=$H$88),L83,0) -> 43000 | P88: =if(and($F$6>$H$87,$F$6<=$H$88),M83,0) -> 11500 | Q88: =if(and($F$6>$H$87,$F$6<=$H$88),N83,0) -> 5250 | R88: =if(and($F$6>$H$87,$F$6<=$H$88),O83,0) -> 20000 | S88: =if(and($F$6>$H$87,$F$6<=$H$88),P83,0) -> 21500 | T88: =if(and($F$6>$H$87,$F$6<=$H$88),Q83,0) -> 4375 | ... X88: =if(and($F$6>$H$87,$F$6<=$H$88),U83,0) -> 11500
G89: 5 | H89: 150 | N89: =if(and($F$6>$H$88,$F$6<=$H$89),J83,0) -> 0 | O89: =if(and($F$6>$H$88,$F$6<=$H$89),K83,0) -> 0 | P89: =if(and($F$6>$H$88,$F$6<=$H$89),L83,0) -> 0 | Q89: =if(and($F$6>$H$88,$F$6<=$H$89),M83,0) -> 0 | R89: =if(and($F$6>$H$88,$F$6<=$H$89),N83,0) -> 0 | S89: =if(and($F$6>$H$88,$F$6<=$H$89),O83,0) -> 0 | T89: =if(and($F$6>$H$88,$F$6<=$H$89),P83,0) -> 0 | U89: =if(and($F$6>$H$88,$F$6<=$H$89),Q83,0) -> 0 | ... Y89: =if(and($F$6>$H$88,$F$6<=$H$89),U83,0) -> 0
G90: 6 | H90: 180 | O90: =if(and($F$6>$H$89,$F$6<=$H$90),J83,0) -> 0 | P90: =if(and($F$6>$H$89,$F$6<=$H$90),K83,0) -> 0 | Q90: =if(and($F$6>$H$89,$F$6<=$H$90),L83,0) -> 0 | R90: =if(and($F$6>$H$89,$F$6<=$H$90),M83,0) -> 0 | S90: =if(and($F$6>$H$89,$F$6<=$H$90),N83,0) -> 0 | T90: =if(and($F$6>$H$89,$F$6<=$H$90),O83,0) -> 0 | U90: =if(and($F$6>$H$89,$F$6<=$H$90),P83,0) -> 0 | V90: =if(and($F$6>$H$89,$F$6<=$H$90),Q83,0) -> 0 | ... Z90: =if(and($F$6>$H$89,$F$6<=$H$90),U83,0) -> 0
G91: 7 | H91: 210 | P91: =if(and($F$6>$H$90,$F$6<=$H$91),J83,0) -> 0 | Q91: =if(and($F$6>$H$90,$F$6<=$H$91),K83,0) -> 0 | R91: =if(and($F$6>$H$90,$F$6<=$H$91),L83,0) -> 0 | S91: =if(and($F$6>$H$90,$F$6<=$H$91),M83,0) -> 0 | T91: =if(and($F$6>$H$90,$F$6<=$H$91),N83,0) -> 0 | U91: =if(and($F$6>$H$90,$F$6<=$H$91),O83,0) -> 0 | V91: =if(and($F$6>$H$90,$F$6<=$H$91),P83,0) -> 0 | W91: =if(and($F$6>$H$90,$F$6<=$H$91),Q83,0) -> 0 | ... AA91: =if(and($F$6>$H$90,$F$6<=$H$91),U83,0) -> 0
G92: 8 | H92: 240 | Q92: =if(and($F$6>$H$91,$F$6<=$H$92),J83,0) -> 0 | R92: =if(and($F$6>$H$91,$F$6<=$H$92),K83,0) -> 0 | S92: =if(and($F$6>$H$91,$F$6<=$H$92),L83,0) -> 0 | T92: =if(and($F$6>$H$91,$F$6<=$H$92),M83,0) -> 0 | U92: =if(and($F$6>$H$91,$F$6<=$H$92),N83,0) -> 0 | V92: =if(and($F$6>$H$91,$F$6<=$H$92),O83,0) -> 0 | W92: =if(and($F$6>$H$91,$F$6<=$H$92),P83,0) -> 0 | X92: =if(and($F$6>$H$91,$F$6<=$H$92),Q83,0) -> 0 | ... AB92: =if(and($F$6>$H$91,$F$6<=$H$92),U83,0) -> 0
G93: 9 | H93: 270 | R93: =if(and($F$6>$H$92,$F$6<=$H$93),J83,0) -> 0 | S93: =if(and($F$6>$H$92,$F$6<=$H$93),K83,0) -> 0 | T93: =if(and($F$6>$H$92,$F$6<=$H$93),L83,0) -> 0 | U93: =if(and($F$6>$H$92,$F$6<=$H$93),M83,0) -> 0 | V93: =if(and($F$6>$H$92,$F$6<=$H$93),N83,0) -> 0 | W93: =if(and($F$6>$H$92,$F$6<=$H$93),O83,0) -> 0 | X93: =if(and($F$6>$H$92,$F$6<=$H$93),P83,0) -> 0 | Y93: =if(and($F$6>$H$92,$F$6<=$H$93),Q83,0) -> 0 | ... AC93: =if(and($F$6>$H$92,$F$6<=$H$93),U83,0) -> 0
G94: 10 | H94: 300 | S94: =if(and($F$6>$H$93,$F$6<=$H$94),J83,0) -> 0 | T94: =if(and($F$6>$H$93,$F$6<=$H$94),K83,0) -> 0 | U94: =if(and($F$6>$H$93,$F$6<=$H$94),L83,0) -> 0 | V94: =if(and($F$6>$H$93,$F$6<=$H$94),M83,0) -> 0 | W94: =if(and($F$6>$H$93,$F$6<=$H$94),N83,0) -> 0 | X94: =if(and($F$6>$H$93,$F$6<=$H$94),O83,0) -> 0 | Y94: =if(and($F$6>$H$93,$F$6<=$H$94),P83,0) -> 0 | Z94: =if(and($F$6>$H$93,$F$6<=$H$94),Q83,0) -> 0 | ... AD94: =if(and($F$6>$H$93,$F$6<=$H$94),U83,0) -> 0
G95: 11 | H95: 330 | T95: =if(and($F$6>$H$94,$F$6<=$H$95),J83,0) -> 0 | U95: =if(and($F$6>$H$94,$F$6<=$H$95),K83,0) -> 0 | V95: =if(and($F$6>$H$94,$F$6<=$H$95),L83,0) -> 0 | W95: =if(and($F$6>$H$94,$F$6<=$H$95),M83,0) -> 0 | X95: =if(and($F$6>$H$94,$F$6<=$H$95),N83,0) -> 0 | Y95: =if(and($F$6>$H$94,$F$6<=$H$95),O83,0) -> 0 | Z95: =if(and($F$6>$H$94,$F$6<=$H$95),P83,0) -> 0 | AA95: =if(and($F$6>$H$94,$F$6<=$H$95),Q83,0) -> 0 | ... AE95: =if(and($F$6>$H$94,$F$6<=$H$95),U83,0) -> 0
G96: 12 | H96: 360 | U96: =if(and($F$6>$H$95,$F$6<=$H$96),J83,0) -> 0 | V96: =if(and($F$6>$H$95,$F$6<=$H$96),K83,0) -> 0 | W96: =if(and($F$6>$H$95,$F$6<=$H$96),L83,0) -> 0 | X96: =if(and($F$6>$H$95,$F$6<=$H$96),M83,0) -> 0 | Y96: =if(and($F$6>$H$95,$F$6<=$H$96),N83,0) -> 0 | Z96: =if(and($F$6>$H$95,$F$6<=$H$96),O83,0) -> 0 | AA96: =if(and($F$6>$H$95,$F$6<=$H$96),P83,0) -> 0 | AB96: =if(and($F$6>$H$95,$F$6<=$H$96),Q83,0) -> 0 | ... AF96: =if(and($F$6>$H$95,$F$6<=$H$96),U83,0) -> 0
J98: =sum(J85:J96) -> 0 | K98: =sum(K85:K96) -> 0 | L98: =sum(L85:L96) -> 0 | M98: =sum(M85:M96) -> 7500 | N98: =sum(N85:N96) -> 12000 | O98: =sum(O85:O96) -> 43000 | P98: =sum(P85:P96) -> 11500 | Q98: =sum(Q85:Q96) -> 5250 | ... AF98: =sum(AF85:AF96) -> 0
D102: Calculations | F102: 30 day bands
D103: =D21 -> Stock 1 | H103: =H21 -> SkyRockets | J103: =if($H$103="",0,if($H$103="Sky Rockets",J21*$W$7*$AA$21,if($H$103="Steady Eddy",J21*$X$7*$AA$21,J21*$Y$7*$AA$21))) -> 1405.05 | K103: =if($H$103="",0,if($H$103="Sky Rockets",K21*$W$7*$AA$21,if($H$103="Steady Eddy",K21*$X$7*$AA$21,K21*$Y$7*$AA$21))) -> 495.9 | L103: =if($H$103="",0,if($H$103="Sky Rockets",L21*$W$7*$AA$21,if($H$103="Steady Eddy",L21*$X$7*$AA$21,L21*$Y$7*$AA$21))) -> 1446.375 | M103: =if($H$103="",0,if($H$103="Sky Rockets",M21*$W$7*$AA$21,if($H$103="Steady Eddy",M21*$X$7*$AA$21,M21*$Y$7*$AA$21))) -> 991.8 | N103: =if($H$103="",0,if($H$103="Sky Rockets",N21*$W$7*$AA$21,if($H$103="Steady Eddy",N21*$X$7*$AA$21,N21*$Y$7*$AA$21))) -> 495.9 | O103: =if($H$103="",0,if($H$103="Sky Rockets",O21*$W$7*$AA$21,if($H$103="Steady Eddy",O21*$X$7*$AA$21,O21*$Y$7*$AA$21))) -> 1900.95 | P103: =if($H$103="",0,if($H$103="Sky Rockets",P21*$W$7*$AA$21,if($H$103="Steady Eddy",P21*$X$7*$AA$21,P21*$Y$7*$AA$21))) -> 578.55 | Q103: =if($H$103="",0,if($H$103="Sky Rockets",Q21*$W$7*$AA$21,if($H$103="Steady Eddy",Q21*$X$7*$AA$21,Q21*$Y$7*$AA$21))) -> 495.9 | ... U103: =if($H$103="",0,if($H$103="Sky Rockets",U21*$W$7*$AA$21,if($H$103="Steady Eddy",U21*$X$7*$AA$21,U21*$Y$7*$AA$21))) -> 661.2
D104: =D22 -> Stock 2 | H104: =H22 -> Steady Eddy | J104: =if($H$104="",0,if($H$104="Sky Rockets",J22*$W$7*$AA$22,if($H$104="Steady Eddy",J22*$X$7*$AA$22,J22*$Y$7*$AA$22))) -> 2746.26 | K104: =if($H$104="",0,if($H$104="Sky Rockets",K22*$W$7*$AA$22,if($H$104="Steady Eddy",K22*$X$7*$AA$22,K22*$Y$7*$AA$22))) -> 1165.08 | L104: =if($H$104="",0,if($H$104="Sky Rockets",L22*$W$7*$AA$22,if($H$104="Steady Eddy",L22*$X$7*$AA$22,L22*$Y$7*$AA$22))) -> 2912.7 | M104: =if($H$104="",0,if($H$104="Sky Rockets",M22*$W$7*$AA$22,if($H$104="Steady Eddy",M22*$X$7*$AA$22,M22*$Y$7*$AA$22))) -> 1914.06 | N104: =if($H$104="",0,if($H$104="Sky Rockets",N22*$W$7*$AA$22,if($H$104="Steady Eddy",N22*$X$7*$AA$22,N22*$Y$7*$AA$22))) -> 1165.08 | O104: =if($H$104="",0,if($H$104="Sky Rockets",O22*$W$7*$AA$22,if($H$104="Steady Eddy",O22*$X$7*$AA$22,O22*$Y$7*$AA$22))) -> 3744.9 | P104: =if($H$104="",0,if($H$104="Sky Rockets",P22*$W$7*$AA$22,if($H$104="Steady Eddy",P22*$X$7*$AA$22,P22*$Y$7*$AA$22))) -> 1081.86 | Q104: =if($H$104="",0,if($H$104="Sky Rockets",Q22*$W$7*$AA$22,if($H$104="Steady Eddy",Q22*$X$7*$AA$22,Q22*$Y$7*$AA$22))) -> 0 | ... U104: =if($H$104="",0,if($H$104="Sky Rockets",U22*$W$7*$AA$22,if($H$104="Steady Eddy",U22*$X$7*$AA$22,U22*$Y$7*$AA$22))) -> 1248.3
D105: =D23 -> Stock 3 | H105: =H23 -> Slow Burn | J105: =if($H$105="",0,if($H$105="Sky Rockets",J23*$W$7*$AA$23,if($H$105="Steady Eddy",J23*$X$7*$AA$23,J23*$Y$7*$AA$23))) -> 1466.325 | K105: =if($H$105="",0,if($H$105="Sky Rockets",K23*$W$7*$AA$23,if($H$105="Steady Eddy",K23*$X$7*$AA$23,K23*$Y$7*$AA$23))) -> 0 | L105: =if($H$105="",0,if($H$105="Sky Rockets",L23*$W$7*$AA$23,if($H$105="Steady Eddy",L23*$X$7*$AA$23,L23*$Y$7*$AA$23))) -> 1424.43 | M105: =if($H$105="",0,if($H$105="Sky Rockets",M23*$W$7*$AA$23,if($H$105="Steady Eddy",M23*$X$7*$AA$23,M23*$Y$7*$AA$23))) -> 0 | N105: =if($H$105="",0,if($H$105="Sky Rockets",N23*$W$7*$AA$23,if($H$105="Steady Eddy",N23*$X$7*$AA$23,N23*$Y$7*$AA$23))) -> 670.32 | O105: =if($H$105="",0,if($H$105="Sky Rockets",O23*$W$7*$AA$23,if($H$105="Steady Eddy",O23*$X$7*$AA$23,O23*$Y$7*$AA$23))) -> 1843.38 | P105: =if($H$105="",0,if($H$105="Sky Rockets",P23*$W$7*$AA$23,if($H$105="Steady Eddy",P23*$X$7*$AA$23,P23*$Y$7*$AA$23))) -> 628.425 | Q105: =if($H$105="",0,if($H$105="Sky Rockets",Q23*$W$7*$AA$23,if($H$105="Steady Eddy",Q23*$X$7*$AA$23,Q23*$Y$7*$AA$23))) -> 0 | ... U105: =if($H$105="",0,if($H$105="Sky Rockets",U23*$W$7*$AA$23,if($H$105="Steady Eddy",U23*$X$7*$AA$23,U23*$Y$7*$AA$23))) -> 0
D106: =D24 -> Stock 4 | H106: =H24 -> Steady Eddy | J106: =if($H$106="",0,if($H$106="Sky Rockets",J24*$W$7*$AA$24,if($H$106="Steady Eddy",J24*$X$7*$AA$24,J24*$Y$7*$AA$24))) -> 3205.68 | K106: =if($H$106="",0,if($H$106="Sky Rockets",K24*$W$7*$AA$24,if($H$106="Steady Eddy",K24*$X$7*$AA$24,K24*$Y$7*$AA$24))) -> 0 | L106: =if($H$106="",0,if($H$106="Sky Rockets",L24*$W$7*$AA$24,if($H$106="Steady Eddy",L24*$X$7*$AA$24,L24*$Y$7*$AA$24))) -> 3290.04 | M106: =if($H$106="",0,if($H$106="Sky Rockets",M24*$W$7*$AA$24,if($H$106="Steady Eddy",M24*$X$7*$AA$24,M24*$Y$7*$AA$24))) -> 0 | N106: =if($H$106="",0,if($H$106="Sky Rockets",N24*$W$7*$AA$24,if($H$106="Steady Eddy",N24*$X$7*$AA$24,N24*$Y$7*$AA$24))) -> 1518.48 | O106: =if($H$106="",0,if($H$106="Sky Rockets",O24*$W$7*$AA$24,if($H$106="Steady Eddy",O24*$X$7*$AA$24,O24*$Y$7*$AA$24))) -> 4133.64 | P106: =if($H$106="",0,if($H$106="Sky Rockets",P24*$W$7*$AA$24,if($H$106="Steady Eddy",P24*$X$7*$AA$24,P24*$Y$7*$AA$24))) -> 0 | Q106: =if($H$106="",0,if($H$106="Sky Rockets",Q24*$W$7*$AA$24,if($H$106="Steady Eddy",Q24*$X$7*$AA$24,Q24*$Y$7*$AA$24))) -> 0 | ... U106: =if($H$106="",0,if($H$106="Sky Rockets",U24*$W$7*$AA$24,if($H$106="Steady Eddy",U24*$X$7*$AA$24,U24*$Y$7*$AA$24))) -> 0
D107: =D25 -> Stock 5 | H107: =H25 -> SkyRockets | J107: =if($H$107="",0,if($H$107="Sky Rockets",J25*$W$7*$AA$25,if($H$107="Steady Eddy",J25*$X$7*$AA$25,J25*$Y$7*$AA$25))) -> 1528.74 | K107: =if($H$107="",0,if($H$107="Sky Rockets",K25*$W$7*$AA$25,if($H$107="Steady Eddy",K25*$X$7*$AA$25,K25*$Y$7*$AA$25))) -> 0 | L107: =if($H$107="",0,if($H$107="Sky Rockets",L25*$W$7*$AA$25,if($H$107="Steady Eddy",L25*$X$7*$AA$25,L25*$Y$7*$AA$25))) -> 1613.67 | M107: =if($H$107="",0,if($H$107="Sky Rockets",M25*$W$7*$AA$25,if($H$107="Steady Eddy",M25*$X$7*$AA$25,M25*$Y$7*$AA$25))) -> 1104.09 | N107: =if($H$107="",0,if($H$107="Sky Rockets",N25*$W$7*$AA$25,if($H$107="Steady Eddy",N25*$X$7*$AA$25,N25*$Y$7*$AA$25))) -> 467.115 | O107: =if($H$107="",0,if($H$107="Sky Rockets",O25*$W$7*$AA$25,if($H$107="Steady Eddy",O25*$X$7*$AA$25,O25*$Y$7*$AA$25))) -> 2038.32 | P107: =if($H$107="",0,if($H$107="Sky Rockets",P25*$W$7*$AA$25,if($H$107="Steady Eddy",P25*$X$7*$AA$25,P25*$Y$7*$AA$25))) -> 0 | Q107: =if($H$107="",0,if($H$107="Sky Rockets",Q25*$W$7*$AA$25,if($H$107="Steady Eddy",Q25*$X$7*$AA$25,Q25*$Y$7*$AA$25))) -> 467.115 | ... U107: =if($H$107="",0,if($H$107="Sky Rockets",U25*$W$7*$AA$25,if($H$107="Steady Eddy",U25*$X$7*$AA$25,U25*$Y$7*$AA$25))) -> 0
D108: =D26 -> Stock 6 | H108: =H26 -> Slow Burn | J108: =if($H$108="",0,if($H$108="Sky Rockets",J26*$W$7*$AA$26,if($H$108="Steady Eddy",J26*$X$7*$AA$26,J26*$Y$7*$AA$26))) -> 1496.25 | K108: =if($H$108="",0,if($H$108="Sky Rockets",K26*$W$7*$AA$26,if($H$108="Steady Eddy",K26*$X$7*$AA$26,K26*$Y$7*$AA$26))) -> 555.75 | L108: =if($H$108="",0,if($H$108="Sky Rockets",L26*$W$7*$AA$26,if($H$108="Steady Eddy",L26*$X$7*$AA$26,L26*$Y$7*$AA$26))) -> 0 | M108: =if($H$108="",0,if($H$108="Sky Rockets",M26*$W$7*$AA$26,if($H$108="Steady Eddy",M26*$X$7*$AA$26,M26*$Y$7*$AA$26))) -> 1068.75 | N108: =if($H$108="",0,if($H$108="Sky Rockets",N26*$W$7*$AA$26,if($H$108="Steady Eddy",N26*$X$7*$AA$26,N26*$Y$7*$AA$26))) -> 0 | O108: =if($H$108="",0,if($H$108="Sky Rockets",O26*$W$7*$AA$26,if($H$108="Steady Eddy",O26*$X$7*$AA$26,O26*$Y$7*$AA$26))) -> 2009.25 | P108: =if($H$108="",0,if($H$108="Sky Rockets",P26*$W$7*$AA$26,if($H$108="Steady Eddy",P26*$X$7*$AA$26,P26*$Y$7*$AA$26))) -> 0 | Q108: =if($H$108="",0,if($H$108="Sky Rockets",Q26*$W$7*$AA$26,if($H$108="Steady Eddy",Q26*$X$7*$AA$26,Q26*$Y$7*$AA$26))) -> 555.75 | ... U108: =if($H$108="",0,if($H$108="Sky Rockets",U26*$W$7*$AA$26,if($H$108="Steady Eddy",U26*$X$7*$AA$26,U26*$Y$7*$AA$26))) -> 726.75
D109: =D27 -> Stock 7 | H109: =H27 -> SkyRockets | J109: =if($H$109="",0,if($H$109="Sky Rockets",J27*$W$7*$AA$27,if($H$109="Steady Eddy",J27*$X$7*$AA$27,J27*$Y$7*$AA$27))) -> 1463.19 | K109: =if($H$109="",0,if($H$109="Sky Rockets",K27*$W$7*$AA$27,if($H$109="Steady Eddy",K27*$X$7*$AA$27,K27*$Y$7*$AA$27))) -> 645.525 | L109: =if($H$109="",0,if($H$109="Sky Rockets",L27*$W$7*$AA$27,if($H$109="Steady Eddy",L27*$X$7*$AA$27,L27*$Y$7*$AA$27))) -> 0 | M109: =if($H$109="",0,if($H$109="Sky Rockets",M27*$W$7*$AA$27,if($H$109="Steady Eddy",M27*$X$7*$AA$27,M27*$Y$7*$AA$27))) -> 1032.84 | N109: =if($H$109="",0,if($H$109="Sky Rockets",N27*$W$7*$AA$27,if($H$109="Steady Eddy",N27*$X$7*$AA$27,N27*$Y$7*$AA$27))) -> 0 | O109: =if($H$109="",0,if($H$109="Sky Rockets",O27*$W$7*$AA$27,if($H$109="Steady Eddy",O27*$X$7*$AA$27,O27*$Y$7*$AA$27))) -> 0 | P109: =if($H$109="",0,if($H$109="Sky Rockets",P27*$W$7*$AA$27,if($H$109="Steady Eddy",P27*$X$7*$AA$27,P27*$Y$7*$AA$27))) -> 0 | Q109: =if($H$109="",0,if($H$109="Sky Rockets",Q27*$W$7*$AA$27,if($H$109="Steady Eddy",Q27*$X$7*$AA$27,Q27*$Y$7*$AA$27))) -> 645.525 | ... U109: =if($H$109="",0,if($H$109="Sky Rockets",U27*$W$7*$AA$27,if($H$109="Steady Eddy",U27*$X$7*$AA$27,U27*$Y$7*$AA$27))) -> 129.105
D110: =D28 -> Stock 8 | H110: =H28 -> SkyRockets | J110: =if($H$110="",0,if($H$110="Sky Rockets",J28*$W$7*$AA$28,if($H$110="Steady Eddy",J28*$X$7*$AA$28,J28*$Y$7*$AA$28))) -> 1602.84 | K110: =if($H$110="",0,if($H$110="Sky Rockets",K28*$W$7*$AA$28,if($H$110="Steady Eddy",K28*$X$7*$AA$28,K28*$Y$7*$AA$28))) -> 736.44 | L110: =if($H$110="",0,if($H$110="Sky Rockets",L28*$W$7*$AA$28,if($H$110="Steady Eddy",L28*$X$7*$AA$28,L28*$Y$7*$AA$28))) -> 0 | M110: =if($H$110="",0,if($H$110="Sky Rockets",M28*$W$7*$AA$28,if($H$110="Steady Eddy",M28*$X$7*$AA$28,M28*$Y$7*$AA$28))) -> 1169.64 | N110: =if($H$110="",0,if($H$110="Sky Rockets",N28*$W$7*$AA$28,if($H$110="Steady Eddy",N28*$X$7*$AA$28,N28*$Y$7*$AA$28))) -> 1602.84 | O110: =if($H$110="",0,if($H$110="Sky Rockets",O28*$W$7*$AA$28,if($H$110="Steady Eddy",O28*$X$7*$AA$28,O28*$Y$7*$AA$28))) -> 0 | P110: =if($H$110="",0,if($H$110="Sky Rockets",P28*$W$7*$AA$28,if($H$110="Steady Eddy",P28*$X$7*$AA$28,P28*$Y$7*$AA$28))) -> 0 | Q110: =if($H$110="",0,if($H$110="Sky Rockets",Q28*$W$7*$AA$28,if($H$110="Steady Eddy",Q28*$X$7*$AA$28,Q28*$Y$7*$AA$28))) -> 736.44 | ... U110: =if($H$110="",0,if($H$110="Sky Rockets",U28*$W$7*$AA$28,if($H$110="Steady Eddy",U28*$X$7*$AA$28,U28*$Y$7*$AA$28))) -> 216.6
D111: =D29 -> Stock 9 | H111: =H29 -> Steady Eddy | J111: =if($H$111="",0,if($H$111="Sky Rockets",J29*$W$7*$AA$29,if($H$111="Steady Eddy",J29*$X$7*$AA$29,J29*$Y$7*$AA$29))) -> 2965.14 | K111: =if($H$111="",0,if($H$111="Sky Rockets",K29*$W$7*$AA$29,if($H$111="Steady Eddy",K29*$X$7*$AA$29,K29*$Y$7*$AA$29))) -> 1046.52 | L111: =if($H$111="",0,if($H$111="Sky Rockets",L29*$W$7*$AA$29,if($H$111="Steady Eddy",L29*$X$7*$AA$29,L29*$Y$7*$AA$29))) -> 3226.77 | M111: =if($H$111="",0,if($H$111="Sky Rockets",M29*$W$7*$AA$29,if($H$111="Steady Eddy",M29*$X$7*$AA$29,M29*$Y$7*$AA$29))) -> 2093.04 | N111: =if($H$111="",0,if($H$111="Sky Rockets",N29*$W$7*$AA$29,if($H$111="Steady Eddy",N29*$X$7*$AA$29,N29*$Y$7*$AA$29))) -> 2790.72 | O111: =if($H$111="",0,if($H$111="Sky Rockets",O29*$W$7*$AA$29,if($H$111="Steady Eddy",O29*$X$7*$AA$29,O29*$Y$7*$AA$29))) -> 0 | P111: =if($H$111="",0,if($H$111="Sky Rockets",P29*$W$7*$AA$29,if($H$111="Steady Eddy",P29*$X$7*$AA$29,P29*$Y$7*$AA$29))) -> 0 | Q111: =if($H$111="",0,if($H$111="Sky Rockets",Q29*$W$7*$AA$29,if($H$111="Steady Eddy",Q29*$X$7*$AA$29,Q29*$Y$7*$AA$29))) -> 1046.52 | ... U111: =if($H$111="",0,if($H$111="Sky Rockets",U29*$W$7*$AA$29,if($H$111="Steady Eddy",U29*$X$7*$AA$29,U29*$Y$7*$AA$29))) -> 610.47
D112: =D30 -> Stock 10 | H112: =H30 -> Steady Eddy | J112: =if($H$112="",0,if($H$112="Sky Rockets",J30*$W$7*$AA$30,if($H$112="Steady Eddy",J30*$X$7*$AA$30,J30*$Y$7*$AA$30))) -> 2896.74 | K112: =if($H$112="",0,if($H$112="Sky Rockets",K30*$W$7*$AA$30,if($H$112="Steady Eddy",K30*$X$7*$AA$30,K30*$Y$7*$AA$30))) -> 1228.92 | L112: =if($H$112="",0,if($H$112="Sky Rockets",L30*$W$7*$AA$30,if($H$112="Steady Eddy",L30*$X$7*$AA$30,L30*$Y$7*$AA$30))) -> 2721.18 | M112: =if($H$112="",0,if($H$112="Sky Rockets",M30*$W$7*$AA$30,if($H$112="Steady Eddy",M30*$X$7*$AA$30,M30*$Y$7*$AA$30))) -> 2018.94 | N112: =if($H$112="",0,if($H$112="Sky Rockets",N30*$W$7*$AA$30,if($H$112="Steady Eddy",N30*$X$7*$AA$30,N30*$Y$7*$AA$30))) -> 2984.52 | O112: =if($H$112="",0,if($H$112="Sky Rockets",O30*$W$7*$AA$30,if($H$112="Steady Eddy",O30*$X$7*$AA$30,O30*$Y$7*$AA$30))) -> 2721.18 | P112: =if($H$112="",0,if($H$112="Sky Rockets",P30*$W$7*$AA$30,if($H$112="Steady Eddy",P30*$X$7*$AA$30,P30*$Y$7*$AA$30))) -> 0 | Q112: =if($H$112="",0,if($H$112="Sky Rockets",Q30*$W$7*$AA$30,if($H$112="Steady Eddy",Q30*$X$7*$AA$30,Q30*$Y$7*$AA$30))) -> 1228.92 | ... U112: =if($H$112="",0,if($H$112="Sky Rockets",U30*$W$7*$AA$30,if($H$112="Steady Eddy",U30*$X$7*$AA$30,U30*$Y$7*$AA$30))) -> 87.78
D113: =D31 -> Stock 11 | H113: =H31 -> Steady Eddy | J113: =if($H$113="",0,if($H$113="Sky Rockets",J31*$W$7*$AA$31,if($H$113="Steady Eddy",J31*$X$7*$AA$31,J31*$Y$7*$AA$31))) -> 3092.25 | K113: =if($H$113="",0,if($H$113="Sky Rockets",K31*$W$7*$AA$31,if($H$113="Steady Eddy",K31*$X$7*$AA$31,K31*$Y$7*$AA$31))) -> 1413.6 | L113: =if($H$113="",0,if($H$113="Sky Rockets",L31*$W$7*$AA$31,if($H$113="Steady Eddy",L31*$X$7*$AA$31,L31*$Y$7*$AA$31))) -> 3092.25 | M113: =if($H$113="",0,if($H$113="Sky Rockets",M31*$W$7*$AA$31,if($H$113="Steady Eddy",M31*$X$7*$AA$31,M31*$Y$7*$AA$31))) -> 0 | N113: =if($H$113="",0,if($H$113="Sky Rockets",N31*$W$7*$AA$31,if($H$113="Steady Eddy",N31*$X$7*$AA$31,N31*$Y$7*$AA$31))) -> 3180.6 | O113: =if($H$113="",0,if($H$113="Sky Rockets",O31*$W$7*$AA$31,if($H$113="Steady Eddy",O31*$X$7*$AA$31,O31*$Y$7*$AA$31))) -> 3092.25 | P113: =if($H$113="",0,if($H$113="Sky Rockets",P31*$W$7*$AA$31,if($H$113="Steady Eddy",P31*$X$7*$AA$31,P31*$Y$7*$AA$31))) -> 1325.25 | Q113: =if($H$113="",0,if($H$113="Sky Rockets",Q31*$W$7*$AA$31,if($H$113="Steady Eddy",Q31*$X$7*$AA$31,Q31*$Y$7*$AA$31))) -> 1413.6 | ... U113: =if($H$113="",0,if($H$113="Sky Rockets",U31*$W$7*$AA$31,if($H$113="Steady Eddy",U31*$X$7*$AA$31,U31*$Y$7*$AA$31))) -> 441.75
D114: =D32 -> Stock 12 | H114: =H32 -> Steady Eddy | J114: =if($H$114="",0,if($H$114="Sky Rockets",J32*$W$7*$AA$32,if($H$114="Steady Eddy",J32*$X$7*$AA$32,J32*$Y$7*$AA$32))) -> 3378.96 | K114: =if($H$114="",0,if($H$114="Sky Rockets",K32*$W$7*$AA$32,if($H$114="Steady Eddy",K32*$X$7*$AA$32,K32*$Y$7*$AA$32))) -> 1600.56 | L114: =if($H$114="",0,if($H$114="Sky Rockets",L32*$W$7*$AA$32,if($H$114="Steady Eddy",L32*$X$7*$AA$32,L32*$Y$7*$AA$32))) -> 3467.88 | M114: =if($H$114="",0,if($H$114="Sky Rockets",M32*$W$7*$AA$32,if($H$114="Steady Eddy",M32*$X$7*$AA$32,M32*$Y$7*$AA$32))) -> 0 | N114: =if($H$114="",0,if($H$114="Sky Rockets",N32*$W$7*$AA$32,if($H$114="Steady Eddy",N32*$X$7*$AA$32,N32*$Y$7*$AA$32))) -> 3378.96 | O114: =if($H$114="",0,if($H$114="Sky Rockets",O32*$W$7*$AA$32,if($H$114="Steady Eddy",O32*$X$7*$AA$32,O32*$Y$7*$AA$32))) -> 3467.88 | P114: =if($H$114="",0,if($H$114="Sky Rockets",P32*$W$7*$AA$32,if($H$114="Steady Eddy",P32*$X$7*$AA$32,P32*$Y$7*$AA$32))) -> 1600.56 | Q114: =if($H$114="",0,if($H$114="Sky Rockets",Q32*$W$7*$AA$32,if($H$114="Steady Eddy",Q32*$X$7*$AA$32,Q32*$Y$7*$AA$32))) -> 1600.56 | ... U114: =if($H$114="",0,if($H$114="Sky Rockets",U32*$W$7*$AA$32,if($H$114="Steady Eddy",U32*$X$7*$AA$32,U32*$Y$7*$AA$32))) -> 0
D115: =D33 -> Stock 13 | H115: =H33 -> Steady Eddy | J115: =if($H$115="",0,if($H$115="Sky Rockets",J33*$W$7*$AA$33,if($H$115="Steady Eddy",J33*$X$7*$AA$33,J33*$Y$7*$AA$33))) -> 3221.64 | K115: =if($H$115="",0,if($H$115="Sky Rockets",K33*$W$7*$AA$33,if($H$115="Steady Eddy",K33*$X$7*$AA$33,K33*$Y$7*$AA$33))) -> 1163.37 | L115: =if($H$115="",0,if($H$115="Sky Rockets",L33*$W$7*$AA$33,if($H$115="Steady Eddy",L33*$X$7*$AA$33,L33*$Y$7*$AA$33))) -> 3400.62 | M115: =if($H$115="",0,if($H$115="Sky Rockets",M33*$W$7*$AA$33,if($H$115="Steady Eddy",M33*$X$7*$AA$33,M33*$Y$7*$AA$33))) -> 0 | N115: =if($H$115="",0,if($H$115="Sky Rockets",N33*$W$7*$AA$33,if($H$115="Steady Eddy",N33*$X$7*$AA$33,N33*$Y$7*$AA$33))) -> 2953.17 | O115: =if($H$115="",0,if($H$115="Sky Rockets",O33*$W$7*$AA$33,if($H$115="Steady Eddy",O33*$X$7*$AA$33,O33*$Y$7*$AA$33))) -> 3400.62 | P115: =if($H$115="",0,if($H$115="Sky Rockets",P33*$W$7*$AA$33,if($H$115="Steady Eddy",P33*$X$7*$AA$33,P33*$Y$7*$AA$33))) -> 1431.84 | Q115: =if($H$115="",0,if($H$115="Sky Rockets",Q33*$W$7*$AA$33,if($H$115="Steady Eddy",Q33*$X$7*$AA$33,Q33*$Y$7*$AA$33))) -> 1163.37 | ... U115: =if($H$115="",0,if($H$115="Sky Rockets",U33*$W$7*$AA$33,if($H$115="Steady Eddy",U33*$X$7*$AA$33,U33*$Y$7*$AA$33))) -> 0
D116: =D34 -> Stock 14 | H116: =H34 -> SkyRockets | J116: =if($H$116="",0,if($H$116="Sky Rockets",J34*$W$7*$AA$34,if($H$116="Steady Eddy",J34*$X$7*$AA$34,J34*$Y$7*$AA$34))) -> 1576.05 | K116: =if($H$116="",0,if($H$116="Sky Rockets",K34*$W$7*$AA$34,if($H$116="Steady Eddy",K34*$X$7*$AA$34,K34*$Y$7*$AA$34))) -> 675.45 | L116: =if($H$116="",0,if($H$116="Sky Rockets",L34*$W$7*$AA$34,if($H$116="Steady Eddy",L34*$X$7*$AA$34,L34*$Y$7*$AA$34))) -> 1576.05 | M116: =if($H$116="",0,if($H$116="Sky Rockets",M34*$W$7*$AA$34,if($H$116="Steady Eddy",M34*$X$7*$AA$34,M34*$Y$7*$AA$34))) -> 1125.75 | N116: =if($H$116="",0,if($H$116="Sky Rockets",N34*$W$7*$AA$34,if($H$116="Steady Eddy",N34*$X$7*$AA$34,N34*$Y$7*$AA$34))) -> 0 | O116: =if($H$116="",0,if($H$116="Sky Rockets",O34*$W$7*$AA$34,if($H$116="Steady Eddy",O34*$X$7*$AA$34,O34*$Y$7*$AA$34))) -> 0 | P116: =if($H$116="",0,if($H$116="Sky Rockets",P34*$W$7*$AA$34,if($H$116="Steady Eddy",P34*$X$7*$AA$34,P34*$Y$7*$AA$34))) -> 675.45 | Q116: =if($H$116="",0,if($H$116="Sky Rockets",Q34*$W$7*$AA$34,if($H$116="Steady Eddy",Q34*$X$7*$AA$34,Q34*$Y$7*$AA$34))) -> 0 | ... U116: =if($H$116="",0,if($H$116="Sky Rockets",U34*$W$7*$AA$34,if($H$116="Steady Eddy",U34*$X$7*$AA$34,U34*$Y$7*$AA$34))) -> 0
D117: =D35 -> Stock 15 | H117: =H35 -> SkyRockets | J117: =if($H$117="",0,if($H$117="Sky Rockets",J35*$W$7*$AA$35,if($H$117="Steady Eddy",J35*$X$7*$AA$35,J35*$Y$7*$AA$35))) -> 1540.71 | K117: =if($H$117="",0,if($H$117="Sky Rockets",K35*$W$7*$AA$35,if($H$117="Steady Eddy",K35*$X$7*$AA$35,K35*$Y$7*$AA$35))) -> 770.355 | L117: =if($H$117="",0,if($H$117="Sky Rockets",L35*$W$7*$AA$35,if($H$117="Steady Eddy",L35*$X$7*$AA$35,L35*$Y$7*$AA$35))) -> 1450.08 | M117: =if($H$117="",0,if($H$117="Sky Rockets",M35*$W$7*$AA$35,if($H$117="Steady Eddy",M35*$X$7*$AA$35,M35*$Y$7*$AA$35))) -> 1087.56 | N117: =if($H$117="",0,if($H$117="Sky Rockets",N35*$W$7*$AA$35,if($H$117="Steady Eddy",N35*$X$7*$AA$35,N35*$Y$7*$AA$35))) -> 0 | O117: =if($H$117="",0,if($H$117="Sky Rockets",O35*$W$7*$AA$35,if($H$117="Steady Eddy",O35*$X$7*$AA$35,O35*$Y$7*$AA$35))) -> 0 | P117: =if($H$117="",0,if($H$117="Sky Rockets",P35*$W$7*$AA$35,if($H$117="Steady Eddy",P35*$X$7*$AA$35,P35*$Y$7*$AA$35))) -> 634.41 | Q117: =if($H$117="",0,if($H$117="Sky Rockets",Q35*$W$7*$AA$35,if($H$117="Steady Eddy",Q35*$X$7*$AA$35,Q35*$Y$7*$AA$35))) -> 0 | ... U117: =if($H$117="",0,if($H$117="Sky Rockets",U35*$W$7*$AA$35,if($H$117="Steady Eddy",U35*$X$7*$AA$35,U35*$Y$7*$AA$35))) -> 0
D118: =D36 -> Stock 16 | H118: =H36 -> SkyRockets | J118: =if($H$118="",0,if($H$118="Sky Rockets",J36*$W$7*$AA$36,if($H$118="Steady Eddy",J36*$X$7*$AA$36,J36*$Y$7*$AA$36))) -> 1687.2 | K118: =if($H$118="",0,if($H$118="Sky Rockets",K36*$W$7*$AA$36,if($H$118="Steady Eddy",K36*$X$7*$AA$36,K36*$Y$7*$AA$36))) -> 866.4 | L118: =if($H$118="",0,if($H$118="Sky Rockets",L36*$W$7*$AA$36,if($H$118="Steady Eddy",L36*$X$7*$AA$36,L36*$Y$7*$AA$36))) -> 1641.6 | M118: =if($H$118="",0,if($H$118="Sky Rockets",M36*$W$7*$AA$36,if($H$118="Steady Eddy",M36*$X$7*$AA$36,M36*$Y$7*$AA$36))) -> 1231.2 | N118: =if($H$118="",0,if($H$118="Sky Rockets",N36*$W$7*$AA$36,if($H$118="Steady Eddy",N36*$X$7*$AA$36,N36*$Y$7*$AA$36))) -> 2234.4 | O118: =if($H$118="",0,if($H$118="Sky Rockets",O36*$W$7*$AA$36,if($H$118="Steady Eddy",O36*$X$7*$AA$36,O36*$Y$7*$AA$36))) -> 2097.6 | P118: =if($H$118="",0,if($H$118="Sky Rockets",P36*$W$7*$AA$36,if($H$118="Steady Eddy",P36*$X$7*$AA$36,P36*$Y$7*$AA$36))) -> 775.2 | Q118: =if($H$118="",0,if($H$118="Sky Rockets",Q36*$W$7*$AA$36,if($H$118="Steady Eddy",Q36*$X$7*$AA$36,Q36*$Y$7*$AA$36))) -> 0 | ... U118: =if($H$118="",0,if($H$118="Sky Rockets",U36*$W$7*$AA$36,if($H$118="Steady Eddy",U36*$X$7*$AA$36,U36*$Y$7*$AA$36))) -> 0
D119: =D37 -> Stock 17 | H119: =H37 -> Slow Burn | J119: =if($H$119="",0,if($H$119="Sky Rockets",J37*$W$7*$AA$37,if($H$119="Steady Eddy",J37*$X$7*$AA$37,J37*$Y$7*$AA$37))) -> 1651.86 | K119: =if($H$119="",0,if($H$119="Sky Rockets",K37*$W$7*$AA$37,if($H$119="Steady Eddy",K37*$X$7*$AA$37,K37*$Y$7*$AA$37))) -> 504.735 | L119: =if($H$119="",0,if($H$119="Sky Rockets",L37*$W$7*$AA$37,if($H$119="Steady Eddy",L37*$X$7*$AA$37,L37*$Y$7*$AA$37))) -> 1605.975 | M119: =if($H$119="",0,if($H$119="Sky Rockets",M37*$W$7*$AA$37,if($H$119="Steady Eddy",M37*$X$7*$AA$37,M37*$Y$7*$AA$37))) -> 1193.01 | N119: =if($H$119="",0,if($H$119="Sky Rockets",N37*$W$7*$AA$37,if($H$119="Steady Eddy",N37*$X$7*$AA$37,N37*$Y$7*$AA$37))) -> 1881.285 | O119: =if($H$119="",0,if($H$119="Sky Rockets",O37*$W$7*$AA$37,if($H$119="Steady Eddy",O37*$X$7*$AA$37,O37*$Y$7*$AA$37))) -> 2064.825 | P119: =if($H$119="",0,if($H$119="Sky Rockets",P37*$W$7*$AA$37,if($H$119="Steady Eddy",P37*$X$7*$AA$37,P37*$Y$7*$AA$37))) -> 734.16 | Q119: =if($H$119="",0,if($H$119="Sky Rockets",Q37*$W$7*$AA$37,if($H$119="Steady Eddy",Q37*$X$7*$AA$37,Q37*$Y$7*$AA$37))) -> 0 | ... U119: =if($H$119="",0,if($H$119="Sky Rockets",U37*$W$7*$AA$37,if($H$119="Steady Eddy",U37*$X$7*$AA$37,U37*$Y$7*$AA$37))) -> 0
D120: =D38 -> Stock 18 | H120: =H38 -> Slow Burn | J120: =if($H$120="",0,if($H$120="Sky Rockets",J38*$W$7*$AA$38,if($H$120="Steady Eddy",J38*$X$7*$AA$38,J38*$Y$7*$AA$38))) -> 1477.44 | K120: =if($H$120="",0,if($H$120="Sky Rockets",K38*$W$7*$AA$38,if($H$120="Steady Eddy",K38*$X$7*$AA$38,K38*$Y$7*$AA$38))) -> 554.04 | L120: =if($H$120="",0,if($H$120="Sky Rockets",L38*$W$7*$AA$38,if($H$120="Steady Eddy",L38*$X$7*$AA$38,L38*$Y$7*$AA$38))) -> 1569.78 | M120: =if($H$120="",0,if($H$120="Sky Rockets",M38*$W$7*$AA$38,if($H$120="Steady Eddy",M38*$X$7*$AA$38,M38*$Y$7*$AA$38))) -> 1015.74 | N120: =if($H$120="",0,if($H$120="Sky Rockets",N38*$W$7*$AA$38,if($H$120="Steady Eddy",N38*$X$7*$AA$38,N38*$Y$7*$AA$38))) -> 1939.14 | O120: =if($H$120="",0,if($H$120="Sky Rockets",O38*$W$7*$AA$38,if($H$120="Steady Eddy",O38*$X$7*$AA$38,O38*$Y$7*$AA$38))) -> 2031.48 | P120: =if($H$120="",0,if($H$120="Sky Rockets",P38*$W$7*$AA$38,if($H$120="Steady Eddy",P38*$X$7*$AA$38,P38*$Y$7*$AA$38))) -> 554.04 | Q120: =if($H$120="",0,if($H$120="Sky Rockets",Q38*$W$7*$AA$38,if($H$120="Steady Eddy",Q38*$X$7*$AA$38,Q38*$Y$7*$AA$38))) -> 554.04 | ... U120: =if($H$120="",0,if($H$120="Sky Rockets",U38*$W$7*$AA$38,if($H$120="Steady Eddy",U38*$X$7*$AA$38,U38*$Y$7*$AA$38))) -> 184.68
D121: =D39 -> Stock 19 | H121: =H39 -> SkyRockets | J121: =if($H$121="",0,if($H$121="Sky Rockets",J39*$W$7*$AA$39,if($H$121="Steady Eddy",J39*$X$7*$AA$39,J39*$Y$7*$AA$39))) -> 1440.105 | K121: =if($H$121="",0,if($H$121="Sky Rockets",K39*$W$7*$AA$39,if($H$121="Steady Eddy",K39*$X$7*$AA$39,K39*$Y$7*$AA$39))) -> 650.37 | L121: =if($H$121="",0,if($H$121="Sky Rockets",L39*$W$7*$AA$39,if($H$121="Steady Eddy",L39*$X$7*$AA$39,L39*$Y$7*$AA$39))) -> 1718.835 | M121: =if($H$121="",0,if($H$121="Sky Rockets",M39*$W$7*$AA$39,if($H$121="Steady Eddy",M39*$X$7*$AA$39,M39*$Y$7*$AA$39))) -> 975.555 | N121: =if($H$121="",0,if($H$121="Sky Rockets",N39*$W$7*$AA$39,if($H$121="Steady Eddy",N39*$X$7*$AA$39,N39*$Y$7*$AA$39))) -> 2044.02 | O121: =if($H$121="",0,if($H$121="Sky Rockets",O39*$W$7*$AA$39,if($H$121="Steady Eddy",O39*$X$7*$AA$39,O39*$Y$7*$AA$39))) -> 2183.385 | P121: =if($H$121="",0,if($H$121="Sky Rockets",P39*$W$7*$AA$39,if($H$121="Steady Eddy",P39*$X$7*$AA$39,P39*$Y$7*$AA$39))) -> 511.005 | Q121: =if($H$121="",0,if($H$121="Sky Rockets",Q39*$W$7*$AA$39,if($H$121="Steady Eddy",Q39*$X$7*$AA$39,Q39*$Y$7*$AA$39))) -> 650.37 | ... U121: =if($H$121="",0,if($H$121="Sky Rockets",U39*$W$7*$AA$39,if($H$121="Steady Eddy",U39*$X$7*$AA$39,U39*$Y$7*$AA$39))) -> 325.185
D122: =D40 -> Stock 20 | H122: =H40 -> Steady Eddy | J122: =if($H$122="",0,if($H$122="Sky Rockets",J40*$W$7*$AA$40,if($H$122="Steady Eddy",J40*$X$7*$AA$40,J40*$Y$7*$AA$40))) -> 3178.32 | K122: =if($H$122="",0,if($H$122="Sky Rockets",K40*$W$7*$AA$40,if($H$122="Steady Eddy",K40*$X$7*$AA$40,K40*$Y$7*$AA$40))) -> 1682.64 | L122: =if($H$122="",0,if($H$122="Sky Rockets",L40*$W$7*$AA$40,if($H$122="Steady Eddy",L40*$X$7*$AA$40,L40*$Y$7*$AA$40))) -> 3552.24 | M122: =if($H$122="",0,if($H$122="Sky Rockets",M40*$W$7*$AA$40,if($H$122="Steady Eddy",M40*$X$7*$AA$40,M40*$Y$7*$AA$40))) -> 2243.52 | N122: =if($H$122="",0,if($H$122="Sky Rockets",N40*$W$7*$AA$40,if($H$122="Steady Eddy",N40*$X$7*$AA$40,N40*$Y$7*$AA$40))) -> 4487.04 | O122: =if($H$122="",0,if($H$122="Sky Rockets",O40*$W$7*$AA$40,if($H$122="Steady Eddy",O40*$X$7*$AA$40,O40*$Y$7*$AA$40))) -> 4487.04 | P122: =if($H$122="",0,if($H$122="Sky Rockets",P40*$W$7*$AA$40,if($H$122="Steady Eddy",P40*$X$7*$AA$40,P40*$Y$7*$AA$40))) -> 1308.72 | Q122: =if($H$122="",0,if($H$122="Sky Rockets",Q40*$W$7*$AA$40,if($H$122="Steady Eddy",Q40*$X$7*$AA$40,Q40*$Y$7*$AA$40))) -> 1682.64 | ... U122: =if($H$122="",0,if($H$122="Sky Rockets",U40*$W$7*$AA$40,if($H$122="Steady Eddy",U40*$X$7*$AA$40,U40*$Y$7*$AA$40))) -> 747.84
D124: Calculations | F124: 60 day bands | H124: 30 | J124: =sum(J103:J122) -> 43020.75 | K124: =sum(K103:K122) -> 15755.655 | L124: =sum(L103:L122) -> 39710.475 | M124: =sum(M103:M122) -> 20265.495 | N124: =sum(N103:N122) -> 33793.59 | O124: =sum(O103:O122) -> 41216.7 | P124: =sum(P103:P122) -> 11839.47 | Q124: =sum(Q103:Q122) -> 12240.75 | ... U124: =sum(U103:U122) -> 5379.66
D126: =D103 -> Stock 1 | H126: =H103 -> SkyRockets | J126: =if($H$126="",0,if($H$126="Sky Rockets",J21*$W$8*$AA$21,if($H$126="Steady Eddy",J21*$X$8*$AA$21,J21*$Y$8*$AA$21))) -> 4215.15 | K126: =if($H$126="",0,if($H$126="Sky Rockets",K21*$W$8*$AA$21,if($H$126="Steady Eddy",K21*$X$8*$AA$21,K21*$Y$8*$AA$21))) -> 1487.7 | L126: =if($H$126="",0,if($H$126="Sky Rockets",L21*$W$8*$AA$21,if($H$126="Steady Eddy",L21*$X$8*$AA$21,L21*$Y$8*$AA$21))) -> 4339.125 | M126: =if($H$126="",0,if($H$126="Sky Rockets",M21*$W$8*$AA$21,if($H$126="Steady Eddy",M21*$X$8*$AA$21,M21*$Y$8*$AA$21))) -> 2975.4 | N126: =if($H$126="",0,if($H$126="Sky Rockets",N21*$W$8*$AA$21,if($H$126="Steady Eddy",N21*$X$8*$AA$21,N21*$Y$8*$AA$21))) -> 1487.7 | O126: =if($H$126="",0,if($H$126="Sky Rockets",O21*$W$8*$AA$21,if($H$126="Steady Eddy",O21*$X$8*$AA$21,O21*$Y$8*$AA$21))) -> 5702.85 | P126: =if($H$126="",0,if($H$126="Sky Rockets",P21*$W$8*$AA$21,if($H$126="Steady Eddy",P21*$X$8*$AA$21,P21*$Y$8*$AA$21))) -> 1735.65 | Q126: =if($H$126="",0,if($H$126="Sky Rockets",Q21*$W$8*$AA$21,if($H$126="Steady Eddy",Q21*$X$8*$AA$21,Q21*$Y$8*$AA$21))) -> 1487.7 | ... U126: =if($H$126="",0,if($H$126="Sky Rockets",U21*$W$8*$AA$21,if($H$126="Steady Eddy",U21*$X$8*$AA$21,U21*$Y$8*$AA$21))) -> 1983.6
D127: =D104 -> Stock 2 | H127: =H104 -> Steady Eddy | J127: =if($H$127="",0,if($H$127="Sky Rockets",J22*$W$8*$AA$22,if($H$127="Steady Eddy",J22*$X$8*$AA$22,J22*$Y$8*$AA$22))) -> 4119.39 | K127: =if($H$127="",0,if($H$127="Sky Rockets",K22*$W$8*$AA$22,if($H$127="Steady Eddy",K22*$X$8*$AA$22,K22*$Y$8*$AA$22))) -> 1747.62 | L127: =if($H$127="",0,if($H$127="Sky Rockets",L22*$W$8*$AA$22,if($H$127="Steady Eddy",L22*$X$8*$AA$22,L22*$Y$8*$AA$22))) -> 4369.05 | M127: =if($H$127="",0,if($H$127="Sky Rockets",M22*$W$8*$AA$22,if($H$127="Steady Eddy",M22*$X$8*$AA$22,M22*$Y$8*$AA$22))) -> 2871.09 | N127: =if($H$127="",0,if($H$127="Sky Rockets",N22*$W$8*$AA$22,if($H$127="Steady Eddy",N22*$X$8*$AA$22,N22*$Y$8*$AA$22))) -> 1747.62 | O127: =if($H$127="",0,if($H$127="Sky Rockets",O22*$W$8*$AA$22,if($H$127="Steady Eddy",O22*$X$8*$AA$22,O22*$Y$8*$AA$22))) -> 5617.35 | P127: =if($H$127="",0,if($H$127="Sky Rockets",P22*$W$8*$AA$22,if($H$127="Steady Eddy",P22*$X$8*$AA$22,P22*$Y$8*$AA$22))) -> 1622.79 | Q127: =if($H$127="",0,if($H$127="Sky Rockets",Q22*$W$8*$AA$22,if($H$127="Steady Eddy",Q22*$X$8*$AA$22,Q22*$Y$8*$AA$22))) -> 0 | ... U127: =if($H$127="",0,if($H$127="Sky Rockets",U22*$W$8*$AA$22,if($H$127="Steady Eddy",U22*$X$8*$AA$22,U22*$Y$8*$AA$22))) -> 1872.45
...

Sheet Copy of Supplier 2 Inputs
F3: Total Days Elapsed From Order to Retail | K3: =F6+K5+F13 -> 154 | L3: =F6+L5+F13 -> 149 | M3: =F6+M5+F13 -> 144
U4: Stock Turn Days | W4: Shipment % | AO4: Yes | AP4: =K6 -> Sea | AQ4: =W5 -> SkyRockets
H5: Refrigerated Surcharge | J5: Container Size | K5: 25 | L5: 20 | M5: 15 | N5: Total Shipping Days | W5: SkyRockets | X5: Steady Eddy | Y5: Slow Burn | AO5: No | AP5: =L6 -> Air | AQ5: =X5 -> Steady Eddy
D6: Manufacture Days | F6: 120 | K6: Sea | L6: Air | M6: Express | AP6: =M6 -> Express | AQ6: =Y5 -> Slow Burn
D7: Order Deposit % | F7: 0.6 | H7: 2500 | J7: 10 ft | K7: 3500 | L7: 5000 | M7: 6500 | U7: 30 | W7: 0.4 | X7: 0.2 | Y7: 0.1
D8: Interest Cover % | F8: 0.06 | H8: 4000 | J8: 20 ft | K8: 8000 | L8: 10000 | M8: 11500 | U8: 60 | W8: 0.25 | X8: 0.3 | Y8: 0.3
D9: Currency Movement % | F9: 0.1 | H9: 6000 | J9: 40 ft | K9: 12000 | L9: 14000 | M9: 15500 | U9: 90 | W9: 0.2 | X9: 0.2 | Y9: 0.4
D10: Order Balance Due Days | F10: 91 | U10: 120 | W10: 0.15 | X10: 0.3 | Y10: 0.2
H12: Deposit Pmts | J12: =J54 -> 64585.8 | K12: =K54 -> 23379.6 | L12: =L54 -> 56586.6 | M12: =M54 -> 33959.4 | N12: =N54 -> 47503.8 | O12: =O54 -> 60406.2 | P12: =P54 -> 17821.8 | Q12: =Q54 -> 17206.2 | ... U12: =U54 -> 8024.4 | W12: =100%-sum(W7:W10) -> 0 | X12: =100%-sum(X7:X10) -> 0 | Y12: =100%-sum(Y7:Y10) -> 0
D13: Pre-Retail Prep Days | F13: 9 | H13: Balance Pmts | J13: =J75 -> 0 | K13: =K75 -> 0 | L13: =L75 -> 0 | M13: =M75 -> 44798.625 | N13: =N75 -> 16216.783 | O13: =O75 -> 39250.142 | P13: =P75 -> 23555.246 | Q13: =Q75 -> 32950.043 | ... U13: =U75 -> 32683.273 | W13: Up to | X13: Up to | Y13: Up to | AA13: =U4 -> Stock Turn Days
H15: Total Import Pmts | J15: =sum(J12:J13) -> 64585.8 | K15: =sum(K12:K13) -> 23379.6 | L15: =sum(L12:L13) -> 56586.6 | M15: =sum(M12:M13) -> 78758.025 | N15: =sum(N12:N13) -> 63720.583 | O15: =sum(O12:O13) -> 99656.342 | P15: =sum(P12:P13) -> 41377.046 | Q15: =sum(Q12:Q13) -> 50156.243 | ... U15: =sum(U12:U13) -> 40707.673 | W15: =U8 -> 60 | X15: =U9 -> 90 | Y15: =U10 -> 120
H17: Projected Sales
D19: Stock Items | F19: Unit Cost | H19: Item Popularity | J19: ='Supplier 1 Inputs'!J19 -> Jan | K19: ='Supplier 1 Inputs'!K19 -> Feb | L19: ='Supplier 1 Inputs'!L19 -> Mar | M19: ='Supplier 1 Inputs'!M19 -> Apr | N19: ='Supplier 1 Inputs'!N19 -> May | O19: ='Supplier 1 Inputs'!O19 -> Jun | P19: ='Supplier 1 Inputs'!P19 -> Jul | Q19: ='Supplier 1 Inputs'!Q19 -> Aug | ... U19: ='Supplier 1 Inputs'!U19 -> Dec | W19: New Stock Retail Markup % | X19: Std Retail Markup % | Y19: Runout Stock Markup % | AA19: New Stock Retail Price | AB19: Std Retail Price | AC19: Runout Stock Price
D21: Stock 1 | F21: 145 | H21: SkyRockets | J21: 34 | K21: 12 | L21: 35 | M21: 24 | N21: 12 | O21: 46 | P21: 14 | Q21: 12 | R21: 36 | S21: 4 | T21: 2 | U21: 16 | W21: 1.85 | X21: 1.52 | Y21: 1.22 | AA21: =(F21*W21)+F21 -> 413.25 | AB21: =(F21*X21)+F21 -> 365.4 | AC21: =(F21*Y21)+F21 -> 321.9
D22: Stock 2 | F22: 146 | H22: Steady Eddy | J22: 33 | K22: 14 | L22: 35 | M22: 23 | N22: 14 | O22: 45 | P22: 13 | R22: 25 | S22: 3 | U22: 15 | W22: 1.85 | X22: 1.52 | Y22: 1.22 | AA22: =(F22*W22)+F22 -> 416.1 | AB22: =(F22*X22)+F22 -> 367.92 | AC22: =(F22*Y22)+F22 -> 324.12
D23: Stock 3 | F23: 147 | H23: Slow Burn | J23: 35 | L23: 34 | N23: 16 | O23: 44 | P23: 15 | S23: 5 | W23: 1.85 | X23: 1.52 | Y23: 1.22 | AA23: =(F23*W23)+F23 -> 418.95 | AB23: =(F23*X23)+F23 -> 370.44 | AC23: =(F23*Y23)+F23 -> 326.34
D24: Stock 4 | F24: 148 | H24: Steady Eddy | J24: 38 | L24: 39 | N24: 18 | O24: 49 | S24: 8 | T24: 18 | W24: 1.85 | X24: 1.52 | Y24: 1.22 | AA24: =(F24*W24)+F24 -> 421.8 | AB24: =(F24*X24)+F24 -> 372.96 | AC24: =(F24*Y24)+F24 -> 328.56
D25: Stock 5 | F25: 149 | H25: SkyRockets | J25: 36 | L25: 38 | M25: 26 | N25: 11 | O25: 48 | Q25: 11 | R25: 28 | S25: 6 | T25: 17 | W25: 1.85 | X25: 1.52 | Y25: 1.22 | AA25: =(F25*W25)+F25 -> 424.65 | AB25: =(F25*X25)+F25 -> 375.48 | AC25: =(F25*Y25)+F25 -> 330.78
D26: Stock 6 | F26: 150 | H26: Slow Burn | J26: 35 | K26: 13 | M26: 25 | O26: 47 | Q26: 13 | R26: 37 | T26: 13 | U26: 17 | W26: 1.85 | X26: 1.52 | Y26: 1.22 | AA26: =(F26*W26)+F26 -> 427.5 | AB26: =(F26*X26)+F26 -> 378 | AC26: =(F26*Y26)+F26 -> 333
D27: Stock 7 | F27: 151 | H27: SkyRockets | J27: 34 | K27: 15 | M27: 24 | Q27: 15 | R27: 33 | T27: 15 | U27: 3 | W27: 1.85 | X27: 1.52 | Y27: 1.22 | AA27: =(F27*W27)+F27 -> 430.35 | AB27: =(F27*X27)+F27 -> 380.52 | AC27: =(F27*Y27)+F27 -> 335.22
D28: Stock 8 | F28: 152 | H28: SkyRockets | J28: 37 | K28: 17 | M28: 27 | N28: 37 | Q28: 17 | S28: 27 | T28: 17 | U28: 5 | W28: 1.85 | X28: 1.52 | Y28: 1.22 | AA28: =(F28*W28)+F28 -> 433.2 | AB28: =(F28*X28)+F28 -> 383.04 | AC28: =(F28*Y28)+F28 -> 337.44
D29: Stock 9 | F29: 153 | H29: Steady Eddy | J29: 34 | K29: 12 | L29: 37 | M29: 24 | N29: 32 | Q29: 12 | S29: 24 | T29: 12 | U29: 7 | W29: 1.85 | X29: 1.52 | Y29: 1.22 | AA29: =(F29*W29)+F29 -> 436.05 | AB29: =(F29*X29)+F29 -> 385.56 | AC29: =(F29*Y29)+F29 -> 339.66
D30: Stock 10 | F30: 154 | H30: Steady Eddy | J30: 33 | K30: 14 | L30: 31 | M30: 23 | N30: 34 | O30: 31 | Q30: 14 | R30: 41 | S30: 23 | U30: 1 | W30: 1.85 | X30: 1.52 | Y30: 1.22 | AA30: =(F30*W30)+F30 -> 438.9 | AB30: =(F30*X30)+F30 -> 388.08 | AC30: =(F30*Y30)+F30 -> 341.88
D31: Stock 11 | F31: 155 | H31: Steady Eddy | J31: 35 | K31: 16 | L31: 35 | N31: 36 | O31: 35 | P31: 15 | Q31: 16 | R31: 55 | S31: 25 | U31: 5 | W31: 1.85 | X31: 1.52 | Y31: 1.22 | AA31: =(F31*W31)+F31 -> 441.75 | AB31: =(F31*X31)+F31 -> 390.6 | AC31: =(F31*Y31)+F31 -> 344.1
D32: Stock 12 | F32: 156 | H32: Steady Eddy | J32: 38 | K32: 18 | L32: 39 | N32: 38 | O32: 39 | P32: 18 | Q32: 18 | R32: 69 | S32: 28 | T32: 18 | W32: 1.85 | X32: 1.52 | Y32: 1.22 | AA32: =(F32*W32)+F32 -> 444.6 | AB32: =(F32*X32)+F32 -> 393.12 | AC32: =(F32*Y32)+F32 -> 346.32
D33: Stock 13 | F33: 157 | H33: Steady Eddy | J33: 36 | K33: 13 | L33: 38 | N33: 33 | O33: 38 | P33: 16 | Q33: 13 | S33: 26 | T33: 13 | W33: 1.85 | X33: 1.52 | Y33: 1.22 | AA33: =(F33*W33)+F33 -> 447.45 | AB33: =(F33*X33)+F33 -> 395.64 | AC33: =(F33*Y33)+F33 -> 348.54
D34: Stock 14 | F34: 158 | H34: SkyRockets | J34: 35 | K34: 15 | L34: 35 | M34: 25 | P34: 15 | T34: 15 | W34: 1.85 | X34: 1.52 | Y34: 1.22 | AA34: =(F34*W34)+F34 -> 450.3 | AB34: =(F34*X34)+F34 -> 398.16 | AC34: =(F34*Y34)+F34 -> 350.76
D35: Stock 15 | F35: 159 | H35: SkyRockets | J35: 34 | K35: 17 | L35: 32 | M35: 24 | P35: 14 | R35: 42 | T35: 17 | W35: 1.85 | X35: 1.52 | Y35: 1.22 | AA35: =(F35*W35)+F35 -> 453.15 | AB35: =(F35*X35)+F35 -> 400.68 | AC35: =(F35*Y35)+F35 -> 352.98
D36: Stock 16 | F36: 160 | H36: SkyRockets | J36: 37 | K36: 19 | L36: 36 | M36: 27 | N36: 49 | O36: 46 | P36: 17 | R36: 36 | T36: 19 | W36: 1.85 | X36: 1.52 | Y36: 1.22 | AA36: =(F36*W36)+F36 -> 456 | AB36: =(F36*X36)+F36 -> 403.2 | AC36: =(F36*Y36)+F36 -> 355.2
D37: Stock 17 | F37: 161 | H37: Slow Burn | J37: 36 | K37: 11 | L37: 35 | M37: 26 | N37: 41 | O37: 45 | P37: 16 | R37: 25 | S37: 6 | T37: 11 | W37: 1.85 | X37: 1.52 | Y37: 1.22 | AA37: =(F37*W37)+F37 -> 458.85 | AB37: =(F37*X37)+F37 -> 405.72 | AC37: =(F37*Y37)+F37 -> 357.42
D38: Stock 18 | F38: 162 | H38: Slow Burn | J38: 32 | K38: 12 | L38: 34 | M38: 22 | N38: 42 | O38: 44 | P38: 12 | Q38: 12 | R38: 24 | S38: 2 | T38: 12 | U38: 4 | W38: 1.85 | X38: 1.52 | Y38: 1.22 | AA38: =(F38*W38)+F38 -> 461.7 | AB38: =(F38*X38)+F38 -> 408.24 | AC38: =(F38*Y38)+F38 -> 359.64
D39: Stock 19 | F39: 163 | H39: SkyRockets | J39: 31 | K39: 14 | L39: 37 | M39: 21 | N39: 44 | O39: 47 | P39: 11 | Q39: 14 | R39: 17 | S39: 1 | T39: 14 | U39: 7 | W39: 1.85 | X39: 1.52 | Y39: 1.22 | AA39: =(F39*W39)+F39 -> 464.55 | AB39: =(F39*X39)+F39 -> 410.76 | AC39: =(F39*Y39)+F39 -> 361.86
D40: Stock 20 | F40: 164 | H40: Steady Eddy | J40: 34 | K40: 18 | L40: 38 | M40: 24 | N40: 48 | O40: 48 | P40: 14 | Q40: 18 | R40: 38 | S40: 4 | T40: 18 | U40: 8 | W40: 1.85 | X40: 1.52 | Y40: 1.22 | AA40: =(F40*W40)+F40 -> 467.4 | AB40: =(F40*X40)+F40 -> 413.28 | AC40: =(F40*Y40)+F40 -> 364.08
H42: Refrigerated | J42: Yes | K42: No | L42: Yes | M42: Yes | N42: No | O42: No | P42: No | Q42: Yes | R42: No | S42: No | T42: Yes | U42: No
H43: Container Size | J43: 10 ft | K43: 20 ft | L43: 40 ft | M43: 20 ft | N43: 10 ft | O43: 20 ft | P43: 40 ft | Q43: 10 ft | R43: 10 ft | S43: 20 ft | T43: 40 ft | U43: 20 ft
H44: Shipping Speed | J44: Air | K44: Sea | L44: Express | M44: Express | N44: Sea | O44: Air | P44: Express | Q44: Sea | R44: Air | S44: Express | T44: Sea | U44: Express
H45: # of Containers | J45: 1 | K45: 1.5 | L45: 2 | M45: 1 | N45: 1.5 | O45: 2 | P45: 1 | Q45: 1.25 | R45: 1 | S45: 1 | T45: 1 | U45: 1
H47: Shipping Costs | J47: =J98 -> 0 | K47: =K98 -> 0 | L47: =L98 -> 0 | M47: =M98 -> 7500 | N47: =N98 -> 12000 | O47: =O98 -> 43000 | P47: =P98 -> 11500 | Q47: =Q98 -> 5250 | ... U47: =U98 -> 7500
D50: Stock/ Manufacture Pmts
F51: =sum(J51:U51) -> 4469 | H51: Total Units | J51: =sum(J21:J40) -> 697 | K51: =sum(K21:K40) -> 250 | L51: =sum(L21:L40) -> 608 | M51: =sum(M21:M40) -> 365 | N51: =sum(N21:N40) -> 505 | O51: =sum(O21:O40) -> 652 | P51: =sum(P21:P40) -> 190 | Q51: =sum(Q21:Q40) -> 185 | ... U51: =sum(U21:U40) -> 88
F52: =sum(J52:U52) -> 693271 | H52: Total Unit Cost | J52: =J21*$F$21+J22*$F$22+J23*$F$23+J24*$F$24+J25*$F$25+J26*$F$26+J27*$F$27+J28*$F$28+J29*$F$29+J30*$F$30+J31*$F$31+J32*$F$32+J33*$F$33+J34*$F$34+J35*$F$35+J36*$F$36+J37*$F$37+J38*$F$38+J39*$F$39+J40*$F$40 -> 107643 | K52: =K21*$F$21+K22*$F$22+K23*$F$23+K24*$F$24+K25*$F$25+K26*$F$26+K27*$F$27+K28*$F$28+K29*$F$29+K30*$F$30+K31*$F$31+K32*$F$32+K33*$F$33+K34*$F$34+K35*$F$35+K36*$F$36+K37*$F$37+K38*$F$38+K39*$F$39+K40*$F$40 -> 38966 | L52: =L21*$F$21+L22*$F$22+L23*$F$23+L24*$F$24+L25*$F$25+L26*$F$26+L27*$F$27+L28*$F$28+L29*$F$29+L30*$F$30+L31*$F$31+L32*$F$32+L33*$F$33+L34*$F$34+L35*$F$35+L36*$F$36+L37*$F$37+L38*$F$38+L39*$F$39+L40*$F$40 -> 94311 | M52: =M21*$F$21+M22*$F$22+M23*$F$23+M24*$F$24+M25*$F$25+M26*$F$26+M27*$F$27+M28*$F$28+M29*$F$29+M30*$F$30+M31*$F$31+M32*$F$32+M33*$F$33+M34*$F$34+M35*$F$35+M36*$F$36+M37*$F$37+M38*$F$38+M39*$F$39+M40*$F$40 -> 56599 | N52: =N21*$F$21+N22*$F$22+N23*$F$23+N24*$F$24+N25*$F$25+N26*$F$26+N27*$F$27+N28*$F$28+N29*$F$29+N30*$F$30+N31*$F$31+N32*$F$32+N33*$F$33+N34*$F$34+N35*$F$35+N36*$F$36+N37*$F$37+N38*$F$38+N39*$F$39+N40*$F$40 -> 79173 | O52: =O21*$F$21+O22*$F$22+O23*$F$23+O24*$F$24+O25*$F$25+O26*$F$26+O27*$F$27+O28*$F$28+O29*$F$29+O30*$F$30+O31*$F$31+O32*$F$32+O33*$F$33+O34*$F$34+O35*$F$35+O36*$F$36+O37*$F$37+O38*$F$38+O39*$F$39+O40*$F$40 -> 100677 | P52: =P21*$F$21+P22*$F$22+P23*$F$23+P24*$F$24+P25*$F$25+P26*$F$26+P27*$F$27+P28*$F$28+P29*$F$29+P30*$F$30+P31*$F$31+P32*$F$32+P33*$F$33+P34*$F$34+P35*$F$35+P36*$F$36+P37*$F$37+P38*$F$38+P39*$F$39+P40*$F$40 -> 29703 | Q52: =Q21*$F$21+Q22*$F$22+Q23*$F$23+Q24*$F$24+Q25*$F$25+Q26*$F$26+Q27*$F$27+Q28*$F$28+Q29*$F$29+Q30*$F$30+Q31*$F$31+Q32*$F$32+Q33*$F$33+Q34*$F$34+Q35*$F$35+Q36*$F$36+Q37*$F$37+Q38*$F$38+Q39*$F$39+Q40*$F$40 -> 28677 | ... U52: =U21*$F$21+U22*$F$22+U23*$F$23+U24*$F$24+U25*$F$25+U26*$F$26+U27*$F$27+U28*$F$28+U29*$F$29+U30*$F$30+U31*$F$31+U32*$F$32+U33*$F$33+U34*$F$34+U35*$F$35+U36*$F$36+U37*$F$37+U38*$F$38+U39*$F$39+U40*$F$40 -> 13374
F54: =sum(J54:U54) -> 415962.6 | H54: Deposit | J54: =J52*$F$7 -> 64585.8 | K54: =K52*$F$7 -> 23379.6 | L54: =L52*$F$7 -> 56586.6 | M54: =M52*$F$7 -> 33959.4 | N54: =N52*$F$7 -> 47503.8 | O54: =O52*$F$7 -> 60406.2 | P54: =P52*$F$7 -> 17821.8 | Q54: =Q52*$F$7 -> 17206.2 | ... U54: =U52*$F$7 -> 8024.4
D56: =F54+F56 -> 671612.7 | F56: =sum(J75:U75) -> 255650.1 | H56: Balance Due | J56: =J52-J54 -> 43057.2 | K56: =K52-K54 -> 15586.4 | L56: =L52-L54 -> 37724.4 | M56: =M52-M54 -> 22639.6 | N56: =N52-N54 -> 31669.2 | O56: =O52-O54 -> 40270.8 | P56: =P52-P54 -> 11881.2 | Q56: =Q52-Q54 -> 11470.8 | ... U56: =U52-U54 -> 5349.6
H58: Balance Interest | J58: =J56*$F$8/12*$F$10/30 -> 653.0342 | K58: =K56*$F$8/12*$F$10/30 -> 236.39373 | L58: =L56*$F$8/12*$F$10/30 -> 572.1534 | M58: =M56*$F$8/12*$F$10/30 -> 343.36727 | N58: =N56*$F$8/12*$F$10/30 -> 480.3162 | O58: =O56*$F$8/12*$F$10/30 -> 610.7738 | P58: =P56*$F$8/12*$F$10/30 -> 180.1982 | Q58: =Q56*$F$8/12*$F$10/30 -> 173.9738 | ... U58: =U56*$F$8/12*$F$10/30 -> 81.1356
H59: FX Loss | J59: =J56*$F$9/12*$F$10/30 -> 1088.3903 | K59: =K56*$F$9/12*$F$10/30 -> 393.98956 | L59: =L56*$F$9/12*$F$10/30 -> 953.589 | M59: =M56*$F$9/12*$F$10/30 -> 572.27878 | N59: =N56*$F$9/12*$F$10/30 -> 800.527 | O59: =O56*$F$9/12*$F$10/30 -> 1017.9563 | P59: =P56*$F$9/12*$F$10/30 -> 300.33033 | Q59: =Q56*$F$9/12*$F$10/30 -> 289.95633 | ... U59: =U56*$F$9/12*$F$10/30 -> 135.226
H60: Interest Total | J60: =J58+J59 -> 1741.4245 | K60: =K58+K59 -> 630.38329 | L60: =L58+L59 -> 1525.7424 | M60: =M58+M59 -> 915.64604 | N60: =N58+N59 -> 1280.8432 | O60: =O58+O59 -> 1628.7301 | P60: =P58+P59 -> 480.52853 | Q60: =Q58+Q59 -> 463.93013 | ... U60: =U58+U59 -> 216.3616
G62: 1 | H62: 30 | J62: =if($F$10<=$H$62,J56+J60,0) -> 0 | K62: =if($F$10<=$H$62,K56+K60,0) -> 0 | L62: =if($F$10<=$H$62,L56+L60,0) -> 0 | M62: =if($F$10<=$H$62,M56+M60,0) -> 0 | N62: =if($F$10<=$H$62,N56+N60,0) -> 0 | O62: =if($F$10<=$H$62,O56+O60,0) -> 0 | P62: =if($F$10<=$H$62,P56+P60,0) -> 0 | Q62: =if($F$10<=$H$62,Q56+Q60,0) -> 0 | ... U62: =if($F$10<=$H$62,U56+U60,0) -> 0
G63: 2 | H63: 60 | K63: =if(and($F$10>$H$62,$F$10<=$H$63),J56+J60,0) -> 0 | L63: =if(and($F$10>$H$62,$F$10<=$H$63),K56+K60,0) -> 0 | M63: =if(and($F$10>$H$62,$F$10<=$H$63),L56+L60,0) -> 0 | N63: =if(and($F$10>$H$62,$F$10<=$H$63),M56+M60,0) -> 0 | O63: =if(and($F$10>$H$62,$F$10<=$H$63),N56+N60,0) -> 0 | P63: =if(and($F$10>$H$62,$F$10<=$H$63),O56+O60,0) -> 0 | Q63: =if(and($F$10>$H$62,$F$10<=$H$63),P56+P60,0) -> 0 | R63: =if(and($F$10>$H$62,$F$10<=$H$63),Q56+Q60,0) -> 0 | ... V63: =if(and($F$10>$H$62,$F$10<=$H$63),U56+U60,0) -> 0
G64: 3 | H64: 90 | L64: =if(and($F$10>$H$63,$F$10<=$H$64),J56+J60,0) -> 0 | M64: =if(and($F$10>$H$63,$F$10<=$H$64),K56+K60,0) -> 0 | N64: =if(and($F$10>$H$63,$F$10<=$H$64),L56+L60,0) -> 0 | O64: =if(and($F$10>$H$63,$F$10<=$H$64),M56+M60,0) -> 0 | P64: =if(and($F$10>$H$63,$F$10<=$H$64),N56+N60,0) -> 0 | Q64: =if(and($F$10>$H$63,$F$10<=$H$64),O56+O60,0) -> 0 | R64: =if(and($F$10>$H$63,$F$10<=$H$64),P56+P60,0) -> 0 | S64: =if(and($F$10>$H$63,$F$10<=$H$64),Q56+Q60,0) -> 0 | ... W64: =if(and($F$10>$H$63,$F$10<=$H$64),U56+U60,0) -> 0
G65: 4 | H65: 120 | M65: =if(and($F$10>$H$64,$F$10<=$H$65),J56+J60,0) -> 44798.625 | N65: =if(and($F$10>$H$64,$F$10<=$H$65),K56+K60,0) -> 16216.783 | O65: =if(and($F$10>$H$64,$F$10<=$H$65),L56+L60,0) -> 39250.142 | P65: =if(and($F$10>$H$64,$F$10<=$H$65),M56+M60,0) -> 23555.246 | Q65: =if(and($F$10>$H$64,$F$10<=$H$65),N56+N60,0) -> 32950.043 | R65: =if(and($F$10>$H$64,$F$10<=$H$65),O56+O60,0) -> 41899.53 | S65: =if(and($F$10>$H$64,$F$10<=$H$65),P56+P60,0) -> 12361.729 | T65: =if(and($F$10>$H$64,$F$10<=$H$65),Q56+Q60,0) -> 11934.73 | ... X65: =if(and($F$10>$H$64,$F$10<=$H$65),U56+U60,0) -> 5565.9616
G66: 5 | H66: 150 | N66: =if(and($F$10>$H$65,$F$10<=$H$66),J56+J60,0) -> 0 | O66: =if(and($F$10>$H$65,$F$10<=$H$66),K56+K60,0) -> 0 | P66: =if(and($F$10>$H$65,$F$10<=$H$66),L56+L60,0) -> 0 | Q66: =if(and($F$10>$H$65,$F$10<=$H$66),M56+M60,0) -> 0 | R66: =if(and($F$10>$H$65,$F$10<=$H$66),N56+N60,0) -> 0 | S66: =if(and($F$10>$H$65,$F$10<=$H$66),O56+O60,0) -> 0 | T66: =if(and($F$10>$H$65,$F$10<=$H$66),P56+P60,0) -> 0 | U66: =if(and($F$10>$H$65,$F$10<=$H$66),Q56+Q60,0) -> 0 | ... Y66: =if(and($F$10>$H$65,$F$10<=$H$66),U56+U60,0) -> 0
G67: 6 | H67: 180 | O67: =if(and($F$10>$H$66,$F$10<=$H$67),J56+J60,0) -> 0 | P67: =if(and($F$10>$H$66,$F$10<=$H$67),K56+K60,0) -> 0 | Q67: =if(and($F$10>$H$66,$F$10<=$H$67),L56+L60,0) -> 0 | R67: =if(and($F$10>$H$66,$F$10<=$H$67),M56+M60,0) -> 0 | S67: =if(and($F$10>$H$66,$F$10<=$H$67),N56+N60,0) -> 0 | T67: =if(and($F$10>$H$66,$F$10<=$H$67),O56+O60,0) -> 0 | U67: =if(and($F$10>$H$66,$F$10<=$H$67),P56+P60,0) -> 0 | V67: =if(and($F$10>$H$66,$F$10<=$H$67),Q56+Q60,0) -> 0 | ... Z67: =if(and($F$10>$H$66,$F$10<=$H$67),U56+U60,0) -> 0
G68: 7 | H68: 210 | P68: =if(and($F$10>$H$67,$F$10<=$H$68),J56+J60,0) -> 0 | Q68: =if(and($F$10>$H$67,$F$10<=$H$68),K56+K60,0) -> 0 | R68: =if(and($F$10>$H$67,$F$10<=$H$68),L56+L60,0) -> 0 | S68: =if(and($F$10>$H$67,$F$10<=$H$68),M56+M60,0) -> 0 | T68: =if(and($F$10>$H$67,$F$10<=$H$68),N56+N60,0) -> 0 | U68: =if(and($F$10>$H$67,$F$10<=$H$68),O56+O60,0) -> 0 | V68: =if(and($F$10>$H$67,$F$10<=$H$68),P56+P60,0) -> 0 | W68: =if(and($F$10>$H$67,$F$10<=$H$68),Q56+Q60,0) -> 0 | ... AA68: =if(and($F$10>$H$67,$F$10<=$H$68),U56+U60,0) -> 0
G69: 8 | H69: 240 | Q69: =if(and($F$10>$H$68,$F$10<=$H$69),J56+J60,0) -> 0 | R69: =if(and($F$10>$H$68,$F$10<=$H$69),K56+K60,0) -> 0 | S69: =if(and($F$10>$H$68,$F$10<=$H$69),L56+L60,0) -> 0 | T69: =if(and($F$10>$H$68,$F$10<=$H$69),M56+M60,0) -> 0 | U69: =if(and($F$10>$H$68,$F$10<=$H$69),N56+N60,0) -> 0 | V69: =if(and($F$10>$H$68,$F$10<=$H$69),O56+O60,0) -> 0 | W69: =if(and($F$10>$H$68,$F$10<=$H$69),P56+P60,0) -> 0 | X69: =if(and($F$10>$H$68,$F$10<=$H$69),Q56+Q60,0) -> 0 | ... AB69: =if(and($F$10>$H$68,$F$10<=$H$69),U56+U60,0) -> 0
G70: 9 | H70: 270 | R70: =if(and($F$10>$H$69,$F$10<=$H$70),J56+J60,0) -> 0 | S70: =if(and($F$10>$H$69,$F$10<=$H$70),K56+K60,0) -> 0 | T70: =if(and($F$10>$H$69,$F$10<=$H$70),L56+L60,0) -> 0 | U70: =if(and($F$10>$H$69,$F$10<=$H$70),M56+M60,0) -> 0 | V70: =if(and($F$10>$H$69,$F$10<=$H$70),N56+N60,0) -> 0 | W70: =if(and($F$10>$H$69,$F$10<=$H$70),O56+O60,0) -> 0 | X70: =if(and($F$10>$H$69,$F$10<=$H$70),P56+P60,0) -> 0 | Y70: =if(and($F$10>$H$69,$F$10<=$H$70),Q56+Q60,0) -> 0 | ... AC70: =if(and($F$10>$H$69,$F$10<=$H$70),U56+U60,0) -> 0
G71: 10 | H71: 300 | S71: =if(and($F$10>$H$70,$F$10<=$H$71),J56+J60,0) -> 0 | T71: =if(and($F$10>$H$70,$F$10<=$H$71),K56+K60,0) -> 0 | U71: =if(and($F$10>$H$70,$F$10<=$H$71),L56+L60,0) -> 0 | V71: =if(and($F$10>$H$70,$F$10<=$H$71),M56+M60,0) -> 0 | W71: =if(and($F$10>$H$70,$F$10<=$H$71),N56+N60,0) -> 0 | X71: =if(and($F$10>$H$70,$F$10<=$H$71),O56+O60,0) -> 0 | Y71: =if(and($F$10>$H$70,$F$10<=$H$71),P56+P60,0) -> 0 | Z71: =if(and($F$10>$H$70,$F$10<=$H$71),Q56+Q60,0) -> 0 | ... AD71: =if(and($F$10>$H$70,$F$10<=$H$71),U56+U60,0) -> 0
G72: 11 | H72: 330 | T72: =if(and($F$10>$H$71,$F$10<=$H$72),J56+J60,0) -> 0 | U72: =if(and($F$10>$H$71,$F$10<=$H$72),K56+K60,0) -> 0 | V72: =if(and($F$10>$H$71,$F$10<=$H$72),L56+L60,0) -> 0 | W72: =if(and($F$10>$H$71,$F$10<=$H$72),M56+M60,0) -> 0 | X72: =if(and($F$10>$H$71,$F$10<=$H$72),N56+N60,0) -> 0 | Y72: =if(and($F$10>$H$71,$F$10<=$H$72),O56+O60,0) -> 0 | Z72: =if(and($F$10>$H$71,$F$10<=$H$72),P56+P60,0) -> 0 | AA72: =if(and($F$10>$H$71,$F$10<=$H$72),Q56+Q60,0) -> 0 | ... AE72: =if(and($F$10>$H$71,$F$10<=$H$72),U56+U60,0) -> 0
G73: 12 | H73: 360 | U73: =if(and($F$10>$H$72,$F$10<=$H$73),J56+J60,0) -> 0 | V73: =if(and($F$10>$H$72,$F$10<=$H$73),K56+K60,0) -> 0 | W73: =if(and($F$10>$H$72,$F$10<=$H$73),L56+L60,0) -> 0 | X73: =if(and($F$10>$H$72,$F$10<=$H$73),M56+M60,0) -> 0 | Y73: =if(and($F$10>$H$72,$F$10<=$H$73),N56+N60,0) -> 0 | Z73: =if(and($F$10>$H$72,$F$10<=$H$73),O56+O60,0) -> 0 | AA73: =if(and($F$10>$H$72,$F$10<=$H$73),P56+P60,0) -> 0 | AB73: =if(and($F$10>$H$72,$F$10<=$H$73),Q56+Q60,0) -> 0 | ... AF73: =if(and($F$10>$H$72,$F$10<=$H$73),U56+U60,0) -> 0
H75: =H56 -> Balance Due | J75: =sum(J62:J73) -> 0 | K75: =sum(K62:K73) -> 0 | L75: =sum(L62:L73) -> 0 | M75: =sum(M62:M73) -> 44798.625 | N75: =sum(N62:N73) -> 16216.783 | O75: =sum(O62:O73) -> 39250.142 | P75: =sum(P62:P73) -> 23555.246 | Q75: =sum(Q62:Q73) -> 32950.043 | ... AF75: =sum(AF62:AF73) -> 0
D78: Shipping Speed Calculations | H78: =J7 -> 10 ft | J78: =if(J45=0,0,if(J44="Sea",$K$7,if(J44="Air",$L$7,$M$7)+if($J$42="yes",$H$7,0))) -> 7500 | K78: =if(K45=0,0,if(K44="Sea",$K$7,if(K44="Air",$L$7,$M$7)+if($J$42="yes",$H$7,0))) -> 3500 | L78: =if(L45=0,0,if(L44="Sea",$K$7,if(L44="Air",$L$7,$M$7)+if($J$42="yes",$H$7,0))) -> 9000 | M78: =if(M45=0,0,if(M44="Sea",$K$7,if(M44="Air",$L$7,$M$7)+if($J$42="yes",$H$7,0))) -> 9000 | N78: =if(N45=0,0,if(N44="Sea",$K$7,if(N44="Air",$L$7,$M$7)+if($J$42="yes",$H$7,0))) -> 3500 | O78: =if(O45=0,0,if(O44="Sea",$K$7,if(O44="Air",$L$7,$M$7)+if($J$42="yes",$H$7,0))) -> 7500 | P78: =if(P45=0,0,if(P44="Sea",$K$7,if(P44="Air",$L$7,$M$7)+if($J$42="yes",$H$7,0))) -> 9000 | Q78: =if(Q45=0,0,if(Q44="Sea",$K$7,if(Q44="Air",$L$7,$M$7)+if($J$42="yes",$H$7,0))) -> 3500 | ... U78: =if(U45=0,0,if(U44="Sea",$K$7,if(U44="Air",$L$7,$M$7)+if($J$42="yes",$H$7,0))) -> 9000
H79: =J8 -> 20 ft | J79: =if(J45=0,0,if(J44="Sea",$K$8,if(J44="Air",$L$8,$M$8)+if($J$42="yes",$H$8,0))) -> 14000 | K79: =if(K45=0,0,if(K44="Sea",$K$8,if(K44="Air",$L$8,$M$8))) -> 8000 | L79: =if(L45=0,0,if(L44="Sea",$K$8,if(L44="Air",$L$8,$M$8))) -> 11500 | M79: =if(M45=0,0,if(M44="Sea",$K$8,if(M44="Air",$L$8,$M$8))) -> 11500 | N79: =if(N45=0,0,if(N44="Sea",$K$8,if(N44="Air",$L$8,$M$8))) -> 8000 | O79: =if(O45=0,0,if(O44="Sea",$K$8,if(O44="Air",$L$8,$M$8))) -> 10000 | P79: =if(P45=0,0,if(P44="Sea",$K$8,if(P44="Air",$L$8,$M$8))) -> 11500 | Q79: =if(Q45=0,0,if(Q44="Sea",$K$8,if(Q44="Air",$L$8,$M$8))) -> 8000 | R79: =if(R45=0,0,if(R44="Sea",$K$8,if(R44="Air",$L$8,$M$8))) -> 10000 | ... U79: =if(U45=0,0,if(U44="Sea",$K$8,if(U44="Air",$L$8,$M$8))) -> 11500
H80: =J9 -> 40 ft | J80: =if(J45=0,0,if(J44="Sea",$K$9,if(J44="Air",$L$9,$M$9)+if($J$42="yes",$H$9,0))) -> 20000 | K80: =if(K45=0,0,if(K44="Sea",$K$9,if(K44="Air",$L$9,$M$9)+if($J$42="yes",$H$9,0))) -> 12000 | L80: =if(L45=0,0,if(L44="Sea",$K$9,if(L44="Air",$L$9,$M$9)+if($J$42="yes",$H$9,0))) -> 21500 | M80: =if(M45=0,0,if(M44="Sea",$K$9,if(M44="Air",$L$9,$M$9)+if($J$42="yes",$H$9,0))) -> 21500 | N80: =if(N45=0,0,if(N44="Sea",$K$9,if(N44="Air",$L$9,$M$9)+if($J$42="yes",$H$9,0))) -> 12000 | O80: =if(O45=0,0,if(O44="Sea",$K$9,if(O44="Air",$L$9,$M$9)+if($J$42="yes",$H$9,0))) -> 20000 | P80: =if(P45=0,0,if(P44="Sea",$K$9,if(P44="Air",$L$9,$M$9)+if($J$42="yes",$H$9,0))) -> 21500 | Q80: =if(Q45=0,0,if(Q44="Sea",$K$9,if(Q44="Air",$L$9,$M$9)+if($J$42="yes",$H$9,0))) -> 12000 | ... U80: =if(U45=0,0,if(U44="Sea",$K$9,if(U44="Air",$L$9,$M$9)+if($J$42="yes",$H$9,0))) -> 21500
D83: Shipping Payments | H83: Shipping Cost | J83: =if(J45=0,0,if(J43="10 ft",J78*J45,if(J43="20 ft",J79*J45,J80*J45))) -> 7500 | K83: =if(K45=0,0,if(K43="10 ft",K78*K45,if(K43="20 ft",K79*K45,K80*K45))) -> 12000 | L83: =if(L45=0,0,if(L43="10 ft",L78*L45,if(L43="20 ft",L79*L45,L80*L45))) -> 43000 | M83: =if(M45=0,0,if(M43="10 ft",M78*M45,if(M43="20 ft",M79*M45,M80*M45))) -> 11500 | N83: =if(N45=0,0,if(N43="10 ft",N78*N45,if(N43="20 ft",N79*N45,N80*N45))) -> 5250 | O83: =if(O45=0,0,if(O43="10 ft",O78*O45,if(O43="20 ft",O79*O45,O80*O45))) -> 20000 | P83: =if(P45=0,0,if(P43="10 ft",P78*P45,if(P43="20 ft",P79*P45,P80*P45))) -> 21500 | Q83: =if(Q45=0,0,if(Q43="10 ft",Q78*Q45,if(Q43="20 ft",Q79*Q45,Q80*Q45))) -> 4375 | ... U83: =if(U45=0,0,if(U43="10 ft",U78*U45,if(U43="20 ft",U79*U45,U80*U45))) -> 11500
G85: 1 | H85: 30 | J85: =if($F$6<=$H$85,J83,0) -> 0 | K85: =if($F$6<=$H$85,K83,0) -> 0 | L85: =if($F$6<=$H$85,L83,0) -> 0 | M85: =if($F$6<=$H$85,M83,0) -> 0 | N85: =if($F$6<=$H$85,N83,0) -> 0 | O85: =if($F$6<=$H$85,O83,0) -> 0 | P85: =if($F$6<=$H$85,P83,0) -> 0 | Q85: =if($F$6<=$H$85,Q83,0) -> 0 | ... U85: =if($F$6<=$H$85,U83,0) -> 0
G86: 2 | H86: 60 | K86: =if(and($F$6>$H$85,$F$6<=$H$86),J83,0) -> 0 | L86: =if(and($F$6>$H$85,$F$6<=$H$86),K83,0) -> 0 | M86: =if(and($F$6>$H$85,$F$6<=$H$86),L83,0) -> 0 | N86: =if(and($F$6>$H$85,$F$6<=$H$86),M83,0) -> 0 | O86: =if(and($F$6>$H$85,$F$6<=$H$86),N83,0) -> 0 | P86: =if(and($F$6>$H$85,$F$6<=$H$86),O83,0) -> 0 | Q86: =if(and($F$6>$H$85,$F$6<=$H$86),P83,0) -> 0 | R86: =if(and($F$6>$H$85,$F$6<=$H$86),Q83,0) -> 0 | ... V86: =if(and($F$6>$H$85,$F$6<=$H$86),U83,0) -> 0
G87: 3 | H87: 90 | L87: =if(and($F$6>$H$86,$F$6<=$H$87),J83,0) -> 0 | M87: =if(and($F$6>$H$86,$F$6<=$H$87),K83,0) -> 0 | N87: =if(and($F$6>$H$86,$F$6<=$H$87),L83,0) -> 0 | O87: =if(and($F$6>$H$86,$F$6<=$H$87),M83,0) -> 0 | P87: =if(and($F$6>$H$86,$F$6<=$H$87),N83,0) -> 0 | Q87: =if(and($F$6>$H$86,$F$6<=$H$87),O83,0) -> 0 | R87: =if(and($F$6>$H$86,$F$6<=$H$87),P83,0) -> 0 | S87: =if(and($F$6>$H$86,$F$6<=$H$87),Q83,0) -> 0 | ... W87: =if(and($F$6>$H$86,$F$6<=$H$87),U83,0) -> 0
G88: 4 | H88: 120 | M88: =if(and($F$6>$H$87,$F$6<=$H$88),J83,0) -> 7500 | N88: =if(and($F$6>$H$87,$F$6<=$H$88),K83,0) -> 12000 | O88: =if(and($F$6>$H$87,$F$6<=$H$88),L83,0) -> 43000 | P88: =if(and($F$6>$H$87,$F$6<=$H$88),M83,0) -> 11500 | Q88: =if(and($F$6>$H$87,$F$6<=$H$88),N83,0) -> 5250 | R88: =if(and($F$6>$H$87,$F$6<=$H$88),O83,0) -> 20000 | S88: =if(and($F$6>$H$87,$F$6<=$H$88),P83,0) -> 21500 | T88: =if(and($F$6>$H$87,$F$6<=$H$88),Q83,0) -> 4375 | ... X88: =if(and($F$6>$H$87,$F$6<=$H$88),U83,0) -> 11500
G89: 5 | H89: 150 | N89: =if(and($F$6>$H$88,$F$6<=$H$89),J83,0) -> 0 | O89: =if(and($F$6>$H$88,$F$6<=$H$89),K83,0) -> 0 | P89: =if(and($F$6>$H$88,$F$6<=$H$89),L83,0) -> 0 | Q89: =if(and($F$6>$H$88,$F$6<=$H$89),M83,0) -> 0 | R89: =if(and($F$6>$H$88,$F$6<=$H$89),N83,0) -> 0 | S89: =if(and($F$6>$H$88,$F$6<=$H$89),O83,0) -> 0 | T89: =if(and($F$6>$H$88,$F$6<=$H$89),P83,0) -> 0 | U89: =if(and($F$6>$H$88,$F$6<=$H$89),Q83,0) -> 0 | ... Y89: =if(and($F$6>$H$88,$F$6<=$H$89),U83,0) -> 0
G90: 6 | H90: 180 | O90: =if(and($F$6>$H$89,$F$6<=$H$90),J83,0) -> 0 | P90: =if(and($F$6>$H$89,$F$6<=$H$90),K83,0) -> 0 | Q90: =if(and($F$6>$H$89,$F$6<=$H$90),L83,0) -> 0 | R90: =if(and($F$6>$H$89,$F$6<=$H$90),M83,0) -> 0 | S90: =if(and($F$6>$H$89,$F$6<=$H$90),N83,0) -> 0 | T90: =if(and($F$6>$H$89,$F$6<=$H$90),O83,0) -> 0 | U90: =if(and($F$6>$H$89,$F$6<=$H$90),P83,0) -> 0 | V90: =if(and($F$6>$H$89,$F$6<=$H$90),Q83,0) -> 0 | ... Z90: =if(and($F$6>$H$89,$F$6<=$H$90),U83,0) -> 0
G91: 7 | H91: 210 | P91: =if(and($F$6>$H$90,$F$6<=$H$91),J83,0) -> 0 | Q91: =if(and($F$6>$H$90,$F$6<=$H$91),K83,0) -> 0 | R91: =if(and($F$6>$H$90,$F$6<=$H$91),L83,0) -> 0 | S91: =if(and($F$6>$H$90,$F$6<=$H$91),M83,0) -> 0 | T91: =if(and($F$6>$H$90,$F$6<=$H$91),N83,0) -> 0 | U91: =if(and($F$6>$H$90,$F$6<=$H$91),O83,0) -> 0 | V91: =if(and($F$6>$H$90,$F$6<=$H$91),P83,0) -> 0 | W91: =if(and($F$6>$H$90,$F$6<=$H$91),Q83,0) -> 0 | ... AA91: =if(and($F$6>$H$90,$F$6<=$H$91),U83,0) -> 0
G92: 8 | H92: 240 | Q92: =if(and($F$6>$H$91,$F$6<=$H$92),J83,0) -> 0 | R92: =if(and($F$6>$H$91,$F$6<=$H$92),K83,0) -> 0 | S92: =if(and($F$6>$H$91,$F$6<=$H$92),L83,0) -> 0 | T92: =if(and($F$6>$H$91,$F$6<=$H$92),M83,0) -> 0 | U92: =if(and($F$6>$H$91,$F$6<=$H$92),N83,0) -> 0 | V92: =if(and($F$6>$H$91,$F$6<=$H$92),O83,0) -> 0 | W92: =if(and($F$6>$H$91,$F$6<=$H$92),P83,0) -> 0 | X92: =if(and($F$6>$H$91,$F$6<=$H$92),Q83,0) -> 0 | ... AB92: =if(and($F$6>$H$91,$F$6<=$H$92),U83,0) -> 0
G93: 9 | H93: 270 | R93: =if(and($F$6>$H$92,$F$6<=$H$93),J83,0) -> 0 | S93: =if(and($F$6>$H$92,$F$6<=$H$93),K83,0) -> 0 | T93: =if(and($F$6>$H$92,$F$6<=$H$93),L83,0) -> 0 | U93: =if(and($F$6>$H$92,$F$6<=$H$93),M83,0) -> 0 | V93: =if(and($F$6>$H$92,$F$6<=$H$93),N83,0) -> 0 | W93: =if(and($F$6>$H$92,$F$6<=$H$93),O83,0) -> 0 | X93: =if(and($F$6>$H$92,$F$6<=$H$93),P83,0) -> 0 | Y93: =if(and($F$6>$H$92,$F$6<=$H$93),Q83,0) -> 0 | ... AC93: =if(and($F$6>$H$92,$F$6<=$H$93),U83,0) -> 0
G94: 10 | H94: 300 | S94: =if(and($F$6>$H$93,$F$6<=$H$94),J83,0) -> 0 | T94: =if(and($F$6>$H$93,$F$6<=$H$94),K83,0) -> 0 | U94: =if(and($F$6>$H$93,$F$6<=$H$94),L83,0) -> 0 | V94: =if(and($F$6>$H$93,$F$6<=$H$94),M83,0) -> 0 | W94: =if(and($F$6>$H$93,$F$6<=$H$94),N83,0) -> 0 | X94: =if(and($F$6>$H$93,$F$6<=$H$94),O83,0) -> 0 | Y94: =if(and($F$6>$H$93,$F$6<=$H$94),P83,0) -> 0 | Z94: =if(and($F$6>$H$93,$F$6<=$H$94),Q83,0) -> 0 | ... AD94: =if(and($F$6>$H$93,$F$6<=$H$94),U83,0) -> 0
G95: 11 | H95: 330 | T95: =if(and($F$6>$H$94,$F$6<=$H$95),J83,0) -> 0 | U95: =if(and($F$6>$H$94,$F$6<=$H$95),K83,0) -> 0 | V95: =if(and($F$6>$H$94,$F$6<=$H$95),L83,0) -> 0 | W95: =if(and($F$6>$H$94,$F$6<=$H$95),M83,0) -> 0 | X95: =if(and($F$6>$H$94,$F$6<=$H$95),N83,0) -> 0 | Y95: =if(and($F$6>$H$94,$F$6<=$H$95),O83,0) -> 0 | Z95: =if(and($F$6>$H$94,$F$6<=$H$95),P83,0) -> 0 | AA95: =if(and($F$6>$H$94,$F$6<=$H$95),Q83,0) -> 0 | ... AE95: =if(and($F$6>$H$94,$F$6<=$H$95),U83,0) -> 0
G96: 12 | H96: 360 | U96: =if(and($F$6>$H$95,$F$6<=$H$96),J83,0) -> 0 | V96: =if(and($F$6>$H$95,$F$6<=$H$96),K83,0) -> 0 | W96: =if(and($F$6>$H$95,$F$6<=$H$96),L83,0) -> 0 | X96: =if(and($F$6>$H$95,$F$6<=$H$96),M83,0) -> 0 | Y96: =if(and($F$6>$H$95,$F$6<=$H$96),N83,0) -> 0 | Z96: =if(and($F$6>$H$95,$F$6<=$H$96),O83,0) -> 0 | AA96: =if(and($F$6>$H$95,$F$6<=$H$96),P83,0) -> 0 | AB96: =if(and($F$6>$H$95,$F$6<=$H$96),Q83,0) -> 0 | ... AF96: =if(and($F$6>$H$95,$F$6<=$H$96),U83,0) -> 0
J98: =sum(J85:J96) -> 0 | K98: =sum(K85:K96) -> 0 | L98: =sum(L85:L96) -> 0 | M98: =sum(M85:M96) -> 7500 | N98: =sum(N85:N96) -> 12000 | O98: =sum(O85:O96) -> 43000 | P98: =sum(P85:P96) -> 11500 | Q98: =sum(Q85:Q96) -> 5250 | ... AF98: =sum(AF85:AF96) -> 0
D102: Calculations | F102: 30 day bands
D103: =D21 -> Stock 1 | H103: =H21 -> SkyRockets | J103: =if($H$103="",0,if($H$103="Sky Rockets",J21*$W$7*$AA$21,if($H$103="Steady Eddy",J21*$X$7*$AA$21,J21*$Y$7*$AA$21))) -> 1405.05 | K103: =if($H$103="",0,if($H$103="Sky Rockets",K21*$W$7*$AA$21,if($H$103="Steady Eddy",K21*$X$7*$AA$21,K21*$Y$7*$AA$21))) -> 495.9 | L103: =if($H$103="",0,if($H$103="Sky Rockets",L21*$W$7*$AA$21,if($H$103="Steady Eddy",L21*$X$7*$AA$21,L21*$Y$7*$AA$21))) -> 1446.375 | M103: =if($H$103="",0,if($H$103="Sky Rockets",M21*$W$7*$AA$21,if($H$103="Steady Eddy",M21*$X$7*$AA$21,M21*$Y$7*$AA$21))) -> 991.8 | N103: =if($H$103="",0,if($H$103="Sky Rockets",N21*$W$7*$AA$21,if($H$103="Steady Eddy",N21*$X$7*$AA$21,N21*$Y$7*$AA$21))) -> 495.9 | O103: =if($H$103="",0,if($H$103="Sky Rockets",O21*$W$7*$AA$21,if($H$103="Steady Eddy",O21*$X$7*$AA$21,O21*$Y$7*$AA$21))) -> 1900.95 | P103: =if($H$103="",0,if($H$103="Sky Rockets",P21*$W$7*$AA$21,if($H$103="Steady Eddy",P21*$X$7*$AA$21,P21*$Y$7*$AA$21))) -> 578.55 | Q103: =if($H$103="",0,if($H$103="Sky Rockets",Q21*$W$7*$AA$21,if($H$103="Steady Eddy",Q21*$X$7*$AA$21,Q21*$Y$7*$AA$21))) -> 495.9 | ... U103: =if($H$103="",0,if($H$103="Sky Rockets",U21*$W$7*$AA$21,if($H$103="Steady Eddy",U21*$X$7*$AA$21,U21*$Y$7*$AA$21))) -> 661.2
D104: =D22 -> Stock 2 | H104: =H22 -> Steady Eddy | J104: =if($H$104="",0,if($H$104="Sky Rockets",J22*$W$7*$AA$22,if($H$104="Steady Eddy",J22*$X$7*$AA$22,J22*$Y$7*$AA$22))) -> 2746.26 | K104: =if($H$104="",0,if($H$104="Sky Rockets",K22*$W$7*$AA$22,if($H$104="Steady Eddy",K22*$X$7*$AA$22,K22*$Y$7*$AA$22))) -> 1165.08 | L104: =if($H$104="",0,if($H$104="Sky Rockets",L22*$W$7*$AA$22,if($H$104="Steady Eddy",L22*$X$7*$AA$22,L22*$Y$7*$AA$22))) -> 2912.7 | M104: =if($H$104="",0,if($H$104="Sky Rockets",M22*$W$7*$AA$22,if($H$104="Steady Eddy",M22*$X$7*$AA$22,M22*$Y$7*$AA$22))) -> 1914.06 | N104: =if($H$104="",0,if($H$104="Sky Rockets",N22*$W$7*$AA$22,if($H$104="Steady Eddy",N22*$X$7*$AA$22,N22*$Y$7*$AA$22))) -> 1165.08 | O104: =if($H$104="",0,if($H$104="Sky Rockets",O22*$W$7*$AA$22,if($H$104="Steady Eddy",O22*$X$7*$AA$22,O22*$Y$7*$AA$22))) -> 3744.9 | P104: =if($H$104="",0,if($H$104="Sky Rockets",P22*$W$7*$AA$22,if($H$104="Steady Eddy",P22*$X$7*$AA$22,P22*$Y$7*$AA$22))) -> 1081.86 | Q104: =if($H$104="",0,if($H$104="Sky Rockets",Q22*$W$7*$AA$22,if($H$104="Steady Eddy",Q22*$X$7*$AA$22,Q22*$Y$7*$AA$22))) -> 0 | ... U104: =if($H$104="",0,if($H$104="Sky Rockets",U22*$W$7*$AA$22,if($H$104="Steady Eddy",U22*$X$7*$AA$22,U22*$Y$7*$AA$22))) -> 1248.3
D105: =D23 -> Stock 3 | H105: =H23 -> Slow Burn | J105: =if($H$105="",0,if($H$105="Sky Rockets",J23*$W$7*$AA$23,if($H$105="Steady Eddy",J23*$X$7*$AA$23,J23*$Y$7*$AA$23))) -> 1466.325 | K105: =if($H$105="",0,if($H$105="Sky Rockets",K23*$W$7*$AA$23,if($H$105="Steady Eddy",K23*$X$7*$AA$23,K23*$Y$7*$AA$23))) -> 0 | L105: =if($H$105="",0,if($H$105="Sky Rockets",L23*$W$7*$AA$23,if($H$105="Steady Eddy",L23*$X$7*$AA$23,L23*$Y$7*$AA$23))) -> 1424.43 | M105: =if($H$105="",0,if($H$105="Sky Rockets",M23*$W$7*$AA$23,if($H$105="Steady Eddy",M23*$X$7*$AA$23,M23*$Y$7*$AA$23))) -> 0 | N105: =if($H$105="",0,if($H$105="Sky Rockets",N23*$W$7*$AA$23,if($H$105="Steady Eddy",N23*$X$7*$AA$23,N23*$Y$7*$AA$23))) -> 670.32 | O105: =if($H$105="",0,if($H$105="Sky Rockets",O23*$W$7*$AA$23,if($H$105="Steady Eddy",O23*$X$7*$AA$23,O23*$Y$7*$AA$23))) -> 1843.38 | P105: =if($H$105="",0,if($H$105="Sky Rockets",P23*$W$7*$AA$23,if($H$105="Steady Eddy",P23*$X$7*$AA$23,P23*$Y$7*$AA$23))) -> 628.425 | Q105: =if($H$105="",0,if($H$105="Sky Rockets",Q23*$W$7*$AA$23,if($H$105="Steady Eddy",Q23*$X$7*$AA$23,Q23*$Y$7*$AA$23))) -> 0 | ... U105: =if($H$105="",0,if($H$105="Sky Rockets",U23*$W$7*$AA$23,if($H$105="Steady Eddy",U23*$X$7*$AA$23,U23*$Y$7*$AA$23))) -> 0
D106: =D24 -> Stock 4 | H106: =H24 -> Steady Eddy | J106: =if($H$106="",0,if($H$106="Sky Rockets",J24*$W$7*$AA$24,if($H$106="Steady Eddy",J24*$X$7*$AA$24,J24*$Y$7*$AA$24))) -> 3205.68 | K106: =if($H$106="",0,if($H$106="Sky Rockets",K24*$W$7*$AA$24,if($H$106="Steady Eddy",K24*$X$7*$AA$24,K24*$Y$7*$AA$24))) -> 0 | L106: =if($H$106="",0,if($H$106="Sky Rockets",L24*$W$7*$AA$24,if($H$106="Steady Eddy",L24*$X$7*$AA$24,L24*$Y$7*$AA$24))) -> 3290.04 | M106: =if($H$106="",0,if($H$106="Sky Rockets",M24*$W$7*$AA$24,if($H$106="Steady Eddy",M24*$X$7*$AA$24,M24*$Y$7*$AA$24))) -> 0 | N106: =if($H$106="",0,if($H$106="Sky Rockets",N24*$W$7*$AA$24,if($H$106="Steady Eddy",N24*$X$7*$AA$24,N24*$Y$7*$AA$24))) -> 1518.48 | O106: =if($H$106="",0,if($H$106="Sky Rockets",O24*$W$7*$AA$24,if($H$106="Steady Eddy",O24*$X$7*$AA$24,O24*$Y$7*$AA$24))) -> 4133.64 | P106: =if($H$106="",0,if($H$106="Sky Rockets",P24*$W$7*$AA$24,if($H$106="Steady Eddy",P24*$X$7*$AA$24,P24*$Y$7*$AA$24))) -> 0 | Q106: =if($H$106="",0,if($H$106="Sky Rockets",Q24*$W$7*$AA$24,if($H$106="Steady Eddy",Q24*$X$7*$AA$24,Q24*$Y$7*$AA$24))) -> 0 | ... U106: =if($H$106="",0,if($H$106="Sky Rockets",U24*$W$7*$AA$24,if($H$106="Steady Eddy",U24*$X$7*$AA$24,U24*$Y$7*$AA$24))) -> 0
D107: =D25 -> Stock 5 | H107: =H25 -> SkyRockets | J107: =if($H$107="",0,if($H$107="Sky Rockets",J25*$W$7*$AA$25,if($H$107="Steady Eddy",J25*$X$7*$AA$25,J25*$Y$7*$AA$25))) -> 1528.74 | K107: =if($H$107="",0,if($H$107="Sky Rockets",K25*$W$7*$AA$25,if($H$107="Steady Eddy",K25*$X$7*$AA$25,K25*$Y$7*$AA$25))) -> 0 | L107: =if($H$107="",0,if($H$107="Sky Rockets",L25*$W$7*$AA$25,if($H$107="Steady Eddy",L25*$X$7*$AA$25,L25*$Y$7*$AA$25))) -> 1613.67 | M107: =if($H$107="",0,if($H$107="Sky Rockets",M25*$W$7*$AA$25,if($H$107="Steady Eddy",M25*$X$7*$AA$25,M25*$Y$7*$AA$25))) -> 1104.09 | N107: =if($H$107="",0,if($H$107="Sky Rockets",N25*$W$7*$AA$25,if($H$107="Steady Eddy",N25*$X$7*$AA$25,N25*$Y$7*$AA$25))) -> 467.115 | O107: =if($H$107="",0,if($H$107="Sky Rockets",O25*$W$7*$AA$25,if($H$107="Steady Eddy",O25*$X$7*$AA$25,O25*$Y$7*$AA$25))) -> 2038.32 | P107: =if($H$107="",0,if($H$107="Sky Rockets",P25*$W$7*$AA$25,if($H$107="Steady Eddy",P25*$X$7*$AA$25,P25*$Y$7*$AA$25))) -> 0 | Q107: =if($H$107="",0,if($H$107="Sky Rockets",Q25*$W$7*$AA$25,if($H$107="Steady Eddy",Q25*$X$7*$AA$25,Q25*$Y$7*$AA$25))) -> 467.115 | ... U107: =if($H$107="",0,if($H$107="Sky Rockets",U25*$W$7*$AA$25,if($H$107="Steady Eddy",U25*$X$7*$AA$25,U25*$Y$7*$AA$25))) -> 0
D108: =D26 -> Stock 6 | H108: =H26 -> Slow Burn | J108: =if($H$108="",0,if($H$108="Sky Rockets",J26*$W$7*$AA$26,if($H$108="Steady Eddy",J26*$X$7*$AA$26,J26*$Y$7*$AA$26))) -> 1496.25 | K108: =if($H$108="",0,if($H$108="Sky Rockets",K26*$W$7*$AA$26,if($H$108="Steady Eddy",K26*$X$7*$AA$26,K26*$Y$7*$AA$26))) -> 555.75 | L108: =if($H$108="",0,if($H$108="Sky Rockets",L26*$W$7*$AA$26,if($H$108="Steady Eddy",L26*$X$7*$AA$26,L26*$Y$7*$AA$26))) -> 0 | M108: =if($H$108="",0,if($H$108="Sky Rockets",M26*$W$7*$AA$26,if($H$108="Steady Eddy",M26*$X$7*$AA$26,M26*$Y$7*$AA$26))) -> 1068.75 | N108: =if($H$108="",0,if($H$108="Sky Rockets",N26*$W$7*$AA$26,if($H$108="Steady Eddy",N26*$X$7*$AA$26,N26*$Y$7*$AA$26))) -> 0 | O108: =if($H$108="",0,if($H$108="Sky Rockets",O26*$W$7*$AA$26,if($H$108="Steady Eddy",O26*$X$7*$AA$26,O26*$Y$7*$AA$26))) -> 2009.25 | P108: =if($H$108="",0,if($H$108="Sky Rockets",P26*$W$7*$AA$26,if($H$108="Steady Eddy",P26*$X$7*$AA$26,P26*$Y$7*$AA$26))) -> 0 | Q108: =if($H$108="",0,if($H$108="Sky Rockets",Q26*$W$7*$AA$26,if($H$108="Steady Eddy",Q26*$X$7*$AA$26,Q26*$Y$7*$AA$26))) -> 555.75 | ... U108: =if($H$108="",0,if($H$108="Sky Rockets",U26*$W$7*$AA$26,if($H$108="Steady Eddy",U26*$X$7*$AA$26,U26*$Y$7*$AA$26))) -> 726.75
D109: =D27 -> Stock 7 | H109: =H27 -> SkyRockets | J109: =if($H$109="",0,if($H$109="Sky Rockets",J27*$W$7*$AA$27,if($H$109="Steady Eddy",J27*$X$7*$AA$27,J27*$Y$7*$AA$27))) -> 1463.19 | K109: =if($H$109="",0,if($H$109="Sky Rockets",K27*$W$7*$AA$27,if($H$109="Steady Eddy",K27*$X$7*$AA$27,K27*$Y$7*$AA$27))) -> 645.525 | L109: =if($H$109="",0,if($H$109="Sky Rockets",L27*$W$7*$AA$27,if($H$109="Steady Eddy",L27*$X$7*$AA$27,L27*$Y$7*$AA$27))) -> 0 | M109: =if($H$109="",0,if($H$109="Sky Rockets",M27*$W$7*$AA$27,if($H$109="Steady Eddy",M27*$X$7*$AA$27,M27*$Y$7*$AA$27))) -> 1032.84 | N109: =if($H$109="",0,if($H$109="Sky Rockets",N27*$W$7*$AA$27,if($H$109="Steady Eddy",N27*$X$7*$AA$27,N27*$Y$7*$AA$27))) -> 0 | O109: =if($H$109="",0,if($H$109="Sky Rockets",O27*$W$7*$AA$27,if($H$109="Steady Eddy",O27*$X$7*$AA$27,O27*$Y$7*$AA$27))) -> 0 | P109: =if($H$109="",0,if($H$109="Sky Rockets",P27*$W$7*$AA$27,if($H$109="Steady Eddy",P27*$X$7*$AA$27,P27*$Y$7*$AA$27))) -> 0 | Q109: =if($H$109="",0,if($H$109="Sky Rockets",Q27*$W$7*$AA$27,if($H$109="Steady Eddy",Q27*$X$7*$AA$27,Q27*$Y$7*$AA$27))) -> 645.525 | ... U109: =if($H$109="",0,if($H$109="Sky Rockets",U27*$W$7*$AA$27,if($H$109="Steady Eddy",U27*$X$7*$AA$27,U27*$Y$7*$AA$27))) -> 129.105
D110: =D28 -> Stock 8 | H110: =H28 -> SkyRockets | J110: =if($H$110="",0,if($H$110="Sky Rockets",J28*$W$7*$AA$28,if($H$110="Steady Eddy",J28*$X$7*$AA$28,J28*$Y$7*$AA$28))) -> 1602.84 | K110: =if($H$110="",0,if($H$110="Sky Rockets",K28*$W$7*$AA$28,if($H$110="Steady Eddy",K28*$X$7*$AA$28,K28*$Y$7*$AA$28))) -> 736.44 | L110: =if($H$110="",0,if($H$110="Sky Rockets",L28*$W$7*$AA$28,if($H$110="Steady Eddy",L28*$X$7*$AA$28,L28*$Y$7*$AA$28))) -> 0 | M110: =if($H$110="",0,if($H$110="Sky Rockets",M28*$W$7*$AA$28,if($H$110="Steady Eddy",M28*$X$7*$AA$28,M28*$Y$7*$AA$28))) -> 1169.64 | N110: =if($H$110="",0,if($H$110="Sky Rockets",N28*$W$7*$AA$28,if($H$110="Steady Eddy",N28*$X$7*$AA$28,N28*$Y$7*$AA$28))) -> 1602.84 | O110: =if($H$110="",0,if($H$110="Sky Rockets",O28*$W$7*$AA$28,if($H$110="Steady Eddy",O28*$X$7*$AA$28,O28*$Y$7*$AA$28))) -> 0 | P110: =if($H$110="",0,if($H$110="Sky Rockets",P28*$W$7*$AA$28,if($H$110="Steady Eddy",P28*$X$7*$AA$28,P28*$Y$7*$AA$28))) -> 0 | Q110: =if($H$110="",0,if($H$110="Sky Rockets",Q28*$W$7*$AA$28,if($H$110="Steady Eddy",Q28*$X$7*$AA$28,Q28*$Y$7*$AA$28))) -> 736.44 | ... U110: =if($H$110="",0,if($H$110="Sky Rockets",U28*$W$7*$AA$28,if($H$110="Steady Eddy",U28*$X$7*$AA$28,U28*$Y$7*$AA$28))) -> 216.6
D111: =D29 -> Stock 9 | H111: =H29 -> Steady Eddy | J111: =if($H$111="",0,if($H$111="Sky Rockets",J29*$W$7*$AA$29,if($H$111="Steady Eddy",J29*$X$7*$AA$29,J29*$Y$7*$AA$29))) -> 2965.14 | K111: =if($H$111="",0,if($H$111="Sky Rockets",K29*$W$7*$AA$29,if($H$111="Steady Eddy",K29*$X$7*$AA$29,K29*$Y$7*$AA$29))) -> 1046.52 | L111: =if($H$111="",0,if($H$111="Sky Rockets",L29*$W$7*$AA$29,if($H$111="Steady Eddy",L29*$X$7*$AA$29,L29*$Y$7*$AA$29))) -> 3226.77 | M111: =if($H$111="",0,if($H$111="Sky Rockets",M29*$W$7*$AA$29,if($H$111="Steady Eddy",M29*$X$7*$AA$29,M29*$Y$7*$AA$29))) -> 2093.04 | N111: =if($H$111="",0,if($H$111="Sky Rockets",N29*$W$7*$AA$29,if($H$111="Steady Eddy",N29*$X$7*$AA$29,N29*$Y$7*$AA$29))) -> 2790.72 | O111: =if($H$111="",0,if($H$111="Sky Rockets",O29*$W$7*$AA$29,if($H$111="Steady Eddy",O29*$X$7*$AA$29,O29*$Y$7*$AA$29))) -> 0 | P111: =if($H$111="",0,if($H$111="Sky Rockets",P29*$W$7*$AA$29,if($H$111="Steady Eddy",P29*$X$7*$AA$29,P29*$Y$7*$AA$29))) -> 0 | Q111: =if($H$111="",0,if($H$111="Sky Rockets",Q29*$W$7*$AA$29,if($H$111="Steady Eddy",Q29*$X$7*$AA$29,Q29*$Y$7*$AA$29))) -> 1046.52 | ... U111: =if($H$111="",0,if($H$111="Sky Rockets",U29*$W$7*$AA$29,if($H$111="Steady Eddy",U29*$X$7*$AA$29,U29*$Y$7*$AA$29))) -> 610.47
D112: =D30 -> Stock 10 | H112: =H30 -> Steady Eddy | J112: =if($H$112="",0,if($H$112="Sky Rockets",J30*$W$7*$AA$30,if($H$112="Steady Eddy",J30*$X$7*$AA$30,J30*$Y$7*$AA$30))) -> 2896.74 | K112: =if($H$112="",0,if($H$112="Sky Rockets",K30*$W$7*$AA$30,if($H$112="Steady Eddy",K30*$X$7*$AA$30,K30*$Y$7*$AA$30))) -> 1228.92 | L112: =if($H$112="",0,if($H$112="Sky Rockets",L30*$W$7*$AA$30,if($H$112="Steady Eddy",L30*$X$7*$AA$30,L30*$Y$7*$AA$30))) -> 2721.18 | M112: =if($H$112="",0,if($H$112="Sky Rockets",M30*$W$7*$AA$30,if($H$112="Steady Eddy",M30*$X$7*$AA$30,M30*$Y$7*$AA$30))) -> 2018.94 | N112: =if($H$112="",0,if($H$112="Sky Rockets",N30*$W$7*$AA$30,if($H$112="Steady Eddy",N30*$X$7*$AA$30,N30*$Y$7*$AA$30))) -> 2984.52 | O112: =if($H$112="",0,if($H$112="Sky Rockets",O30*$W$7*$AA$30,if($H$112="Steady Eddy",O30*$X$7*$AA$30,O30*$Y$7*$AA$30))) -> 2721.18 | P112: =if($H$112="",0,if($H$112="Sky Rockets",P30*$W$7*$AA$30,if($H$112="Steady Eddy",P30*$X$7*$AA$30,P30*$Y$7*$AA$30))) -> 0 | Q112: =if($H$112="",0,if($H$112="Sky Rockets",Q30*$W$7*$AA$30,if($H$112="Steady Eddy",Q30*$X$7*$AA$30,Q30*$Y$7*$AA$30))) -> 1228.92 | ... U112: =if($H$112="",0,if($H$112="Sky Rockets",U30*$W$7*$AA$30,if($H$112="Steady Eddy",U30*$X$7*$AA$30,U30*$Y$7*$AA$30))) -> 87.78
D113: =D31 -> Stock 11 | H113: =H31 -> Steady Eddy | J113: =if($H$113="",0,if($H$113="Sky Rockets",J31*$W$7*$AA$31,if($H$113="Steady Eddy",J31*$X$7*$AA$31,J31*$Y$7*$AA$31))) -> 3092.25 | K113: =if($H$113="",0,if($H$113="Sky Rockets",K31*$W$7*$AA$31,if($H$113="Steady Eddy",K31*$X$7*$AA$31,K31*$Y$7*$AA$31))) -> 1413.6 | L113: =if($H$113="",0,if($H$113="Sky Rockets",L31*$W$7*$AA$31,if($H$113="Steady Eddy",L31*$X$7*$AA$31,L31*$Y$7*$AA$31))) -> 3092.25 | M113: =if($H$113="",0,if($H$113="Sky Rockets",M31*$W$7*$AA$31,if($H$113="Steady Eddy",M31*$X$7*$AA$31,M31*$Y$7*$AA$31))) -> 0 | N113: =if($H$113="",0,if($H$113="Sky Rockets",N31*$W$7*$AA$31,if($H$113="Steady Eddy",N31*$X$7*$AA$31,N31*$Y$7*$AA$31))) -> 3180.6 | O113: =if($H$113="",0,if($H$113="Sky Rockets",O31*$W$7*$AA$31,if($H$113="Steady Eddy",O31*$X$7*$AA$31,O31*$Y$7*$AA$31))) -> 3092.25 | P113: =if($H$113="",0,if($H$113="Sky Rockets",P31*$W$7*$AA$31,if($H$113="Steady Eddy",P31*$X$7*$AA$31,P31*$Y$7*$AA$31))) -> 1325.25 | Q113: =if($H$113="",0,if($H$113="Sky Rockets",Q31*$W$7*$AA$31,if($H$113="Steady Eddy",Q31*$X$7*$AA$31,Q31*$Y$7*$AA$31))) -> 1413.6 | ... U113: =if($H$113="",0,if($H$113="Sky Rockets",U31*$W$7*$AA$31,if($H$113="Steady Eddy",U31*$X$7*$AA$31,U31*$Y$7*$AA$31))) -> 441.75
D114: =D32 -> Stock 12 | H114: =H32 -> Steady Eddy | J114: =if($H$114="",0,if($H$114="Sky Rockets",J32*$W$7*$AA$32,if($H$114="Steady Eddy",J32*$X$7*$AA$32,J32*$Y$7*$AA$32))) -> 3378.96 | K114: =if($H$114="",0,if($H$114="Sky Rockets",K32*$W$7*$AA$32,if($H$114="Steady Eddy",K32*$X$7*$AA$32,K32*$Y$7*$AA$32))) -> 1600.56 | L114: =if($H$114="",0,if($H$114="Sky Rockets",L32*$W$7*$AA$32,if($H$114="Steady Eddy",L32*$X$7*$AA$32,L32*$Y$7*$AA$32))) -> 3467.88 | M114: =if($H$114="",0,if($H$114="Sky Rockets",M32*$W$7*$AA$32,if($H$114="Steady Eddy",M32*$X$7*$AA$32,M32*$Y$7*$AA$32))) -> 0 | N114: =if($H$114="",0,if($H$114="Sky Rockets",N32*$W$7*$AA$32,if($H$114="Steady Eddy",N32*$X$7*$AA$32,N32*$Y$7*$AA$32))) -> 3378.96 | O114: =if($H$114="",0,if($H$114="Sky Rockets",O32*$W$7*$AA$32,if($H$114="Steady Eddy",O32*$X$7*$AA$32,O32*$Y$7*$AA$32))) -> 3467.88 | P114: =if($H$114="",0,if($H$114="Sky Rockets",P32*$W$7*$AA$32,if($H$114="Steady Eddy",P32*$X$7*$AA$32,P32*$Y$7*$AA$32))) -> 1600.56 | Q114: =if($H$114="",0,if($H$114="Sky Rockets",Q32*$W$7*$AA$32,if($H$114="Steady Eddy",Q32*$X$7*$AA$32,Q32*$Y$7*$AA$32))) -> 1600.56 | ... U114: =if($H$114="",0,if($H$114="Sky Rockets",U32*$W$7*$AA$32,if($H$114="Steady Eddy",U32*$X$7*$AA$32,U32*$Y$7*$AA$32))) -> 0
D115: =D33 -> Stock 13 | H115: =H33 -> Steady Eddy | J115: =if($H$115="",0,if($H$115="Sky Rockets",J33*$W$7*$AA$33,if($H$115="Steady Eddy",J33*$X$7*$AA$33,J33*$Y$7*$AA$33))) -> 3221.64 | K115: =if($H$115="",0,if($H$115="Sky Rockets",K33*$W$7*$AA$33,if($H$115="Steady Eddy",K33*$X$7*$AA$33,K33*$Y$7*$AA$33))) -> 1163.37 | L115: =if($H$115="",0,if($H$115="Sky Rockets",L33*$W$7*$AA$33,if($H$115="Steady Eddy",L33*$X$7*$AA$33,L33*$Y$7*$AA$33))) -> 3400.62 | M115: =if($H$115="",0,if($H$115="Sky Rockets",M33*$W$7*$AA$33,if($H$115="Steady Eddy",M33*$X$7*$AA$33,M33*$Y$7*$AA$33))) -> 0 | N115: =if($H$115="",0,if($H$115="Sky Rockets",N33*$W$7*$AA$33,if($H$115="Steady Eddy",N33*$X$7*$AA$33,N33*$Y$7*$AA$33))) -> 2953.17 | O115: =if($H$115="",0,if($H$115="Sky Rockets",O33*$W$7*$AA$33,if($H$115="Steady Eddy",O33*$X$7*$AA$33,O33*$Y$7*$AA$33))) -> 3400.62 | P115: =if($H$115="",0,if($H$115="Sky Rockets",P33*$W$7*$AA$33,if($H$115="Steady Eddy",P33*$X$7*$AA$33,P33*$Y$7*$AA$33))) -> 1431.84 | Q115: =if($H$115="",0,if($H$115="Sky Rockets",Q33*$W$7*$AA$33,if($H$115="Steady Eddy",Q33*$X$7*$AA$33,Q33*$Y$7*$AA$33))) -> 1163.37 | ... U115: =if($H$115="",0,if($H$115="Sky Rockets",U33*$W$7*$AA$33,if($H$115="Steady Eddy",U33*$X$7*$AA$33,U33*$Y$7*$AA$33))) -> 0
D116: =D34 -> Stock 14 | H116: =H34 -> SkyRockets | J116: =if($H$116="",0,if($H$116="Sky Rockets",J34*$W$7*$AA$34,if($H$116="Steady Eddy",J34*$X$7*$AA$34,J34*$Y$7*$AA$34))) -> 1576.05 | K116: =if($H$116="",0,if($H$116="Sky Rockets",K34*$W$7*$AA$34,if($H$116="Steady Eddy",K34*$X$7*$AA$34,K34*$Y$7*$AA$34))) -> 675.45 | L116: =if($H$116="",0,if($H$116="Sky Rockets",L34*$W$7*$AA$34,if($H$116="Steady Eddy",L34*$X$7*$AA$34,L34*$Y$7*$AA$34))) -> 1576.05 | M116: =if($H$116="",0,if($H$116="Sky Rockets",M34*$W$7*$AA$34,if($H$116="Steady Eddy",M34*$X$7*$AA$34,M34*$Y$7*$AA$34))) -> 1125.75 | N116: =if($H$116="",0,if($H$116="Sky Rockets",N34*$W$7*$AA$34,if($H$116="Steady Eddy",N34*$X$7*$AA$34,N34*$Y$7*$AA$34))) -> 0 | O116: =if($H$116="",0,if($H$116="Sky Rockets",O34*$W$7*$AA$34,if($H$116="Steady Eddy",O34*$X$7*$AA$34,O34*$Y$7*$AA$34))) -> 0 | P116: =if($H$116="",0,if($H$116="Sky Rockets",P34*$W$7*$AA$34,if($H$116="Steady Eddy",P34*$X$7*$AA$34,P34*$Y$7*$AA$34))) -> 675.45 | Q116: =if($H$116="",0,if($H$116="Sky Rockets",Q34*$W$7*$AA$34,if($H$116="Steady Eddy",Q34*$X$7*$AA$34,Q34*$Y$7*$AA$34))) -> 0 | ... U116: =if($H$116="",0,if($H$116="Sky Rockets",U34*$W$7*$AA$34,if($H$116="Steady Eddy",U34*$X$7*$AA$34,U34*$Y$7*$AA$34))) -> 0
D117: =D35 -> Stock 15 | H117: =H35 -> SkyRockets | J117: =if($H$117="",0,if($H$117="Sky Rockets",J35*$W$7*$AA$35,if($H$117="Steady Eddy",J35*$X$7*$AA$35,J35*$Y$7*$AA$35))) -> 1540.71 | K117: =if($H$117="",0,if($H$117="Sky Rockets",K35*$W$7*$AA$35,if($H$117="Steady Eddy",K35*$X$7*$AA$35,K35*$Y$7*$AA$35))) -> 770.355 | L117: =if($H$117="",0,if($H$117="Sky Rockets",L35*$W$7*$AA$35,if($H$117="Steady Eddy",L35*$X$7*$AA$35,L35*$Y$7*$AA$35))) -> 1450.08 | M117: =if($H$117="",0,if($H$117="Sky Rockets",M35*$W$7*$AA$35,if($H$117="Steady Eddy",M35*$X$7*$AA$35,M35*$Y$7*$AA$35))) -> 1087.56 | N117: =if($H$117="",0,if($H$117="Sky Rockets",N35*$W$7*$AA$35,if($H$117="Steady Eddy",N35*$X$7*$AA$35,N35*$Y$7*$AA$35))) -> 0 | O117: =if($H$117="",0,if($H$117="Sky Rockets",O35*$W$7*$AA$35,if($H$117="Steady Eddy",O35*$X$7*$AA$35,O35*$Y$7*$AA$35))) -> 0 | P117: =if($H$117="",0,if($H$117="Sky Rockets",P35*$W$7*$AA$35,if($H$117="Steady Eddy",P35*$X$7*$AA$35,P35*$Y$7*$AA$35))) -> 634.41 | Q117: =if($H$117="",0,if($H$117="Sky Rockets",Q35*$W$7*$AA$35,if($H$117="Steady Eddy",Q35*$X$7*$AA$35,Q35*$Y$7*$AA$35))) -> 0 | ... U117: =if($H$117="",0,if($H$117="Sky Rockets",U35*$W$7*$AA$35,if($H$117="Steady Eddy",U35*$X$7*$AA$35,U35*$Y$7*$AA$35))) -> 0
D118: =D36 -> Stock 16 | H118: =H36 -> SkyRockets | J118: =if($H$118="",0,if($H$118="Sky Rockets",J36*$W$7*$AA$36,if($H$118="Steady Eddy",J36*$X$7*$AA$36,J36*$Y$7*$AA$36))) -> 1687.2 | K118: =if($H$118="",0,if($H$118="Sky Rockets",K36*$W$7*$AA$36,if($H$118="Steady Eddy",K36*$X$7*$AA$36,K36*$Y$7*$AA$36))) -> 866.4 | L118: =if($H$118="",0,if($H$118="Sky Rockets",L36*$W$7*$AA$36,if($H$118="Steady Eddy",L36*$X$7*$AA$36,L36*$Y$7*$AA$36))) -> 1641.6 | M118: =if($H$118="",0,if($H$118="Sky Rockets",M36*$W$7*$AA$36,if($H$118="Steady Eddy",M36*$X$7*$AA$36,M36*$Y$7*$AA$36))) -> 1231.2 | N118: =if($H$118="",0,if($H$118="Sky Rockets",N36*$W$7*$AA$36,if($H$118="Steady Eddy",N36*$X$7*$AA$36,N36*$Y$7*$AA$36))) -> 2234.4 | O118: =if($H$118="",0,if($H$118="Sky Rockets",O36*$W$7*$AA$36,if($H$118="Steady Eddy",O36*$X$7*$AA$36,O36*$Y$7*$AA$36))) -> 2097.6 | P118: =if($H$118="",0,if($H$118="Sky Rockets",P36*$W$7*$AA$36,if($H$118="Steady Eddy",P36*$X$7*$AA$36,P36*$Y$7*$AA$36))) -> 775.2 | Q118: =if($H$118="",0,if($H$118="Sky Rockets",Q36*$W$7*$AA$36,if($H$118="Steady Eddy",Q36*$X$7*$AA$36,Q36*$Y$7*$AA$36))) -> 0 | ... U118: =if($H$118="",0,if($H$118="Sky Rockets",U36*$W$7*$AA$36,if($H$118="Steady Eddy",U36*$X$7*$AA$36,U36*$Y$7*$AA$36))) -> 0
D119: =D37 -> Stock 17 | H119: =H37 -> Slow Burn | J119: =if($H$119="",0,if($H$119="Sky Rockets",J37*$W$7*$AA$37,if($H$119="Steady Eddy",J37*$X$7*$AA$37,J37*$Y$7*$AA$37))) -> 1651.86 | K119: =if($H$119="",0,if($H$119="Sky Rockets",K37*$W$7*$AA$37,if($H$119="Steady Eddy",K37*$X$7*$AA$37,K37*$Y$7*$AA$37))) -> 504.735 | L119: =if($H$119="",0,if($H$119="Sky Rockets",L37*$W$7*$AA$37,if($H$119="Steady Eddy",L37*$X$7*$AA$37,L37*$Y$7*$AA$37))) -> 1605.975 | M119: =if($H$119="",0,if($H$119="Sky Rockets",M37*$W$7*$AA$37,if($H$119="Steady Eddy",M37*$X$7*$AA$37,M37*$Y$7*$AA$37))) -> 1193.01 | N119: =if($H$119="",0,if($H$119="Sky Rockets",N37*$W$7*$AA$37,if($H$119="Steady Eddy",N37*$X$7*$AA$37,N37*$Y$7*$AA$37))) -> 1881.285 | O119: =if($H$119="",0,if($H$119="Sky Rockets",O37*$W$7*$AA$37,if($H$119="Steady Eddy",O37*$X$7*$AA$37,O37*$Y$7*$AA$37))) -> 2064.825 | P119: =if($H$119="",0,if($H$119="Sky Rockets",P37*$W$7*$AA$37,if($H$119="Steady Eddy",P37*$X$7*$AA$37,P37*$Y$7*$AA$37))) -> 734.16 | Q119: =if($H$119="",0,if($H$119="Sky Rockets",Q37*$W$7*$AA$37,if($H$119="Steady Eddy",Q37*$X$7*$AA$37,Q37*$Y$7*$AA$37))) -> 0 | ... U119: =if($H$119="",0,if($H$119="Sky Rockets",U37*$W$7*$AA$37,if($H$119="Steady Eddy",U37*$X$7*$AA$37,U37*$Y$7*$AA$37))) -> 0
D120: =D38 -> Stock 18 | H120: =H38 -> Slow Burn | J120: =if($H$120="",0,if($H$120="Sky Rockets",J38*$W$7*$AA$38,if($H$120="Steady Eddy",J38*$X$7*$AA$38,J38*$Y$7*$AA$38))) -> 1477.44 | K120: =if($H$120="",0,if($H$120="Sky Rockets",K38*$W$7*$AA$38,if($H$120="Steady Eddy",K38*$X$7*$AA$38,K38*$Y$7*$AA$38))) -> 554.04 | L120: =if($H$120="",0,if($H$120="Sky Rockets",L38*$W$7*$AA$38,if($H$120="Steady Eddy",L38*$X$7*$AA$38,L38*$Y$7*$AA$38))) -> 1569.78 | M120: =if($H$120="",0,if($H$120="Sky Rockets",M38*$W$7*$AA$38,if($H$120="Steady Eddy",M38*$X$7*$AA$38,M38*$Y$7*$AA$38))) -> 1015.74 | N120: =if($H$120="",0,if($H$120="Sky Rockets",N38*$W$7*$AA$38,if($H$120="Steady Eddy",N38*$X$7*$AA$38,N38*$Y$7*$AA$38))) -> 1939.14 | O120: =if($H$120="",0,if($H$120="Sky Rockets",O38*$W$7*$AA$38,if($H$120="Steady Eddy",O38*$X$7*$AA$38,O38*$Y$7*$AA$38))) -> 2031.48 | P120: =if($H$120="",0,if($H$120="Sky Rockets",P38*$W$7*$AA$38,if($H$120="Steady Eddy",P38*$X$7*$AA$38,P38*$Y$7*$AA$38))) -> 554.04 | Q120: =if($H$120="",0,if($H$120="Sky Rockets",Q38*$W$7*$AA$38,if($H$120="Steady Eddy",Q38*$X$7*$AA$38,Q38*$Y$7*$AA$38))) -> 554.04 | ... U120: =if($H$120="",0,if($H$120="Sky Rockets",U38*$W$7*$AA$38,if($H$120="Steady Eddy",U38*$X$7*$AA$38,U38*$Y$7*$AA$38))) -> 184.68
D121: =D39 -> Stock 19 | H121: =H39 -> SkyRockets | J121: =if($H$121="",0,if($H$121="Sky Rockets",J39*$W$7*$AA$39,if($H$121="Steady Eddy",J39*$X$7*$AA$39,J39*$Y$7*$AA$39))) -> 1440.105 | K121: =if($H$121="",0,if($H$121="Sky Rockets",K39*$W$7*$AA$39,if($H$121="Steady Eddy",K39*$X$7*$AA$39,K39*$Y$7*$AA$39))) -> 650.37 | L121: =if($H$121="",0,if($H$121="Sky Rockets",L39*$W$7*$AA$39,if($H$121="Steady Eddy",L39*$X$7*$AA$39,L39*$Y$7*$AA$39))) -> 1718.835 | M121: =if($H$121="",0,if($H$121="Sky Rockets",M39*$W$7*$AA$39,if($H$121="Steady Eddy",M39*$X$7*$AA$39,M39*$Y$7*$AA$39))) -> 975.555 | N121: =if($H$121="",0,if($H$121="Sky Rockets",N39*$W$7*$AA$39,if($H$121="Steady Eddy",N39*$X$7*$AA$39,N39*$Y$7*$AA$39))) -> 2044.02 | O121: =if($H$121="",0,if($H$121="Sky Rockets",O39*$W$7*$AA$39,if($H$121="Steady Eddy",O39*$X$7*$AA$39,O39*$Y$7*$AA$39))) -> 2183.385 | P121: =if($H$121="",0,if($H$121="Sky Rockets",P39*$W$7*$AA$39,if($H$121="Steady Eddy",P39*$X$7*$AA$39,P39*$Y$7*$AA$39))) -> 511.005 | Q121: =if($H$121="",0,if($H$121="Sky Rockets",Q39*$W$7*$AA$39,if($H$121="Steady Eddy",Q39*$X$7*$AA$39,Q39*$Y$7*$AA$39))) -> 650.37 | ... U121: =if($H$121="",0,if($H$121="Sky Rockets",U39*$W$7*$AA$39,if($H$121="Steady Eddy",U39*$X$7*$AA$39,U39*$Y$7*$AA$39))) -> 325.185
D122: =D40 -> Stock 20 | H122: =H40 -> Steady Eddy | J122: =if($H$122="",0,if($H$122="Sky Rockets",J40*$W$7*$AA$40,if($H$122="Steady Eddy",J40*$X$7*$AA$40,J40*$Y$7*$AA$40))) -> 3178.32 | K122: =if($H$122="",0,if($H$122="Sky Rockets",K40*$W$7*$AA$40,if($H$122="Steady Eddy",K40*$X$7*$AA$40,K40*$Y$7*$AA$40))) -> 1682.64 | L122: =if($H$122="",0,if($H$122="Sky Rockets",L40*$W$7*$AA$40,if($H$122="Steady Eddy",L40*$X$7*$AA$40,L40*$Y$7*$AA$40))) -> 3552.24 | M122: =if($H$122="",0,if($H$122="Sky Rockets",M40*$W$7*$AA$40,if($H$122="Steady Eddy",M40*$X$7*$AA$40,M40*$Y$7*$AA$40))) -> 2243.52 | N122: =if($H$122="",0,if($H$122="Sky Rockets",N40*$W$7*$AA$40,if($H$122="Steady Eddy",N40*$X$7*$AA$40,N40*$Y$7*$AA$40))) -> 4487.04 | O122: =if($H$122="",0,if($H$122="Sky Rockets",O40*$W$7*$AA$40,if($H$122="Steady Eddy",O40*$X$7*$AA$40,O40*$Y$7*$AA$40))) -> 4487.04 | P122: =if($H$122="",0,if($H$122="Sky Rockets",P40*$W$7*$AA$40,if($H$122="Steady Eddy",P40*$X$7*$AA$40,P40*$Y$7*$AA$40))) -> 1308.72 | Q122: =if($H$122="",0,if($H$122="Sky Rockets",Q40*$W$7*$AA$40,if($H$122="Steady Eddy",Q40*$X$7*$AA$40,Q40*$Y$7*$AA$40))) -> 1682.64 | ... U122: =if($H$122="",0,if($H$122="Sky Rockets",U40*$W$7*$AA$40,if($H$122="Steady Eddy",U40*$X$7*$AA$40,U40*$Y$7*$AA$40))) -> 747.84
D124: Calculations | F124: 60 day bands | H124: 30 | J124: =sum(J103:J122) -> 43020.75 | K124: =sum(K103:K122) -> 15755.655 | L124: =sum(L103:L122) -> 39710.475 | M124: =sum(M103:M122) -> 20265.495 | N124: =sum(N103:N122) -> 33793.59 | O124: =sum(O103:O122) -> 41216.7 | P124: =sum(P103:P122) -> 11839.47 | Q124: =sum(Q103:Q122) -> 12240.75 | ... U124: =sum(U103:U122) -> 5379.66
D126: =D103 -> Stock 1 | H126: =H103 -> SkyRockets | J126: =if($H$126="",0,if($H$126="Sky Rockets",J21*$W$8*$AA$21,if($H$126="Steady Eddy",J21*$X$8*$AA$21,J21*$Y$8*$AA$21))) -> 4215.15 | K126: =if($H$126="",0,if($H$126="Sky Rockets",K21*$W$8*$AA$21,if($H$126="Steady Eddy",K21*$X$8*$AA$21,K21*$Y$8*$AA$21))) -> 1487.7 | L126: =if($H$126="",0,if($H$126="Sky Rockets",L21*$W$8*$AA$21,if($H$126="Steady Eddy",L21*$X$8*$AA$21,L21*$Y$8*$AA$21))) -> 4339.125 | M126: =if($H$126="",0,if($H$126="Sky Rockets",M21*$W$8*$AA$21,if($H$126="Steady Eddy",M21*$X$8*$AA$21,M21*$Y$8*$AA$21))) -> 2975.4 | N126: =if($H$126="",0,if($H$126="Sky Rockets",N21*$W$8*$AA$21,if($H$126="Steady Eddy",N21*$X$8*$AA$21,N21*$Y$8*$AA$21))) -> 1487.7 | O126: =if($H$126="",0,if($H$126="Sky Rockets",O21*$W$8*$AA$21,if($H$126="Steady Eddy",O21*$X$8*$AA$21,O21*$Y$8*$AA$21))) -> 5702.85 | P126: =if($H$126="",0,if($H$126="Sky Rockets",P21*$W$8*$AA$21,if($H$126="Steady Eddy",P21*$X$8*$AA$21,P21*$Y$8*$AA$21))) -> 1735.65 | Q126: =if($H$126="",0,if($H$126="Sky Rockets",Q21*$W$8*$AA$21,if($H$126="Steady Eddy",Q21*$X$8*$AA$21,Q21*$Y$8*$AA$21))) -> 1487.7 | ... U126: =if($H$126="",0,if($H$126="Sky Rockets",U21*$W$8*$AA$21,if($H$126="Steady Eddy",U21*$X$8*$AA$21,U21*$Y$8*$AA$21))) -> 1983.6
D127: =D104 -> Stock 2 | H127: =H104 -> Steady Eddy | J127: =if($H$127="",0,if($H$127="Sky Rockets",J22*$W$8*$AA$22,if($H$127="Steady Eddy",J22*$X$8*$AA$22,J22*$Y$8*$AA$22))) -> 4119.39 | K127: =if($H$127="",0,if($H$127="Sky Rockets",K22*$W$8*$AA$22,if($H$127="Steady Eddy",K22*$X$8*$AA$22,K22*$Y$8*$AA$22))) -> 1747.62 | L127: =if($H$127="",0,if($H$127="Sky Rockets",L22*$W$8*$AA$22,if($H$127="Steady Eddy",L22*$X$8*$AA$22,L22*$Y$8*$AA$22))) -> 4369.05 | M127: =if($H$127="",0,if($H$127="Sky Rockets",M22*$W$8*$AA$22,if($H$127="Steady Eddy",M22*$X$8*$AA$22,M22*$Y$8*$AA$22))) -> 2871.09 | N127: =if($H$127="",0,if($H$127="Sky Rockets",N22*$W$8*$AA$22,if($H$127="Steady Eddy",N22*$X$8*$AA$22,N22*$Y$8*$AA$22))) -> 1747.62 | O127: =if($H$127="",0,if($H$127="Sky Rockets",O22*$W$8*$AA$22,if($H$127="Steady Eddy",O22*$X$8*$AA$22,O22*$Y$8*$AA$22))) -> 5617.35 | P127: =if($H$127="",0,if($H$127="Sky Rockets",P22*$W$8*$AA$22,if($H$127="Steady Eddy",P22*$X$8*$AA$22,P22*$Y$8*$AA$22))) -> 1622.79 | Q127: =if($H$127="",0,if($H$127="Sky Rockets",Q22*$W$8*$AA$22,if($H$127="Steady Eddy",Q22*$X$8*$AA$22,Q22*$Y$8*$AA$22))) -> 0 | ... U127: =if($H$127="",0,if($H$127="Sky Rockets",U22*$W$8*$AA$22,if($H$127="Steady Eddy",U22*$X$8*$AA$22,U22*$Y$8*$AA$22))) -> 1872.45
...

Sheet Index Tables
M2: ='Copy of Supplier 2 Inputs'!W5 -> SkyRockets | N2: ='Copy of Supplier 2 Inputs'!X5 -> Steady Eddy | O2: ='Copy of Supplier 2 Inputs'!Y5 -> Slow Burn
L3: ='Copy of Supplier 2 Inputs'!U7 -> 30 | M3: ='Copy of Supplier 2 Inputs'!W7 -> 0.4 | N3: ='Copy of Supplier 2 Inputs'!X7 -> 0.2 | O3: ='Copy of Supplier 2 Inputs'!Y7 -> 0.1 | P3: =100%-sum(M3:O3) -> 0.3
L4: ='Copy of Supplier 2 Inputs'!U8 -> 60 | M4: ='Copy of Supplier 2 Inputs'!W8 -> 0.25 | N4: ='Copy of Supplier 2 Inputs'!X8 -> 0.3 | O4: ='Copy of Supplier 2 Inputs'!Y8 -> 0.3 | P4: =100%-sum(M4:O4) -> 0.15
L5: ='Copy of Supplier 2 Inputs'!U9 -> 90 | M5: ='Copy of Supplier 2 Inputs'!W9 -> 0.2 | N5: ='Copy of Supplier 2 Inputs'!X9 -> 0.2 | O5: ='Copy of Supplier 2 Inputs'!Y9 -> 0.4 | P5: =100%-sum(M5:O5) -> 0.2
L6: ='Copy of Supplier 2 Inputs'!U10 -> 120 | M6: ='Copy of Supplier 2 Inputs'!W10 -> 0.15 | N6: ='Copy of Supplier 2 Inputs'!X10 -> 0.3 | O6: ='Copy of Supplier 2 Inputs'!Y10 -> 0.2 | P6: =100%-sum(M6:O6) -> 0.35
L7: 150 | M7: 0.2 | N7: 0.4 | O7: 0.4 | P7: =100%-sum(M7:O7) -> 0
L8: 180 | M8: 0.4 | N8: 0.3 | O8: 0.3 | P8: =100%-sum(M8:O8) -> 0
L9: 180+ | M9: 0.15 | N9: 0.55 | O9: 0.3 | P9: =100%-sum(M9:O9) -> 0
D13: 30 | E13: 60 | F13: 90 | G13: 120 | H13: 150 | I13: 180 | J13: 210 | K13: 240 | L13: 270 | M13: 300 | N13: 330 | O13: 360 | P13: 390

Sheet Financial Projections
D4: Seasonal Times | F4: Off Peak | G4: Peak | H4: Peak | I4: Normal | J4: Normal | K4: Off Peak | L4: Off Peak | M4: Normal | N4: Peak | O4: Normal | P4: Peak | Q4: Peak
D5: list at bottom
D6: Wage Costs | F6: 20000 | G6: 20000 | H6: 20000 | I6: 20000 | J6: 20000 | K6: 20000 | L6: 20000 | M6: 20000 | N6: 20000 | O6: 20000 | P6: 20000 | Q6: 20000
F8: ='Supplier 1 Inputs'!J279 -> Jan | G8: ='Supplier 1 Inputs'!K279 -> Feb | H8: ='Supplier 1 Inputs'!L279 -> Mar | I8: ='Supplier 1 Inputs'!M279 -> Apr | J8: ='Supplier 1 Inputs'!N279 -> May | K8: ='Supplier 1 Inputs'!O279 -> Jun | L8: ='Supplier 1 Inputs'!P279 -> Jul | M8: ='Supplier 1 Inputs'!Q279 -> Aug | ... AB8: ='Supplier 1 Inputs'!AF279 -> Nov
D10: ='Supplier 1 Inputs'!H12 -> Deposit Pmts | F10: ='Supplier 1 Inputs'!J12+'Supplier 2 Inputs'!J12 -> 129171.6 | G10: ='Supplier 1 Inputs'!K12+'Supplier 2 Inputs'!K12 -> 46759.2 | H10: ='Supplier 1 Inputs'!L12+'Supplier 2 Inputs'!L12 -> 113173.2 | I10: ='Supplier 1 Inputs'!M12+'Supplier 2 Inputs'!M12 -> 67918.8 | J10: ='Supplier 1 Inputs'!N12+'Supplier 2 Inputs'!N12 -> 95007.6 | K10: ='Supplier 1 Inputs'!O12+'Supplier 2 Inputs'!O12 -> 120812.4 | L10: ='Supplier 1 Inputs'!P12+'Supplier 2 Inputs'!P12 -> 35643.6 | M10: ='Supplier 1 Inputs'!Q12+'Supplier 2 Inputs'!Q12 -> 34412.4 | ... Q10: ='Supplier 1 Inputs'!U12+'Supplier 2 Inputs'!U12 -> 16048.8 | AD10: =sum(F10:AB10) -> 831925.2
D12: ='Supplier 1 Inputs'!H13 -> Balance Pmts | F12: ='Supplier 1 Inputs'!J75+'Supplier 2 Inputs'!J75 -> 0 | G12: ='Supplier 1 Inputs'!K75+'Supplier 2 Inputs'!K75 -> 0 | H12: ='Supplier 1 Inputs'!L75+'Supplier 2 Inputs'!L75 -> 0 | I12: ='Supplier 1 Inputs'!M75+'Supplier 2 Inputs'!M75 -> 89597.249 | J12: ='Supplier 1 Inputs'!N75+'Supplier 2 Inputs'!N75 -> 32433.567 | K12: ='Supplier 1 Inputs'!O75+'Supplier 2 Inputs'!O75 -> 78500.285 | L12: ='Supplier 1 Inputs'!P75+'Supplier 2 Inputs'!P75 -> 47110.492 | M12: ='Supplier 1 Inputs'!Q75+'Supplier 2 Inputs'!Q75 -> 65900.086 | ... AB12: ='Supplier 1 Inputs'!AF75+'Supplier 2 Inputs'!AF75 -> 0 | AD12: =sum(F12:AB12) -> 577047.97 | AO12: Stock Costs | AP12: =AD10+AD12 -> 1408973.2
AO13: Shipping Costs | AP13: =AD14 -> 335250
D14: ='Supplier 1 Inputs'!H47 -> Shipping Costs | F14: ='Supplier 1 Inputs'!J98+'Supplier 2 Inputs'!J98 -> 0 | G14: ='Supplier 1 Inputs'!K98+'Supplier 2 Inputs'!K98 -> 0 | H14: ='Supplier 1 Inputs'!L98+'Supplier 2 Inputs'!L98 -> 0 | I14: ='Supplier 1 Inputs'!M98+'Supplier 2 Inputs'!M98 -> 15000 | J14: ='Supplier 1 Inputs'!N98+'Supplier 2 Inputs'!N98 -> 24000 | K14: ='Supplier 1 Inputs'!O98+'Supplier 2 Inputs'!O98 -> 86000 | L14: ='Supplier 1 Inputs'!P98+'Supplier 2 Inputs'!P98 -> 23000 | M14: ='Supplier 1 Inputs'!Q98+'Supplier 2 Inputs'!Q98 -> 10500 | ... AB14: ='Supplier 1 Inputs'!AF98+'Supplier 2 Inputs'!AF98 -> 0 | AD14: =sum(F14:AB14) -> 335250
D16: Total Payments | F16: =sum(F10:F14) -> 129171.6 | G16: =sum(G10:G14) -> 46759.2 | H16: =sum(H10:H14) -> 113173.2 | I16: =sum(I10:I14) -> 172516.05 | J16: =sum(J10:J14) -> 151441.17 | K16: =sum(K10:K14) -> 285312.68 | L16: =sum(L10:L14) -> 105754.09 | M16: =sum(M10:M14) -> 110812.49 | ... AB16: =sum(AB10:AB14) -> 0 | AD16: =sum(F16:AB16) -> 1744223.2
AO17: Total Sales | AP17: =AD18 -> 3595739.2
D18: Projected Revenue | F18: ='Supplier 1 Inputs'!J281+'Supplier 2 Inputs'!J281 -> 0 | G18: ='Supplier 1 Inputs'!K281+'Supplier 2 Inputs'!K281 -> 0 | H18: ='Supplier 1 Inputs'!L281+'Supplier 2 Inputs'!L281 -> 0 | I18: ='Supplier 1 Inputs'!M281+'Supplier 2 Inputs'!M281 -> 0 | J18: ='Supplier 1 Inputs'!N281+'Supplier 2 Inputs'!N281 -> 86041.5 | K18: ='Supplier 1 Inputs'!O281+'Supplier 2 Inputs'!O281 -> 184069.53 | L18: ='Supplier 1 Inputs'!P281+'Supplier 2 Inputs'!P281 -> 284287.09 | M18: ='Supplier 1 Inputs'!Q281+'Supplier 2 Inputs'!Q281 -> 383249.95 | ... AB18: ='Supplier 1 Inputs'!AF281+'Supplier 2 Inputs'!AF281 -> 0 | AD18: =sum(F18:AB18) -> 3595739.2 | AO18: Total Costs | AP18: =AP12+AP13 -> 1744223.2 | AQ18: =AP18/AP17 -> 0.48508056
AP19: =AP17-AP18 -> 1851516
D20: Import Related Mth Cash Movement
F21: =F18-(F16+F6) -> -149171.6 | G21: =G18-(G16+G6) -> -66759.2 | H21: =H18-(H16+H6) -> -133173.2 | I21: =I18-(I16+I6) -> -192516.05 | J21: =J18-(J16+J6) -> -85399.667 | K21: =K18-(K16+K6) -> -121243.15 | L21: =L18-(L16+L6) -> 158533 | M21: =M18-(M16+M6) -> 252437.47 | ... AB21: =AB18-(AB16+AB6) -> 0
D23: Opening Balance | F23: 1 | G23: =F25 -> -149170.6 | H23: =G25 -> -215929.8 | I23: =H25 -> -349103 | J23: =I25 -> -541619.05 | K23: =J25 -> -627018.72 | L23: =K25 -> -748261.87 | M23: =L25 -> -589728.87 | N23: =M25 -> -337291.4 | ... AB23: =AA25 -> 1611517
D25: Closing Balance | F25: =F21+F23 -> -149170.6 | G25: =G23+G21 -> -215929.8 | H25: =H23+H21 -> -349103 | I25: =I23+I21 -> -541619.05 | J25: =J23+J21 -> -627018.72 | K25: =K23+K21 -> -748261.87 | L25: =L23+L21 -> -589728.87 | M25: =M23+M21 -> -337291.4 | N25: =N23+N21 -> -271689.87 | ... AB25: =AB23+AB21 -> 1611517
N28: Total Sales | Q28: =AP17 -> 3595739.2 | U28: =sum(F6:Q6) -> 240000 | X28: Wages
N31: (Product Costs) | Q31: =AP18 -> 1744223.2
N32: Total Costs | Q32: =AP18+U28 -> 1984223.2 | U32: =Q28-Q32 -> 1611516 | X32: Gross Product Margin
N37: Product Costs as a % of Sales | Q37: =AQ18 -> 0.48508056 | U37: =U28/Q28 -> 0.066745664 | X37: Wages as a % of Sales
D54: Off Peak
D55: Peak
D56: Normal
